Workbook
Name __xlfn_IFERROR: #N/A
Name Excel_BuiltIn__FilterDatabase: 'Feira Santana'!$A$15:$Q$235

Sheet Custo por transação
B2: Levantamento das Receitas e Custos Transacionais (Jun a Ago/23)
B4: Receitas Médias por Transações
B6: Mês | C6: Transações | D6: Fatur. Bruto | E6: Receita Bruta | F6: Fat./Trans. | G6: Rec./Trans. | H6: Rec. %
B7: 45078 | C7: 675712 | D7: 15995584 | E7: =#REF! -> #REF! | F7: =D7/C7 -> 23.672192 | G7: =E7/C7 -> #REF! | H7: =E7/D7 -> #REF!
B8: 45108 | C8: 751665 | D8: 17966884 | E8: =#REF! -> #REF! | F8: =D8/C8 -> 23.902781 | G8: =E8/C8 -> #REF! | H8: =E8/D8 -> #REF!
B9: 45139 | C9: 851310 | D9: 20565837 | E9: =#REF! -> #REF! | F9: =D9/C9 -> 24.157871 | G9: =E9/C9 -> #REF! | H9: =E9/D9 -> #REF!
B10: Total | C10: =SUM(C7:C9) -> 2278687 | D10: =SUM(D7:D9) -> 54528305 | E10: =SUM(E7:E9) -> #REF! | F10: =D10/C10 -> 23.929704 | G10: =E10/C10 -> #REF! | H10: =E10/D10 -> #REF!
B12: Custos Diretos por Transações*
B14: Mês | C14: Transações | D14: Des. Financ.** | E14: Impostos Dir. | F14: Total | G14: Custo Dir/Trans. | H14: Custo %
B15: =B7 -> 45078 | C15: =C7 -> 675712 | D15: =#REF!+#REF! -> #REF! | E15: =#REF!+E57 -> #REF! | F15: =SUM(D15:E15) -> #REF! | G15: =F15/C15 -> #REF! | H15: =F15/D7 -> #REF!
B16: =B8 -> 45108 | C16: =C8 -> 751665 | D16: =#REF!+#REF! -> #REF! | E16: =#REF!+E58 -> #REF! | F16: =SUM(D16:E16) -> #REF! | G16: =F16/C16 -> #REF! | H16: =F16/D8 -> #REF!
B17: =B9 -> 45139 | C17: =C9 -> 851310 | D17: =#REF!+#REF! -> #REF! | E17: =#REF!+E59 -> #REF! | F17: =SUM(D17:E17) -> #REF! | G17: =F17/C17 -> #REF! | H17: =F17/D9 -> #REF!
B18: Total | C18: =SUM(C15:C17) -> 2278687 | D18: =SUM(D15:D17) -> #REF! | E18: =SUM(E15:E17) -> #REF! | F18: =SUM(F15:F17) -> #REF! | G18: =F18/C18 -> #REF! | H18: =F18/D10 -> #REF!
B19: *ISS ajustado para 5% sobre receita bruta
B20: ** Inclui estornos financeiros e chargeback
B22: Custos Indiretos por Transações
B24: Mês | C24: Transações | D24: Infra de Sistemas | E24: Chips Tim | F24: Delivery | G24: Total | H24: Custo Ind./Trans. | I24: Custo %
B25: =B15 -> 45078 | C25: =C15 -> 675712 | D25: =F51 -> #REF! | E25: =#REF! -> #REF! | F25: =#REF! -> #REF! | G25: =SUM(D25:F25) -> #REF! | H25: =G25/C25 -> #REF! | I25: =G25/D7 -> #REF!
B26: =B16 -> 45108 | C26: =C16 -> 751665 | D26: =G51 -> #REF! | E26: =#REF! -> #REF! | F26: =#REF! -> #REF! | G26: =SUM(D26:F26) -> #REF! | H26: =G26/C26 -> #REF! | I26: =G26/D8 -> #REF!
B27: =B17 -> 45139 | C27: =C17 -> 851310 | D27: =H51 -> #REF! | E27: =#REF! -> #REF! | F27: =#REF! -> #REF! | G27: =SUM(D27:F27) -> #REF! | H27: =G27/C27 -> #REF! | I27: =G27/D9 -> #REF!
B28: Total | C28: =SUM(C25:C27) -> 2278687 | D28: =SUM(D25:D27) -> #REF! | E28: =SUM(E25:E27) -> #REF! | F28: =SUM(F25:F27) -> #REF! | G28: =SUM(G25:G27) -> #REF! | H28: =G28/C28 -> #REF! | I28: =G28/D10 -> #REF!
B30: Custos Administrativos por transação
B32: Mês | C32: Transações | D32: Pessoal* | E32: Viagens | F32: Marketing | G32: Outros | H32: Total | I32: Adm/Trans. | J32: Custo %
B33: =B25 -> 45078 | C33: =C25 -> 675712 | D33: =#REF!+#REF!-#REF! -> #REF! | E33: =#REF! -> #REF! | F33: =#REF! -> #REF! | G33: =#REF!-SUM(D33:F33)-F15-G25 -> #REF! | H33: =SUM(D33:G33) -> #REF! | I33: =H33/C33 -> #REF! | J33: =H33/D7 -> #REF!
B34: =B26 -> 45108 | C34: =C26 -> 751665 | D34: =#REF!+#REF!-#REF! -> #REF! | E34: =#REF! -> #REF! | F34: =#REF! -> #REF! | G34: =#REF!-SUM(D34:F34)-F16-G26 -> #REF! | H34: =SUM(D34:G34) -> #REF! | I34: =H34/C34 -> #REF! | J34: =H34/D8 -> #REF!
B35: =B27 -> 45139 | C35: =C27 -> 851310 | D35: =#REF!+#REF!-#REF! -> #REF! | E35: =#REF! -> #REF! | F35: =#REF! -> #REF! | G35: =#REF!-SUM(D35:F35)-F17-G27 -> #REF! | H35: =SUM(D35:G35) -> #REF! | I35: =H35/C35 -> #REF! | J35: =H35/D9 -> #REF!
B36: Total | C36: =SUM(C33:C35) -> 2278687 | D36: =SUM(D33:D35) -> #REF! | E36: =SUM(E33:E35) -> #REF! | F36: =SUM(F33:F35) -> #REF! | G36: =SUM(G33:G35) -> #REF! | H36: =SUM(D36:G36) -> #REF! | I36: =H36/C36 -> #REF! | J36: =H36/D10 -> #REF!
B37: * Inclui Pjs e Body shop e rateio com BIG
F40: 45078 | G40: 45108 | H40: 45139
B41: Sotwares e Licenças de Uso | F41: =#REF! -> #REF! | G41: =#REF! -> #REF! | H41: =#REF! -> #REF!
B42: =#REF! -> #REF! | F42: =#REF! -> #REF! | G42: =#REF! -> #REF! | H42: =#REF! -> #REF!
B43: =#REF! -> #REF! | F43: =#REF! -> #REF! | G43: =#REF! -> #REF! | H43: =#REF! -> #REF!
B44: =#REF! -> #REF! | F44: =#REF! -> #REF! | G44: =#REF! -> #REF! | H44: =#REF! -> #REF!
B45: =#REF! -> #REF! | F45: =#REF! -> #REF! | G45: =#REF! -> #REF! | H45: =#REF! -> #REF!
B46: =#REF! -> #REF! | F46: =#REF! -> #REF! | G46: =#REF! -> #REF! | H46: =#REF! -> #REF!
B47: =#REF! -> #REF! | F47: =#REF! -> #REF! | G47: =#REF! -> #REF! | H47: =#REF! -> #REF!
B48: =#REF! -> #REF! | F48: =#REF! -> #REF! | G48: =#REF! -> #REF! | H48: =#REF! -> #REF!
B49: =#REF! -> #REF! | F49: =#REF! -> #REF! | G49: =#REF! -> #REF! | H49: =#REF! -> #REF!
B50: =#REF! -> #REF! | F50: =#REF! -> #REF! | G50: =#REF! -> #REF! | H50: =#REF! -> #REF!
B51: Total | F51: =SUM(F41:F50) -> #REF! | G51: =SUM(G41:G50) -> #REF! | H51: =SUM(H41:H50) -> #REF!
B56: Ajuste ISS | C56: Devido | D56: Pago | E56: Diferença
B57: =B15 -> 45078 | C57: =E7*5% -> #REF! | D57: 5604 | E57: =C57-D57 -> #REF!
B58: =B16 -> 45108 | C58: =E8*5% -> #REF! | D58: 5604 | E58: =C58-D58 -> #REF!
B59: =B17 -> 45139 | C59: =E9*5% -> #REF! | D59: 5604 | E59: =C59-D59 -> #REF!
B60: Resumo das Receitas e Custos Transacionais
E61: Por Transação | F61: % s/ Fatur.
B62: Entradas
B63: Faturamento Médio por Transação | E63: =F10 -> 23.929704
B64: Receita Média por Transação | E64: =G10 -> #REF! | F64: =H10 -> #REF!
B66: Saídas
B67: Custos Diretos
B68: Despesas Financeiras | E68: =D18/C18 -> #REF! | F68: =D18/D10 -> #REF!
B69: Impostos Diretos | E69: =E18/C18 -> #REF! | F69: =E18/D10 -> #REF!
B70: Total Custos Diretos | E70: =G18 -> #REF! | F70: =H18 -> #REF!
B71: Custos Indiretos
B72: Infraestrutura de Sistemas | E72: =D28/C28 -> #REF! | F72: =D28/D10 -> #REF!
B73: Chips TIM | E73: =E28/C28 -> #REF! | F73: =E28/D10 -> #REF!
B74: Delivery de Cartões | E74: =F28/C28 -> #REF! | F74: =F28/D10 -> #REF!
B75: Total Custos Indiretos | E75: =H28 -> #REF! | F75: =I28 -> #REF!
B76: Custos Administrativos
B77: Pessoal | E77: =D36/C36 -> #REF! | F77: =D36/D10 -> #REF!
B78: Viagens | E78: =E36/C36 -> #REF! | F78: =E36/D10 -> #REF!
B79: Marketing | E79: =F36/C36 -> #REF! | F79: =F36/D10 -> #REF!
B80: Outros | E80: =G36/C36 -> #REF! | F80: =G36/D10 -> #REF!
B81: Total Custos Admnistrativos | E81: =I36 -> #REF! | F81: =J36 -> #REF!
B83: Receita | E83: =F64 -> #REF!
B84: Custos Diretos | E84: =-F70 -> #REF!
B85: Sub-Total | E85: =SUM(E83:E84) -> #REF!
B86: Custos Indiretos | E86: =-F75 -> #REF!
B87: Sub-Total | E87: =SUM(E85:E86) -> #REF!
B88: Custos Administrativos | E88: =-F81 -> #REF!
B89: Sub-Total | E89: =SUM(E87:E88) -> #REF!

Sheet Cargos e Tarefas

Sheet Custos
B2: FIXO | G2: VARIAVEL | L2: DIVIDA FORNECEDORES
B4: DIA VENCIMENTO | C4: ORIGEM | D4: VALOR | G4: DIA VENCIMENTO | H4: ORIGEM | I4: VALOR | L4: Mês | M4: Valor
B5: Dia 5 | C5: Despesas Pessoal | D5: 9779 | G5: Dia 10 | H5: Cartão de credito | I5: 5000 | L5: 46023 | M5: =24124 -> 24124
B6: Dia 5 | C6: Retirada (prolabore) | D6: 17000 | G6: Diariamente | H6: Materia prima | I6: 0 | L6: 46054 | M6: ='PLANO ORÇAMENTARIO - VIP'!E15 -> 217067.97
B7: Dia 30 | C7: Consultoria Financeira | D7: 1000 | G7: Dia 10 | H7: Marketing | I7: 3000 | L7: 46082 | M7: ='PLANO ORÇAMENTARIO - VIP'!G15 -> 176833.13
B8: Dia 20 | C8: Consultoria Contabil | D8: 600 | G8: Dia 20 | H8: Impostos | I8: 35000 | L8: 46113 | M8: ='PLANO ORÇAMENTARIO - VIP'!I15 -> 91175.7
B9: Dia 10 | C9: Aluguel + Condominio | D9: 2150 | G9: Diariamente | H9: Taxas das plataformas | I9: 0 | L9: 46143 | M9: ='PLANO ORÇAMENTARIO - VIP'!K15 -> 48922.88
B10: Dia 10 | C10: Luz | D10: 850 | G10: Diariamente | H10: Cancelamentos e reembolsos | I10: 0 | L10: 46174 | M10: ='PLANO ORÇAMENTARIO - VIP'!M15 -> 21761.12
B11: Dia 10 | C11: Agua | D11: 250 | I11: =SUM(I5:I10) -> 43000 | L11: 46204 | M11: ='PLANO ORÇAMENTARIO - VIP'!O15 -> 0
B12: Dia 20 | C12: Bling | D12: 450 | L12: Total: | M12: =SUM(M5:M11) -> 579884.8
B13: Dia 5 | C13: Despesas de venda | D13: 2000
B14: Dia 15 | C14: Financiamento Pronamp | D14: 6602
D15: =SUM(D5:D14) -> 40681
B18: Fornecedores
B19: Nome | C19: Contato | D19: Telefone | E19: Email

Sheet Resumo Gerencial
B5: RESULTADO GRUPO VIP 01-2026 A 12-2026
B7: Empresa | C7: 46023 | D7: 46054 | E7: 46082 | F7: 46113 | G7: 46143 | H7: 46174 | I7: 46204 | J7: 46235 | K7: 46266 | L7: 46296 | M7: 46327 | N7: 46357
B8: Vip | C8: ='PLANO ORÇAMENTARIO - VIP'!D24 -> -4409.78 | D8: ='PLANO ORÇAMENTARIO - VIP'!F24 -> -26198.19 | E8: ='PLANO ORÇAMENTARIO - VIP'!H24 -> -18203.49 | F8: ='PLANO ORÇAMENTARIO - VIP'!J24 -> 136391.74 | G8: ='VIP MX'!G273 -> 0 | H8: ='VIP MX'!H273 -> 0 | I8: ='VIP MX'!I273 -> 0 | J8: ='VIP MX'!J273 -> 0 | K8: ='VIP MX'!K273 -> 0 | L8: ='VIP MX'!L273 -> 0 | M8: ='VIP MX'!M273 -> 0 | N8: ='VIP MX'!N273 -> 0
B9: Vidal | C9: ='PLANO ORÇAMENTARIO - VIDAL'!D24 -> 125409.35 | D9: ='PLANO ORÇAMENTARIO - VIDAL'!F24 -> 80362 | E9: ='PLANO ORÇAMENTARIO - VIDAL'!H24 -> 127304.9 | F9: ='PLANO ORÇAMENTARIO - VIDAL'!J24 -> 115201.03 | G9: =VIDAL!G275 -> 0 | H9: =VIDAL!H275 -> 0 | I9: =VIDAL!I275 -> 0 | J9: =VIDAL!J275 -> 0 | K9: =VIDAL!K275 -> 0 | L9: =VIDAL!L275 -> 0 | M9: =VIDAL!M275 -> 0 | N9: =VIDAL!N275 -> 0
B10: V3 | C10: ='PLANO ORÇAMENTARIO - V3'!D22 -> 2128 | D10: ='PLANO ORÇAMENTARIO - V3'!F22 -> 2771.72 | E10: ='PLANO ORÇAMENTARIO - V3'!H22 -> 2707.46 | F10: ='PLANO ORÇAMENTARIO - V3'!I22 -> 2739.1 | G10: ='V3'!G275 -> 0 | H10: ='V3'!H275 -> 0 | I10: ='V3'!I275 -> 0 | J10: ='V3'!J275 -> 0 | K10: ='V3'!K275 -> 0 | L10: ='V3'!L275 -> 0 | M10: ='V3'!M275 -> 0 | N10: ='V3'!N275 -> 0
B11: Resultado | C11: =C8+C9+C10 -> 123127.57 | D11: =D8+D9+D10 -> 56935.53 | E11: =E8+E9+E10 -> 111808.87 | F11: =F8+F9+F10 -> 254331.87 | G11: =G8+G9+G10 -> 0 | H11: =H8+H9+H10 -> 0 | I11: =I8+I9+I10 -> 0 | J11: =J8+J9+J10 -> 0 | ... N11: =N8+N9+N10 -> 0

Sheet PLANO ORÇAMENTARIO - VIP
A1: VIP MX | C1: Previsto | D1: Realizado | E1: Previsto | F1: Realizado | G1: Previsto | H1: Realizado | I1: Previsto | J1: Realizado | K1: Previsto | L1: Realizado | M1: Previsto | N1: Realizado | O1: Previsto | P1: Realizado | Q1: Previsto | R1: Realizado | S1: Previsto | T1: Realizado | U1: Previsto | V1: Realizado | W1: Previsto | X1: Realizado | Y1: Previsto | Z1: Realizado
C2: 46023 | D2: 46023 | E2: 46054 | F2: 46054 | G2: 46082 | H2: 46082 | I2: 46113 | J2: 46113 | K2: 46143 | L2: 46143 | M2: 46174 | N2: 46174 | O2: 46204 | P2: 46204 | Q2: 46235 | R2: 46235 | S2: 46266 | T2: 46266 | U2: 46296 | V2: 46296 | W2: 46327 | X2: 46327 | Y2: 46357 | Z2: 46357
A3: Receita Bruta | C3: =SUM(C4:C7) -> 266500 | D3: =SUM(D4:D7) -> 435355.47 | E3: =SUM(E4:E7) -> 266500 | F3: =SUM(F4:F7) -> 363193.79 | G3: =SUM(G4:G7) -> 263000 | H3: =SUM(H4:H7) -> 446257.54 | I3: =SUM(I4:I7) -> 293150 | J3: =SUM(J4:J7) -> 545913.33 | ... Z3: =SUM(Z4:Z7) -> 0
A4: VENDAS MERCADO LIVRE - VIP MX | C4: 260000 | D4: 413271.86 | E4: 260000 | F4: 347450.9 | G4: 260000 | H4: 412851.33 | I4: 286000 | J4: =507580.01 -> 507580.01 | K4: 286000 | M4: 286000
A5: VENDAS AMAZON - VIP MX | C5: 3500 | D5: 10223.04 | E5: 3500 | F5: 0 | G5: 0 | I5: 3850 | K5: 3850 | M5: 3850
A6: VENDAS SHOPEE - VIP MX | C6: 3000 | D6: 11860.57 | E6: 3000 | F6: 15742.89 | G6: 3000 | H6: 33406.21 | I6: 3300 | J6: 38333.32 | K6: 3300 | M6: 3300
A7: RENDIMENTOS | C7: 0 | D7: 0 | E7: 0 | G7: 0 | I7: =G7*0.1+G7 -> 0 | K7: 0 | M7: 0
A10: (-) Despesas do Negócio | C10: =SUM(C11:C23) -> 395348.93 | D10: =SUM(D11:D23) -> 439765.25 | E10: =SUM(E11:E23) -> 343180.71 | F10: =SUM(F11:F23) -> 389391.98 | G10: =SUM(G11:G23) -> 301860.87 | H10: =SUM(H11:H23) -> 464461.03 | I10: =SUM(I11:I23) -> 228299.94 | J10: =SUM(J11:J23) -> 409521.59 | ... Z10: =SUM(Z11:Z23) -> 0
A11: Despesas de pessoal | C11: =1788.08+2195.77+2244.39 -> 6228.24 | D11: =1788.08+2195.77+2244.39+547.99+877.48 -> 7653.71 | E11: =1899+2240.5+1647.2+467.48+791.56 -> 7045.74 | F11: =1788.08+2195.77+1690.53+845.22+499.17 -> 7018.77 | G11: =1899+2240.5+1647.2+467.48+791.56 -> 7045.74 | H11: =2156.17+2195.77+1690.53+531.53+881.63 -> 7455.63 | I11: =1899+2240.5+1647.2+467.48+791.56 -> 7045.74 | J11: =2156.17+3181.6+1690.53+961.58+595.16 -> 8585.04 | K11: =1899+2240.5+1647.2+467.48+791.56 -> 7045.74 | M11: =1899+2240.5+1647.2+467.48+791.56 -> 7045.74
A12: Consultorias e acessorias | C12: =1000+600 -> 1600 | D12: =1000+600 -> 1600 | E12: =1000+600 -> 1600 | F12: =1000+1140 -> 2140 | G12: =1000+600 -> 1600 | H12: =1000+600 -> 1600 | I12: =1000+600 -> 1600 | J12: =1000+640 -> 1640 | K12: =1000+600 -> 1600 | M12: =1000+600 -> 1600
A13: Despesas gerais | C13: 0 | D13: 0 | E13: 0 | F13: 0 | G13: 0 | H13: 0 | I13: 0 | J13: 0 | K13: 0 | L13: 0 | M13: 0 | N13: 0
A14: Tecnologia | C14: 250 | D14: 250 | E14: 250 | F14: 250 | G14: 250 | H14: 250 | I14: 250 | J14: 250 | K14: 250 | M14: 250
A15: Despesas de materia prima | C15: =239024.48+24129.21 -> 263153.69 | D15: 252772.95 | E15: 217067.97 | F15: 228525.11 | G15: 176833.13 | H15: 268703.5 | I15: 91175.7 | J15: 223982.07 | K15: 48922.88 | M15: 21761.12
A16: Despesas de vendas | C16: 2000 | D16: =657.97+697.86 -> 1355.83 | E16: 2000 | F16: 0 | G16: 2000 | H16: =772.85+481.63+508.39 -> 1762.87 | I16: 2000 | J16: =1281.55 -> 1281.55 | K16: 2000 | M16: 2000
A17: Despesas de marketing | C17: 3000 | D17: 0 | E17: 3000 | F17: 0 | G17: 3000 | H17: 0 | I17: 3250 | K17: 3250 | M17: 3250
A18: Impostos Retido de Terceiro | C18: 0 | D18: 0 | E18: 0 | F18: 0 | G18: 0 | I18: 0 | K18: 0 | M18: 0
A19: Impostos | C19: =C4*0.115 -> 29900 | D19: =494.65+28007.24+4855.54 -> 33357.43 | E19: 23000 | F19: =25286.06+1261.89 -> 26547.95 | G19: 23000 | H19: =31526.88+3684.03 -> 35210.91 | I19: 25500 | J19: =37578.42+2450.02 -> 40028.44 | K19: 25500 | M19: 25500
A20: Despesas financeiras | C20: 0 | D20: 0 | E20: 0 | F20: 0 | G20: 0 | I20: 0 | K20: 0 | M20: 0
A21: Taxas plataforma | C21: =(C4+C5+C6)*0.26 -> 69290 | D21: 100405.73 | E21: =(E4+E5+E6)*0.26 -> 69290 | F21: =85892.13 -> 85892.13 | G21: =(G4+G5+G6)*0.26 -> 68380 | H21: 105426.96 | I21: =(I4+I5+I6)*0.26 -> 76219 | J21: 78212.99 | K21: =(K4+K5+K6)*0.26 -> 76219 | M21: =(M4+M5+M6)*0.26 -> 76219
A22: Cancelamentos e Remmbolso | C22: =(C4+C5+C6)*0.05 -> 13325 | D22: 35767.6 | E22: =(E4+E5+E6)*0.05 -> 13325 | F22: =32416.02 -> 32416.02 | G22: =(G4+G5+G6)*0.05 -> 13150 | H22: 37449.16 | I22: =(I4+I5+I6)*0.05 -> 14657.5 | J22: 48939.5 | K22: =(K4+K5+K6)*0.05 -> 14657.5 | M22: =(M4+M5+M6)*0.05 -> 14657.5
A23: Financiamentos | C23: 6602 | D23: 6602 | E23: 6602 | F23: 6602 | G23: 6602 | H23: 6602 | I23: 6602 | J23: 6602 | K23: 6602 | M23: 6602
A24: Resultado | C24: =C3-C10 -> -128848.93 | D24: =D3-D10 -> -4409.78 | E24: =E3-E10 -> -76680.71 | F24: =F3-F10 -> -26198.19 | G24: =G3-G10 -> -38860.87 | H24: =H3-H10 -> -18203.49 | I24: =I3-I10 -> 64850.06 | J24: =J3-J10 -> 136391.74 | ... Z24: =Z3-Z10 -> 0
G41: =6*15 -> 90

Sheet PLANO ORÇAMENTARIO - VIDAL
A1: VIDAL | C1: Previsto | D1: Realizado | E1: Previsto | F1: Realizado | G1: Previsto | H1: Realizado | I1: Previsto | J1: Realizado | K1: Previsto | L1: Realizado | M1: Previsto | N1: Realizado | O1: Previsto | P1: Realizado | Q1: Previsto | R1: Realizado | S1: Previsto | T1: Realizado | U1: Previsto | V1: Realizado | W1: Previsto | X1: Realizado | Y1: Previsto | Z1: Realizado
C2: 46023 | D2: 46023 | E2: 46054 | F2: 46054 | G2: 46082 | H2: 46082 | I2: 46113 | J2: 46113 | K2: 46143 | L2: 46143 | M2: 46174 | N2: 46174 | O2: 46204 | P2: 46204 | Q2: 46235 | R2: 46235 | S2: 46266 | T2: 46266 | U2: 46296 | V2: 46296 | W2: 46327 | X2: 46327 | Y2: 46357 | Z2: 46357
A3: Receita Bruta | C3: =SUM(C4:C7) -> 207000 | D3: =SUM(D4:D7) -> 196570.68 | E3: =SUM(E4:E7) -> 207000 | F3: =SUM(F4:F7) -> 167144.26 | G3: =SUM(G4:G7) -> 207000 | H3: =SUM(H4:H7) -> 229018.47 | I3: =SUM(I4:I7) -> 227700 | J3: =SUM(J4:J7) -> 251047.64 | ... Z3: =SUM(Z4:Z7) -> 0
A4: VENDAS LOJA FISICA | C4: 50000 | D4: 44021.86 | E4: 50000 | F4: 29797.32 | G4: 50000 | H4: 56728.92 | I4: 55000 | J4: 58148.23 | K4: 55000 | M4: 55000 | O4: =M4*0.06+M4 -> 58300
A5: VENDAS MERCADO LIVRE - VIDAL | C5: 155000 | D5: 138853.28 | E5: 155000 | F5: 120539.51 | G5: 155000 | H5: 144159.46 | I5: 170500 | J5: =167726.63+2481.96 -> 170208.59 | K5: 170500 | M5: 170500 | O5: =M5*0.06+M5 -> 180730
A6: VENDAS SHOPEE - VIDAL | C6: 2000 | D6: 13695.54 | E6: 2000 | F6: 16807.43 | G6: 2000 | H6: 28130.09 | I6: 2200 | J6: 22690.82 | K6: 2200 | M6: 2200 | O6: =M6*0.06+M6 -> 2332
A7: RENDIMENTOS | C7: 0 | D7: 0 | E7: 0 | G7: 0 | I7: =G7*0.1+G7 -> 0 | K7: 0 | M7: 0 | O7: =M7*0.06+M7 -> 0
A10: (-) Despesas do Negócio | C10: =SUM(C11:C23) -> 182853.5 | D10: =SUM(D11:D23) -> 71161.33 | E10: =SUM(E11:E23) -> 182853.5 | F10: =SUM(F11:F23) -> 86782.26 | G10: =SUM(G11:G23) -> 182853.5 | H10: =SUM(H11:H23) -> 101713.57 | I10: =SUM(I11:I23) -> 194013.91 | J10: =SUM(J11:J23) -> 135846.61 | ... Z10: =SUM(Z11:Z23) -> 0
A11: Despesas de pessoal | C11: =20000+2240.5+493 -> 22733.5 | D11: =17000+178.31 -> 17178.31 | E11: =20000+2240.5+493 -> 22733.5 | F11: =17000+178.31 -> 17178.31 | G11: =20000+2240.5+493 -> 22733.5 | H11: =17000+178.31+800 -> 17978.31 | I11: =17000+178.31+1098.6 -> 18276.91 | J11: =17000+178.31+1098.6 -> 18276.91 | K11: =17000+178.31+1831 -> 19009.31 | M11: =17000+178.31+1831 -> 19009.31 | O11: =17000+178.31+1831 -> 19009.31
A12: Consultorias e acessorias | C12: 0 | D12: 0 | E12: 0 | F12: 0 | G12: 0 | H12: 0 | I12: 0 | J12: 0 | K12: 0 | L12: 0 | M12: 0 | N12: 0 | O12: 0 | P12: 0
A13: Despesas gerais | C13: =2150+850+250+5000 -> 8250 | D13: =2150+857.07+250+2795.79 -> 6052.86 | E13: =2150+850+250+5000 -> 8250 | F13: =2150+850+250+3000+1000+1822.82 -> 9072.82 | G13: =2150+850+250+5000 -> 8250 | H13: =1100+826.94+250+2844.98 -> 5021.92 | I13: =2150+850+250+5000 -> 8250 | J13: =2100+826.94+250+3393.01+161.39 -> 6731.34 | K13: =2150+850+250+5000 -> 8250 | M13: =2150+850+250+5000 -> 8250 | O13: =2150+850+250+5000 -> 8250
A14: Tecnologia | C14: 200 | D14: 200 | E14: 200 | F14: 200 | G14: 200 | H14: =200+500 -> 700 | I14: =200+250 -> 450 | J14: =200+250+149 -> 599 | K14: 200 | M14: 200 | O14: 200
A15: Despesas de materia prima | C15: 90000 | D15: 0 | E15: 90000 | F15: 3059.34 | G15: 90000 | H15: 10570.07 | I15: 98000 | J15: 30495.45 | K15: 98000 | M15: 98000 | O15: 105000
A16: Despesas de vendas | C16: 0 | D16: 0 | E16: 0 | F16: 0 | G16: 0 | H16: 0 | I16: 0 | J16: 0 | K16: 0 | L16: 0 | M16: 0 | N16: 0 | O16: 0 | P16: 0
A17: Despesas de marketing | C17: 0 | D17: 0 | E17: 0 | F17: 0 | G17: 0 | H17: 440 | I17: 0 | J17: 500 | K17: 0 | L17: 0 | M17: 0 | N17: 0 | O17: 0 | P17: 0
A18: Impostos Retido de Terceiro | C18: 0 | D18: 0 | E18: 0 | G18: 0 | H18: 0 | I18: 0 | K18: 0 | M18: 0 | O18: 0
A19: Impostos | C19: 13000 | D19: 8842.69 | E19: 13000 | F19: =68.72+8852.98 -> 8921.7 | G19: 13000 | H19: 10958.27 | I19: 15500 | J19: 11197.46 | K19: 15500 | M19: 15500 | O19: 18900
A20: Despesas financeiras | C20: 0 | D20: 0 | E20: 0 | G20: 0 | H20: 0 | I20: 0 | K20: 0 | M20: 0 | O20: 0
A21: Taxas plataforma | C21: =(C5+C6)*0.26 -> 40820 | D21: 22834.91 | E21: =(E5+E6)*0.26 -> 40820 | F21: 32636.18 | G21: =(G5+G6)*0.26 -> 40820 | H21: 39540.71 | I21: =(I5+I6)*0.26 -> 44902 | J21: =25220.26+20695.89 -> 45916.15 | K21: =(K5+K6)*0.26 -> 44902 | M21: =(M5+M6)*0.26 -> 44902 | O21: =(O5+O6)*0.26 -> 47596.12
A22: Cancelamentos e Remmbolso | C22: =(C5+C6)*0.05 -> 7850 | D22: 16052.56 | E22: =(E5+E6)*0.05 -> 7850 | F22: 15713.91 | G22: =(G5+G6)*0.05 -> 7850 | H22: 16504.29 | I22: =(I5+I6)*0.05 -> 8635 | J22: =22130.3 -> 22130.3 | K22: =(K5+K6)*0.05 -> 8635 | M22: =(M5+M6)*0.05 -> 8635 | O22: =(O5+O6)*0.05 -> 9153.1
A23: Financiamentos | C23: 0 | D23: 0 | E23: 0 | F23: 0 | G23: 0 | H23: 0 | I23: 0 | J23: 0 | K23: 0 | L23: 0 | M23: 0 | N23: 0 | O23: 0 | P23: 0
A24: Resultado | C24: =C3-C10 -> 24146.5 | D24: =D3-D10 -> 125409.35 | E24: =E3-E10 -> 24146.5 | F24: =F3-F10 -> 80362 | G24: =G3-G10 -> 24146.5 | H24: =H3-H10 -> 127304.9 | I24: =I3-I10 -> 33686.09 | J24: =J3-J10 -> 115201.03 | ... Z24: =Z3-Z10 -> 0

Sheet PLANO ORÇAMENTARIO - V3
A1: V3 | C1: Previsto | D1: Realizado | E1: Previsto | F1: Realizado | G1: Previsto | H1: Realizado | I1: Previsto | J1: Realizado | K1: Previsto | L1: Realizado | M1: Previsto | N1: Realizado | O1: Previsto | P1: Realizado | Q1: Previsto | R1: Realizado | S1: Previsto | T1: Realizado | U1: Previsto | V1: Realizado | W1: Previsto | X1: Realizado | Y1: Previsto | Z1: Realizado
C2: 46023 | D2: 46023 | E2: 46054 | F2: 46054 | G2: 46082 | H2: 46082 | I2: 46113 | J2: 46113 | K2: 46143 | L2: 46143 | M2: 46174 | N2: 46174 | O2: 46204 | P2: 46204 | Q2: 46235 | R2: 46235 | S2: 46266 | T2: 46266 | U2: 46296 | V2: 46296 | W2: 46327 | X2: 46327 | Y2: 46357 | Z2: 46357
A3: Receita Bruta | C3: =SUM(C4:C5) -> 7500 | D3: =SUM(D4:D5) -> 2706 | E3: =SUM(E4:E5) -> 7500 | F3: =SUM(F4:F5) -> 3774.1 | G3: =SUM(G4:G5) -> 7500 | H3: =SUM(H4:H5) -> 3913 | I3: =SUM(I4:I5) -> 3913 | J3: =SUM(J4:J5) -> 3918 | ... Z3: =SUM(Z4:Z5) -> 0
A4: VENDAS MERCADO LIVRE - V3 | C4: 7500 | D4: 2706 | E4: 7500 | F4: =3556.2+217.9 -> 3774.1 | G4: 7500 | H4: 3913 | I4: 3913 | J4: 3918 | K4: 8250 | M4: 8250 | O4: =M4*0.06+M4 -> 8745
A5: RENDIMENTOS | C5: 0 | D5: 0 | E5: 0 | G5: 0 | I5: =G5*0.1+G5 -> 0 | K5: 0 | M5: 0 | O5: =M5*0.06+M5 -> 0 | Q5: 0 | S5: 0 | U5: =S5*0.05+S5 -> 0 | W5: 0 | Y5: 0 | Z5: 0
A8: (-) Despesas do Negócio | C8: =SUM(C9:C21) -> 2250 | D8: =SUM(D9:D21) -> 578 | E8: =SUM(E9:E21) -> 2250 | F8: =SUM(F9:F21) -> 1002.38 | G8: =SUM(G9:G21) -> 2250 | H8: =SUM(H9:H21) -> 1205.54 | I8: =SUM(I9:I21) -> 1173.9 | J8: =SUM(J9:J21) -> 1404.5 | ... Z8: =SUM(Z9:Z21) -> 0
A9: Despesas de pessoal | C9: 0 | D9: 0 | E9: 0 | F9: 0 | G9: 0 | H9: 0 | I9: 0 | J9: 0 | K9: 0 | L9: 0 | M9: 0 | N9: 0 | O9: 0 | P9: 0 | Q9: 0 | R9: 0 | S9: 0 | T9: 0 | U9: 0 | V9: 0 | W9: 0 | X9: 0 | Y9: 0 | Z9: 0
A10: Consultorias e acessorias | C10: 0 | D10: 0 | E10: 0 | F10: 0 | G10: 0 | H10: 0 | I10: 0 | J10: 0 | K10: 0 | L10: 0 | M10: 0 | N10: 0 | O10: 0 | P10: 0 | Q10: 0 | R10: 0 | S10: 0 | T10: 0 | U10: 0 | V10: 0 | W10: 0 | X10: 0 | Y10: 0 | Z10: 0
A11: Despesas gerais | C11: 0 | D11: 0 | E11: 0 | F11: 0 | G11: 0 | H11: 0 | I11: 0 | J11: 0 | K11: 0 | L11: 0 | M11: 0 | N11: 0 | O11: 0 | P11: 0 | Q11: 0 | R11: 0 | S11: 0 | T11: 0 | U11: 0 | V11: 0 | W11: 0 | X11: 0 | Y11: 0 | Z11: 0
A12: Tecnologia | C12: 0 | D12: 0 | E12: 0 | F12: 0 | G12: 0 | H12: 0 | I12: 0 | J12: 0 | K12: 0 | L12: 0 | M12: 0 | N12: 0 | O12: 0 | P12: 0 | Q12: 0 | R12: 0 | S12: 0 | T12: 0 | U12: 0 | V12: 0 | W12: 0 | X12: 0 | Y12: 0 | Z12: 0
A13: Despesas de materia prima | C13: 0 | D13: 0 | E13: 0 | F13: 0 | G13: 0 | H13: 0 | I13: 0 | J13: 0 | K13: 0 | L13: 0 | M13: 0 | N13: 0 | O13: 0 | P13: 0 | Q13: 0 | R13: 0 | S13: 0 | T13: 0 | U13: 0 | V13: 0 | W13: 0 | X13: 0 | Y13: 0 | Z13: 0
A14: Despesas de vendas | C14: 0 | D14: 0 | E14: 0 | F14: 0 | G14: 0 | H14: 0 | I14: 0 | J14: 0 | K14: 0 | L14: 0 | M14: 0 | N14: 0 | O14: 0 | P14: 0 | Q14: 0 | R14: 0 | S14: 0 | T14: 0 | U14: 0 | V14: 0 | W14: 0 | X14: 0 | Y14: 0 | Z14: 0
A15: Despesas de marketing | C15: 0 | D15: 0 | E15: 0 | F15: 0 | G15: 0 | H15: 0 | I15: 0 | J15: 0 | K15: 0 | L15: 0 | M15: 0 | N15: 0 | O15: 0 | P15: 0 | Q15: 0 | R15: 0 | S15: 0 | T15: 0 | U15: 0 | V15: 0 | W15: 0 | X15: 0 | Y15: 0 | Z15: 0
A16: Impostos Retido de Terceiro | C16: 0 | D16: 0 | E16: 0 | F16: 0 | G16: 0 | H16: 0 | I16: 0 | J16: 0 | K16: 0 | L16: 0 | M16: 0 | N16: 0 | O16: 0 | P16: 0 | Q16: 0 | R16: 0 | S16: 0 | T16: 0 | U16: 0 | V16: 0 | W16: 0 | X16: 0 | Y16: 0 | Z16: 0
A17: Impostos | C17: 0 | D17: 0 | E17: 0 | F17: 0 | G17: 0 | H17: 0 | I17: 0 | J17: 0 | K17: 0 | L17: 0 | M17: 0 | N17: 0 | O17: 0 | P17: 0 | Q17: 0 | R17: 0 | S17: 0 | T17: 0 | U17: 0 | V17: 0 | W17: 0 | X17: 0 | Y17: 0 | Z17: 0
A18: Despesas financeiras | C18: 0 | D18: 0 | E18: 0 | F18: 0 | G18: 0 | H18: 0 | I18: 0 | J18: 0 | K18: 0 | L18: 0 | M18: 0 | N18: 0 | O18: 0 | P18: 0 | Q18: 0 | R18: 0 | S18: 0 | T18: 0 | U18: 0 | V18: 0 | W18: 0 | X18: 0 | Y18: 0 | Z18: 0
A19: Taxas plataforma | C19: =C4*0.25 -> 1875 | D19: 578 | E19: =E4*0.25 -> 1875 | F19: 671.91 | G19: =G4*0.25 -> 1875 | H19: 1205.54 | I19: =I4*0.25 -> 978.25 | J19: 1118 | K19: =K4*0.25 -> 2062.5 | L19: 0 | M19: =M4*0.25 -> 2062.5 | N19: 0 | O19: =O4*0.25 -> 2186.25 | P19: 0 | Q19: =Q4*0.25 -> 0 | R19: 0 | S19: =S4*0.25 -> 0 | T19: 0 | U19: =U4*0.25 -> 0 | V19: 0 | W19: =W4*0.25 -> 0 | X19: 0 | Y19: =Y4*0.25 -> 0 | Z19: 0
A20: Cancelamentos e Remmbolso | C20: =C4*0.05 -> 375 | D20: 0 | E20: =E4*0.05 -> 375 | F20: 330.47 | G20: =G4*0.05 -> 375 | H20: 0 | I20: =I4*0.05 -> 195.65 | J20: 286.5 | K20: =K4*0.05 -> 412.5 | L20: 0 | M20: =M4*0.05 -> 412.5 | N20: 0 | O20: =O4*0.05 -> 437.25 | P20: 0 | Q20: =Q4*0.05 -> 0 | R20: 0 | S20: =S4*0.05 -> 0 | T20: 0 | U20: =U4*0.05 -> 0 | V20: 0 | W20: =W4*0.05 -> 0 | X20: 0 | Y20: =Y4*0.05 -> 0 | Z20: 0
A21: Financiamentos | C21: 0 | D21: 0 | E21: 0 | F21: 0 | G21: 0 | H21: 0 | I21: 0 | J21: 0 | K21: 0 | L21: 0 | M21: 0 | N21: 0 | O21: 0 | P21: 0 | Q21: 0 | R21: 0 | S21: 0 | T21: 0 | U21: 0 | V21: 0 | W21: 0 | X21: 0 | Y21: 0 | Z21: 0
A22: Resultado | C22: =C3-C8 -> 5250 | D22: =D3-D8 -> 2128 | E22: =E3-E8 -> 5250 | F22: =F3-F8 -> 2771.72 | G22: =G3-G8 -> 5250 | H22: =H3-H8 -> 2707.46 | I22: =I3-I8 -> 2739.1 | J22: =J3-J8 -> 2513.5 | ... Z22: =Z3-Z8 -> 0

Sheet Planilha1
A1: VIP MX | C1: Previsto | D1: Realizado | E1: Previsto | F1: Realizado | G1: Previsto | H1: Realizado | I1: Previsto | J1: Realizado | K1: Previsto | L1: Realizado | M1: Previsto | N1: Realizado | O1: Previsto | P1: Realizado | Q1: Previsto | R1: Realizado | S1: Previsto | T1: Realizado | U1: Previsto | V1: Realizado | W1: Previsto | X1: Realizado | Y1: Previsto | Z1: Realizado
C2: 46023 | D2: 46023 | E2: 46054 | F2: 46054 | G2: 46082 | H2: 46082 | I2: 46113 | J2: 46113 | K2: 46143 | L2: 46143 | M2: 46174 | N2: 46174 | O2: 46204 | P2: 46204 | Q2: 46235 | R2: 46235 | S2: 46266 | T2: 46266 | U2: 46296 | V2: 46296 | W2: 46327 | X2: 46327 | Y2: 46357 | Z2: 46357
A3: Receita Bruta | C3: =SUM(C4:C7) -> 266500 | D3: =SUM(D4:D7) -> 435355.47 | E3: =SUM(E4:E7) -> 266500 | F3: =SUM(F4:F7) -> 363193.79 | G3: =SUM(G4:G7) -> 263000 | H3: =SUM(H4:H7) -> 446257.54 | I3: =SUM(I4:I7) -> 293150 | J3: =SUM(J4:J7) -> 545913.33 | ... Z3: =SUM(Z4:Z7) -> 0
A4: VENDAS MERCADO LIVRE - VIP MX | C4: 260000 | D4: 413271.86 | E4: 260000 | F4: 347450.9 | G4: 260000 | H4: 412851.33 | I4: 286000 | J4: =507580.01 -> 507580.01 | K4: 286000 | M4: 286000 | O4: =M4*0.06+M4 -> 303160 | Q4: 303160 | S4: 303160 | U4: =S4*0.05+S4 -> 318318 | W4: 318318 | Y4: 318318 | Z4: 0
A5: VENDAS AMAZON - VIP MX | C5: 3500 | D5: 10223.04 | E5: 3500 | F5: 0 | G5: 0 | I5: 3850 | K5: 3850 | M5: 3850 | O5: =M5*0.06+M5 -> 4081 | Q5: 4081 | S5: 4081 | U5: =S5*0.05+S5 -> 4285.05 | W5: 4285.05 | Y5: 4285.05 | Z5: 0
A6: VENDAS SHOPEE - VIP MX | C6: 3000 | D6: 11860.57 | E6: 3000 | F6: 15742.89 | G6: 3000 | H6: 33406.21 | I6: 3300 | J6: 38333.32 | K6: 3300 | M6: 3300 | O6: =M6*0.06+M6 -> 3498 | Q6: 3498 | S6: 3498 | U6: =S6*0.05+S6 -> 3672.9 | W6: 3672.9 | Y6: 3672.9 | Z6: 0
A7: RENDIMENTOS | C7: 0 | D7: 0 | E7: 0 | G7: 0 | I7: =G7*0.1+G7 -> 0 | K7: 0 | M7: 0 | O7: =M7*0.06+M7 -> 0 | Q7: 0 | S7: 0 | U7: =S7*0.05+S7 -> 0 | W7: 0 | Y7: 0 | Z7: 0
A10: (-) Despesas do Negócio | C10: =SUM(C11:C23) -> 395348.93 | D10: =SUM(D11:D23) -> 439765.25 | E10: =SUM(E11:E23) -> 343180.71 | F10: =SUM(F11:F23) -> 389391.98 | G10: =SUM(G11:G23) -> 301860.87 | H10: =SUM(H11:H23) -> 464461.03 | I10: =SUM(I11:I23) -> 228299.94 | J10: =SUM(J11:J23) -> 409521.59 | ... Z10: =SUM(Z11:Z23) -> 0
A11: Despesas de pessoal | C11: =1788.08+2195.77+2244.39 -> 6228.24 | D11: =1788.08+2195.77+2244.39+547.99+877.48 -> 7653.71 | E11: =1899+2240.5+1647.2+467.48+791.56 -> 7045.74 | F11: =1788.08+2195.77+1690.53+845.22+499.17 -> 7018.77 | G11: =1899+2240.5+1647.2+467.48+791.56 -> 7045.74 | H11: =2156.17+2195.77+1690.53+531.53+881.63 -> 7455.63 | I11: =1899+2240.5+1647.2+467.48+791.56 -> 7045.74 | J11: =2156.17+3181.6+1690.53+961.58+595.16 -> 8585.04 | K11: =1899+2240.5+1647.2+467.48+791.56 -> 7045.74 | M11: =1899+2240.5+1647.2+467.48+791.56 -> 7045.74 | O11: =1899+2240.5+1647.2+467.48+791.56 -> 7045.74 | Q11: =1899+2240.5+1647.2+467.48+791.56 -> 7045.74 | S11: =1899+2240.5+1647.2+467.48+791.56 -> 7045.74 | U11: =1899+2240.5+1647.2+467.48+791.56 -> 7045.74 | W11: =1899+2240.5+1647.2+467.48+791.56 -> 7045.74 | Y11: =1899+2240.5+1647.2+467.48+791.56 -> 7045.74 | Z11: 0
A12: Consultorias e acessorias | C12: =1000+600 -> 1600 | D12: =1000+600 -> 1600 | E12: =1000+600 -> 1600 | F12: =1000+1140 -> 2140 | G12: =1000+600 -> 1600 | H12: =1000+600 -> 1600 | I12: =1000+600 -> 1600 | J12: =1000+640 -> 1640 | K12: =1000+600 -> 1600 | M12: =1000+600 -> 1600 | O12: =1000+600 -> 1600 | Q12: =1000+600 -> 1600 | S12: =1000+600 -> 1600 | U12: =1000+600 -> 1600 | W12: =1000+600 -> 1600 | Y12: =1000+600 -> 1600 | Z12: 0
A13: Despesas gerais | C13: 0 | D13: 0 | E13: 0 | F13: 0 | G13: 0 | H13: 0 | I13: 0 | J13: 0 | K13: 0 | L13: 0 | M13: 0 | N13: 0 | O13: 0 | P13: 0 | Q13: 0 | R13: 0 | S13: 0 | T13: 0 | U13: 0 | V13: 0 | W13: 0 | X13: 0 | Y13: 0 | Z13: 0
A14: Tecnologia | C14: 250 | D14: 250 | E14: 250 | F14: 250 | G14: 250 | H14: 250 | I14: 250 | J14: 250 | K14: 250 | M14: 250 | O14: 250 | Q14: 250 | S14: 250 | U14: 250 | W14: 250 | Y14: 250 | Z14: 0
A15: Despesas de materia prima | C15: =239024.48+24129.21 -> 263153.69 | D15: 252772.95 | E15: 217067.97 | F15: 228525.11 | G15: 176833.13 | H15: 268703.5 | I15: 91175.7 | J15: 223982.07 | K15: 48922.88 | M15: 21761.12 | O15: 5550.03 | Q15: 152000 | S15: 152000 | U15: 162500 | W15: 162500 | Y15: 162500 | Z15: 0
A16: Despesas de vendas | C16: 2000 | D16: =657.97+697.86 -> 1355.83 | E16: 2000 | F16: 0 | G16: 2000 | H16: =772.85+481.63+508.39 -> 1762.87 | I16: 2000 | J16: =1281.55 -> 1281.55 | K16: 2000 | M16: 2000 | O16: 2000 | Q16: 2000 | S16: 2000 | U16: 2000 | W16: 2000 | Y16: 2000 | Z16: 0
A17: Despesas de marketing | C17: 3000 | D17: 0 | E17: 3000 | F17: 0 | G17: 3000 | H17: 0 | I17: 3250 | K17: 3250 | M17: 3250 | O17: 3500 | Q17: 3500 | S17: 3500 | U17: 4000 | W17: 4000 | Y17: 4000 | Z17: 0
A18: Impostos Retido de Terceiro | C18: 0 | D18: 0 | E18: 0 | F18: 0 | G18: 0 | I18: 0 | K18: 0 | M18: 0 | O18: 0 | Q18: 0 | S18: 0 | U18: 0 | W18: 0 | Y18: 0 | Z18: 0
A19: Impostos | C19: =C4*0.115 -> 29900 | D19: =494.65+28007.24+4855.54 -> 33357.43 | E19: 23000 | F19: =25286.06+1261.89 -> 26547.95 | G19: 23000 | H19: =31526.88+3684.03 -> 35210.91 | I19: 25500 | J19: =37578.42+2450.02 -> 40028.44 | K19: 25500 | M19: 25500 | O19: 28500 | Q19: 28500 | S19: 28500 | U19: 32000 | W19: 32000 | Y19: 32000 | Z19: 0
A20: Despesas financeiras | C20: 0 | D20: 0 | E20: 0 | F20: 0 | G20: 0 | I20: 0 | K20: 0 | M20: 0 | O20: 0 | Q20: 0 | S20: 0 | U20: 0 | W20: 0 | Y20: 0 | Z20: 0
A21: Taxas plataforma | C21: =(C4+C5+C6)*0.26 -> 69290 | D21: 100405.73 | E21: =(E4+E5+E6)*0.26 -> 69290 | F21: =85892.13 -> 85892.13 | G21: =(G4+G5+G6)*0.26 -> 68380 | H21: 105426.96 | I21: =(I4+I5+I6)*0.26 -> 76219 | J21: 78212.99 | K21: =(K4+K5+K6)*0.26 -> 76219 | M21: =(M4+M5+M6)*0.26 -> 76219 | O21: =(O4+O5+O6)*0.26 -> 80792.14 | Q21: =(Q4+Q5+Q6)*0.26 -> 80792.14 | S21: =(S4+S5+S6)*0.26 -> 80792.14 | U21: =(U4+U5+U6)*0.26 -> 84831.747 | W21: =(W4+W5+W6)*0.26 -> 84831.747 | Y21: =(Y4+Y5+Y6)*0.26 -> 84831.747 | Z21: 0
A22: Cancelamentos e Remmbolso | C22: =(C4+C5+C6)*0.05 -> 13325 | D22: 35767.6 | E22: =(E4+E5+E6)*0.05 -> 13325 | F22: =32416.02 -> 32416.02 | G22: =(G4+G5+G6)*0.05 -> 13150 | H22: 37449.16 | I22: =(I4+I5+I6)*0.05 -> 14657.5 | J22: 48939.5 | K22: =(K4+K5+K6)*0.05 -> 14657.5 | M22: =(M4+M5+M6)*0.05 -> 14657.5 | O22: =(O4+O5+O6)*0.05 -> 15536.95 | Q22: =(Q4+Q5+Q6)*0.05 -> 15536.95 | S22: =(S4+S5+S6)*0.05 -> 15536.95 | U22: =(U4+U5+U6)*0.05 -> 16313.798 | W22: =(W4+W5+W6)*0.05 -> 16313.798 | Y22: =(Y4+Y5+Y6)*0.05 -> 16313.798 | Z22: 0
A23: Financiamentos | C23: 6602 | D23: 6602 | E23: 6602 | F23: 6602 | G23: 6602 | H23: 6602 | I23: 6602 | J23: 6602 | K23: 6602 | M23: 6602 | O23: 6602 | Q23: 6602 | S23: 6602 | U23: 6602 | W23: 6602 | Y23: 6602 | Z23: 0
A24: Resultado | C24: =C3-C10 -> -128848.93 | D24: =D3-D10 -> -4409.78 | E24: =E3-E10 -> -76680.71 | F24: =F3-F10 -> -26198.19 | G24: =G3-G10 -> -38860.87 | H24: =H3-H10 -> -18203.49 | I24: =I3-I10 -> 64850.06 | J24: =J3-J10 -> 136391.74 | ... Z24: =Z3-Z10 -> 0
A27: VIDAL | C27: Previsto | D27: Realizado | E27: Previsto | F27: Realizado | G27: Previsto | H27: Realizado | I27: Previsto | J27: Realizado | K27: Previsto | L27: Realizado | M27: Previsto | N27: Realizado | O27: Previsto | P27: Realizado | Q27: Previsto | R27: Realizado | S27: Previsto | T27: Realizado | U27: Previsto | V27: Realizado | W27: Previsto | X27: Realizado | Y27: Previsto | Z27: Realizado
C28: 46023 | D28: 46023 | E28: 46054 | F28: 46054 | G28: 46082 | H28: 46082 | I28: 46113 | J28: 46113 | K28: 46143 | L28: 46143 | M28: 46174 | N28: 46174 | O28: 46204 | P28: 46204 | Q28: 46235 | R28: 46235 | S28: 46266 | T28: 46266 | U28: 46296 | V28: 46296 | W28: 46327 | X28: 46327 | Y28: 46357 | Z28: 46357
A29: Receita Bruta | C29: =SUM(C30:C33) -> 207000 | D29: =SUM(D30:D33) -> 196570.68 | E29: =SUM(E30:E33) -> 207000 | F29: =SUM(F30:F33) -> 167144.26 | G29: =SUM(G30:G33) -> 207000 | H29: =SUM(H30:H33) -> 229018.47 | I29: =SUM(I30:I33) -> 227700 | J29: =SUM(J30:J33) -> 251047.64 | ... Z29: =SUM(Z30:Z33) -> 0
A30: VENDAS LOJA FISICA | C30: 50000 | D30: 44021.86 | E30: 50000 | F30: 29797.32 | G30: 50000 | H30: 56728.92 | I30: 55000 | J30: 58148.23 | K30: 55000 | M30: 55000 | O30: =M30*0.06+M30 -> 58300 | Q30: 58300 | S30: 58300 | U30: =S30*0.05+S30 -> 61215 | W30: 61215 | Y30: 61215 | Z30: 0
A31: VENDAS MERCADO LIVRE - VIDAL | C31: 155000 | D31: 138853.28 | E31: 155000 | F31: 120539.51 | G31: 155000 | H31: 144159.46 | I31: 170500 | J31: =167726.63+2481.96 -> 170208.59 | K31: 170500 | M31: 170500 | O31: =M31*0.06+M31 -> 180730 | Q31: 180730 | S31: 180730 | U31: =S31*0.05+S31 -> 189766.5 | W31: 189766.5 | Y31: 189766.5 | Z31: 0
A32: VENDAS SHOPEE - VIDAL | C32: 2000 | D32: 13695.54 | E32: 2000 | F32: 16807.43 | G32: 2000 | H32: 28130.09 | I32: 2200 | J32: 22690.82 | K32: 2200 | M32: 2200 | O32: =M32*0.06+M32 -> 2332 | Q32: 2332 | S32: 2332 | U32: =S32*0.05+S32 -> 2448.6 | W32: 2448.6 | Y32: 2448.6 | Z32: 0
A33: RENDIMENTOS | C33: 0 | D33: 0 | E33: 0 | G33: 0 | I33: =G33*0.1+G33 -> 0 | K33: 0 | M33: 0 | O33: =M33*0.06+M33 -> 0 | Q33: 0 | S33: 0 | U33: =S33*0.05+S33 -> 0 | W33: 0 | Y33: 0 | Z33: 0
A36: (-) Despesas do Negócio | C36: =SUM(C37:C49) -> 182853.5 | D36: =SUM(D37:D49) -> 71161.33 | E36: =SUM(E37:E49) -> 182853.5 | F36: =SUM(F37:F49) -> 86782.26 | G36: =SUM(G37:G49) -> 182853.5 | H36: =SUM(H37:H49) -> 101713.57 | I36: =SUM(I37:I49) -> 194013.91 | J36: =SUM(J37:J49) -> 135846.61 | ... Z36: =SUM(Z37:Z49) -> 0
A37: Despesas de pessoal | C37: =20000+2240.5+493 -> 22733.5 | D37: =17000+178.31 -> 17178.31 | E37: =20000+2240.5+493 -> 22733.5 | F37: =17000+178.31 -> 17178.31 | G37: =20000+2240.5+493 -> 22733.5 | H37: =17000+178.31+800 -> 17978.31 | I37: =17000+178.31+1098.6 -> 18276.91 | J37: =17000+178.31+1098.6 -> 18276.91 | K37: =17000+178.31+1831 -> 19009.31 | M37: =17000+178.31+1831 -> 19009.31 | O37: =17000+178.31+1831 -> 19009.31 | Q37: =17000+178.31+1831 -> 19009.31 | S37: =17000+178.31+1831 -> 19009.31 | U37: =17000+178.31+1831 -> 19009.31 | W37: =17000+178.31+1831 -> 19009.31 | Y37: =17000+178.31+1831 -> 19009.31 | Z37: 0
A38: Consultorias e acessorias | C38: 0 | D38: 0 | E38: 0 | F38: 0 | G38: 0 | H38: 0 | I38: 0 | J38: 0 | K38: 0 | L38: 0 | M38: 0 | N38: 0 | O38: 0 | P38: 0 | Q38: 0 | R38: 0 | S38: 0 | T38: 0 | U38: 0 | V38: 0 | W38: 0 | X38: 0 | Y38: 0 | Z38: 0
A39: Despesas gerais | C39: =2150+850+250+5000 -> 8250 | D39: =2150+857.07+250+2795.79 -> 6052.86 | E39: =2150+850+250+5000 -> 8250 | F39: =2150+850+250+3000+1000+1822.82 -> 9072.82 | G39: =2150+850+250+5000 -> 8250 | H39: =1100+826.94+250+2844.98 -> 5021.92 | I39: =2150+850+250+5000 -> 8250 | J39: =2100+826.94+250+3393.01+161.39 -> 6731.34 | K39: =2150+850+250+5000 -> 8250 | M39: =2150+850+250+5000 -> 8250 | O39: =2150+850+250+5000 -> 8250 | Q39: =2150+850+250+5000 -> 8250 | S39: =2150+850+250+5000 -> 8250 | U39: =2150+850+250+5000 -> 8250 | W39: =2150+850+250+5000 -> 8250 | Y39: =2150+850+250+5000 -> 8250 | Z39: 0
A40: Tecnologia | C40: 200 | D40: 200 | E40: 200 | F40: 200 | G40: 200 | H40: =200+500 -> 700 | I40: =200+250 -> 450 | J40: =200+250+149 -> 599 | K40: 200 | M40: 200 | O40: 200 | Q40: 200 | S40: 200 | U40: 200 | W40: 200 | Y40: 200 | Z40: 0
A41: Despesas de materia prima | C41: 90000 | D41: 0 | E41: 90000 | F41: 3059.34 | G41: 90000 | H41: 10570.07 | I41: 98000 | J41: 30495.45 | K41: 98000 | M41: 98000 | O41: 105000 | Q41: 105000 | S41: 105000 | U41: 113500 | W41: 113500 | Y41: 113500 | Z41: 0
A42: Despesas de vendas | C42: 0 | D42: 0 | E42: 0 | F42: 0 | G42: 0 | H42: 0 | I42: 0 | J42: 0 | K42: 0 | L42: 0 | M42: 0 | N42: 0 | O42: 0 | P42: 0 | Q42: 0 | R42: 0 | S42: 0 | T42: 0 | U42: 0 | V42: 0 | W42: 0 | X42: 0 | Y42: 0 | Z42: 0
A43: Despesas de marketing | C43: 0 | D43: 0 | E43: 0 | F43: 0 | G43: 0 | H43: 440 | I43: 0 | J43: 500 | K43: 0 | L43: 0 | M43: 0 | N43: 0 | O43: 0 | P43: 0 | Q43: 0 | R43: 0 | S43: 0 | T43: 0 | U43: 0 | V43: 0 | W43: 0 | X43: 0 | Y43: 0 | Z43: 0
A44: Impostos Retido de Terceiro | C44: 0 | D44: 0 | E44: 0 | G44: 0 | H44: 0 | I44: 0 | K44: 0 | M44: 0 | O44: 0 | Q44: 0 | S44: 0 | U44: 0 | W44: 0 | Y44: 0 | Z44: 0
A45: Impostos | C45: 13000 | D45: 8842.69 | E45: 13000 | F45: =68.72+8852.98 -> 8921.7 | G45: 13000 | H45: 10958.27 | I45: 15500 | J45: 11197.46 | K45: 15500 | M45: 15500 | O45: 18900 | Q45: 18900 | S45: 18900 | U45: 23000 | W45: 23000 | Y45: 23000 | Z45: 0
A46: Despesas financeiras | C46: 0 | D46: 0 | E46: 0 | G46: 0 | H46: 0 | I46: 0 | K46: 0 | M46: 0 | O46: 0 | Q46: 0 | S46: 0 | U46: 0 | W46: 0 | Y46: 0 | Z46: 0
A47: Taxas plataforma | C47: =(C31+C32)*0.26 -> 40820 | D47: 22834.91 | E47: =(E31+E32)*0.26 -> 40820 | F47: 32636.18 | G47: =(G31+G32)*0.26 -> 40820 | H47: 39540.71 | I47: =(I31+I32)*0.26 -> 44902 | J47: =25220.26+20695.89 -> 45916.15 | K47: =(K31+K32)*0.26 -> 44902 | M47: =(M31+M32)*0.26 -> 44902 | O47: =(O31+O32)*0.26 -> 47596.12 | Q47: =(Q31+Q32)*0.26 -> 47596.12 | S47: =(S31+S32)*0.26 -> 47596.12 | U47: =(U31+U32)*0.26 -> 49975.926 | W47: =(W31+W32)*0.26 -> 49975.926 | Y47: =(Y31+Y32)*0.26 -> 49975.926 | Z47: 0
A48: Cancelamentos e Remmbolso | C48: =(C31+C32)*0.05 -> 7850 | D48: 16052.56 | E48: =(E31+E32)*0.05 -> 7850 | F48: 15713.91 | G48: =(G31+G32)*0.05 -> 7850 | H48: 16504.29 | I48: =(I31+I32)*0.05 -> 8635 | J48: =22130.3 -> 22130.3 | K48: =(K31+K32)*0.05 -> 8635 | M48: =(M31+M32)*0.05 -> 8635 | O48: =(O31+O32)*0.05 -> 9153.1 | Q48: =(Q31+Q32)*0.05 -> 9153.1 | S48: =(S31+S32)*0.05 -> 9153.1 | U48: =(U31+U32)*0.05 -> 9610.755 | W48: =(W31+W32)*0.05 -> 9610.755 | Y48: =(Y31+Y32)*0.05 -> 9610.755 | Z48: 0
A49: Financiamentos | C49: 0 | D49: 0 | E49: 0 | F49: 0 | G49: 0 | H49: 0 | I49: 0 | J49: 0 | K49: 0 | L49: 0 | M49: 0 | N49: 0 | O49: 0 | P49: 0 | Q49: 0 | R49: 0 | S49: 0 | T49: 0 | U49: 0 | V49: 0 | W49: 0 | X49: 0 | Y49: 0 | Z49: 0
A50: Resultado | C50: =C29-C36 -> 24146.5 | D50: =D29-D36 -> 125409.35 | E50: =E29-E36 -> 24146.5 | F50: =F29-F36 -> 80362 | G50: =G29-G36 -> 24146.5 | H50: =H29-H36 -> 127304.9 | I50: =I29-I36 -> 33686.09 | J50: =J29-J36 -> 115201.03 | ... Z50: =Z29-Z36 -> 0
A53: V3 | C53: Previsto | D53: Realizado | E53: Previsto | F53: Realizado | G53: Previsto | H53: Realizado | I53: Previsto | J53: Realizado | K53: Previsto | L53: Realizado | M53: Previsto | N53: Realizado | O53: Previsto | P53: Realizado | Q53: Previsto | R53: Realizado | S53: Previsto | T53: Realizado | U53: Previsto | V53: Realizado | W53: Previsto | X53: Realizado | Y53: Previsto | Z53: Realizado
C54: 46023 | D54: 46023 | E54: 46054 | F54: 46054 | G54: 46082 | H54: 46082 | I54: 46113 | J54: 46113 | K54: 46143 | L54: 46143 | M54: 46174 | N54: 46174 | O54: 46204 | P54: 46204 | Q54: 46235 | R54: 46235 | S54: 46266 | T54: 46266 | U54: 46296 | V54: 46296 | W54: 46327 | X54: 46327 | Y54: 46357 | Z54: 46357
A55: Receita Bruta | C55: =SUM(C56:C57) -> 7500 | D55: =SUM(D56:D57) -> 2706 | E55: =SUM(E56:E57) -> 7500 | F55: =SUM(F56:F57) -> 3774.1 | G55: =SUM(G56:G57) -> 7500 | H55: =SUM(H56:H57) -> 3913 | I55: =SUM(I56:I57) -> 3913 | J55: =SUM(J56:J57) -> 3918 | ... Z55: =SUM(Z56:Z57) -> 0
A56: VENDAS MERCADO LIVRE - V3 | C56: 7500 | D56: 2706 | E56: 7500 | F56: =3556.2+217.9 -> 3774.1 | G56: 7500 | H56: 3913 | I56: 3913 | J56: 3918 | K56: 8250 | M56: 8250 | O56: =M56*0.06+M56 -> 8745 | Q56: 8745 | S56: 8745 | U56: =S56*0.05+S56 -> 9182.25 | W56: 9182.25 | Y56: 9182.25 | Z56: 0
A57: RENDIMENTOS | C57: 0 | D57: 0 | E57: 0 | G57: 0 | I57: =G57*0.1+G57 -> 0 | K57: 0 | M57: 0 | O57: =M57*0.06+M57 -> 0 | Q57: 0 | S57: 0 | U57: =S57*0.05+S57 -> 0 | W57: 0 | Y57: 0 | Z57: 0
A60: (-) Despesas do Negócio | C60: =SUM(C61:C73) -> 2250 | D60: =SUM(D61:D73) -> 578 | E60: =SUM(E61:E73) -> 2250 | F60: =SUM(F61:F73) -> 1002.38 | G60: =SUM(G61:G73) -> 2250 | H60: =SUM(H61:H73) -> 1205.54 | I60: =SUM(I61:I73) -> 1173.9 | J60: =SUM(J61:J73) -> 1404.5 | ... Z60: =SUM(Z61:Z73) -> 0
A61: Despesas de pessoal | C61: 0 | D61: 0 | E61: 0 | F61: 0 | G61: 0 | H61: 0 | I61: 0 | J61: 0 | K61: 0 | L61: 0 | M61: 0 | N61: 0 | O61: 0 | P61: 0 | Q61: 0 | R61: 0 | S61: 0 | T61: 0 | U61: 0 | V61: 0 | W61: 0 | X61: 0 | Y61: 0 | Z61: 0
A62: Consultorias e acessorias | C62: 0 | D62: 0 | E62: 0 | F62: 0 | G62: 0 | H62: 0 | I62: 0 | J62: 0 | K62: 0 | L62: 0 | M62: 0 | N62: 0 | O62: 0 | P62: 0 | Q62: 0 | R62: 0 | S62: 0 | T62: 0 | U62: 0 | V62: 0 | W62: 0 | X62: 0 | Y62: 0 | Z62: 0
A63: Despesas gerais | C63: 0 | D63: 0 | E63: 0 | F63: 0 | G63: 0 | H63: 0 | I63: 0 | J63: 0 | K63: 0 | L63: 0 | M63: 0 | N63: 0 | O63: 0 | P63: 0 | Q63: 0 | R63: 0 | S63: 0 | T63: 0 | U63: 0 | V63: 0 | W63: 0 | X63: 0 | Y63: 0 | Z63: 0
A64: Tecnologia | C64: 0 | D64: 0 | E64: 0 | F64: 0 | G64: 0 | H64: 0 | I64: 0 | J64: 0 | K64: 0 | L64: 0 | M64: 0 | N64: 0 | O64: 0 | P64: 0 | Q64: 0 | R64: 0 | S64: 0 | T64: 0 | U64: 0 | V64: 0 | W64: 0 | X64: 0 | Y64: 0 | Z64: 0
A65: Despesas de materia prima | C65: 0 | D65: 0 | E65: 0 | F65: 0 | G65: 0 | H65: 0 | I65: 0 | J65: 0 | K65: 0 | L65: 0 | M65: 0 | N65: 0 | O65: 0 | P65: 0 | Q65: 0 | R65: 0 | S65: 0 | T65: 0 | U65: 0 | V65: 0 | W65: 0 | X65: 0 | Y65: 0 | Z65: 0
A66: Despesas de vendas | C66: 0 | D66: 0 | E66: 0 | F66: 0 | G66: 0 | H66: 0 | I66: 0 | J66: 0 | K66: 0 | L66: 0 | M66: 0 | N66: 0 | O66: 0 | P66: 0 | Q66: 0 | R66: 0 | S66: 0 | T66: 0 | U66: 0 | V66: 0 | W66: 0 | X66: 0 | Y66: 0 | Z66: 0
A67: Despesas de marketing | C67: 0 | D67: 0 | E67: 0 | F67: 0 | G67: 0 | H67: 0 | I67: 0 | J67: 0 | K67: 0 | L67: 0 | M67: 0 | N67: 0 | O67: 0 | P67: 0 | Q67: 0 | R67: 0 | S67: 0 | T67: 0 | U67: 0 | V67: 0 | W67: 0 | X67: 0 | Y67: 0 | Z67: 0
A68: Impostos Retido de Terceiro | C68: 0 | D68: 0 | E68: 0 | F68: 0 | G68: 0 | H68: 0 | I68: 0 | J68: 0 | K68: 0 | L68: 0 | M68: 0 | N68: 0 | O68: 0 | P68: 0 | Q68: 0 | R68: 0 | S68: 0 | T68: 0 | U68: 0 | V68: 0 | W68: 0 | X68: 0 | Y68: 0 | Z68: 0
A69: Impostos | C69: 0 | D69: 0 | E69: 0 | F69: 0 | G69: 0 | H69: 0 | I69: 0 | J69: 0 | K69: 0 | L69: 0 | M69: 0 | N69: 0 | O69: 0 | P69: 0 | Q69: 0 | R69: 0 | S69: 0 | T69: 0 | U69: 0 | V69: 0 | W69: 0 | X69: 0 | Y69: 0 | Z69: 0
A70: Despesas financeiras | C70: 0 | D70: 0 | E70: 0 | F70: 0 | G70: 0 | H70: 0 | I70: 0 | J70: 0 | K70: 0 | L70: 0 | M70: 0 | N70: 0 | O70: 0 | P70: 0 | Q70: 0 | R70: 0 | S70: 0 | T70: 0 | U70: 0 | V70: 0 | W70: 0 | X70: 0 | Y70: 0 | Z70: 0
A71: Taxas plataforma | C71: =C56*0.25 -> 1875 | D71: 578 | E71: =E56*0.25 -> 1875 | F71: 671.91 | G71: =G56*0.25 -> 1875 | H71: 1205.54 | I71: =I56*0.25 -> 978.25 | J71: 1118 | K71: =K56*0.25 -> 2062.5 | L71: 0 | M71: =M56*0.25 -> 2062.5 | N71: 0 | O71: =O56*0.25 -> 2186.25 | P71: 0 | Q71: =Q56*0.25 -> 2186.25 | R71: 0 | S71: =S56*0.25 -> 2186.25 | T71: 0 | U71: =U56*0.25 -> 2295.5625 | V71: 0 | W71: =W56*0.25 -> 2295.5625 | X71: 0 | Y71: =Y56*0.25 -> 2295.5625 | Z71: 0
A72: Cancelamentos e Remmbolso | C72: =C56*0.05 -> 375 | D72: 0 | E72: =E56*0.05 -> 375 | F72: 330.47 | G72: =G56*0.05 -> 375 | H72: 0 | I72: =I56*0.05 -> 195.65 | J72: 286.5 | K72: =K56*0.05 -> 412.5 | L72: 0 | M72: =M56*0.05 -> 412.5 | N72: 0 | O72: =O56*0.05 -> 437.25 | P72: 0 | Q72: =Q56*0.05 -> 437.25 | R72: 0 | S72: =S56*0.05 -> 437.25 | T72: 0 | U72: =U56*0.05 -> 459.1125 | V72: 0 | W72: =W56*0.05 -> 459.1125 | X72: 0 | Y72: =Y56*0.05 -> 459.1125 | Z72: 0
A73: Financiamentos | C73: 0 | D73: 0 | E73: 0 | F73: 0 | G73: 0 | H73: 0 | I73: 0 | J73: 0 | K73: 0 | L73: 0 | M73: 0 | N73: 0 | O73: 0 | P73: 0 | Q73: 0 | R73: 0 | S73: 0 | T73: 0 | U73: 0 | V73: 0 | W73: 0 | X73: 0 | Y73: 0 | Z73: 0
A74: Resultado | C74: =C55-C60 -> 5250 | D74: =D55-D60 -> 2128 | E74: =E55-E60 -> 5250 | F74: =F55-F60 -> 2771.72 | G74: =G55-G60 -> 5250 | H74: =H55-H60 -> 2707.46 | I74: =I55-I60 -> 2739.1 | J74: =J55-J60 -> 2513.5 | ... Z74: =Z55-Z60 -> 0

Sheet Fluxo De caixa - VIP
B1: JANEIRO-26
B2: DATA
C3: Entradas Realizadas | D3: Resgate apl | E3: Aporte Propietario | F3: Despesas realizadas | G3: Aplicação | H3: Shareholder Remuneration | I3: Saldo do dia
I4: 350000
B5: 46023 | C5: 0 | D5: 0 | E5: 0 | F5: 0 | G5: 0 | H5: 0 | I5: =+I4+C5+E5+G5+H5+F5+D5 -> 350000
B6: 46024 | C6: 0 | D6: 0 | E6: 0 | F6: 0 | G6: 0 | H6: 0 | I6: =+I5+C6+E6+G6+H6+F6+D6 -> 350000
B7: 46025 | C7: 0 | D7: 0 | E7: 0 | F7: 0 | G7: 0 | H7: 0 | I7: =+I6+C7+E7+G7+H7+F7+D7 -> 350000
B8: 46026 | C8: 0 | D8: 0 | E8: 0 | F8: 0 | G8: 0 | H8: 0 | I8: =+I7+C8+E8+G8+H8+F8+D8 -> 350000
B9: 46027 | C9: 0 | D9: 0 | E9: 0 | F9: 0 | G9: 0 | H9: 0 | I9: =+I8+C9+E9+G9+H9+F9+D9 -> 350000
B10: 46028 | C10: 0 | D10: 0 | E10: 0 | F10: 0 | G10: 0 | H10: 0 | I10: =+I9+C10+E10+G10+H10+F10+D10 -> 350000
B11: 46029 | C11: 0 | D11: 0 | E11: 0 | F11: 0 | G11: 0 | H11: 0 | I11: =+I10+C11+E11+G11+H11+F11+D11 -> 350000
B12: 46030 | C12: 0 | D12: 0 | E12: 0 | F12: 0 | G12: 0 | H12: 0 | I12: =+I11+C12+E12+G12+H12+F12+D12 -> 350000
B13: 46031 | C13: 0 | D13: 0 | E13: 0 | F13: 0 | G13: 0 | H13: 0 | I13: =+I12+C13+E13+G13+H13+F13+D13 -> 350000
B14: 46032 | C14: 0 | D14: 0 | E14: 0 | F14: 0 | G14: 0 | H14: 0 | I14: =+I13+C14+E14+G14+H14+F14+D14 -> 350000
B15: 46033 | C15: 0 | D15: 0 | E15: 0 | F15: 0 | G15: 0 | H15: 0 | I15: =+I14+C15+E15+G15+H15+F15+D15 -> 350000
B16: 46034 | C16: 0 | D16: 0 | E16: 0 | F16: 0 | G16: 0 | H16: 0 | I16: =+I15+C16+E16+G16+H16+F16+D16 -> 350000
... B35: 46053 | C35: 0 | D35: 0 | E35: 0 | F35: 0 | G35: 0 | H35: 0 | I35: =+I34+C35+E35+G35+H35+F35+D35 -> 350000
B36: TOTAL | C36: =SUM(C5:C35) -> 0 | E36: =SUM(E5:E35) -> 0 | F36: =SUM(F5:F35) -> 0 | G36: =SUM(G5:G35) -> 0 | H36: =SUM(H5:H35) -> 0
B38: Fevereiro-26
B39: DATA
C40: Entradas Realizadas | D40: Resgate apl | E40: Aporte Propietario | F40: Despesas realizadas | G40: Aplicação | H40: Shareholder Remuneration | I40: Saldo do dia
I41: 200000
B42: 46054 | C42: 0 | D42: 0 | E42: 0 | F42: 0 | G42: 0 | H42: 0 | I42: =+I41+C42+E42+G42+H42+F42+D42 -> 200000
B43: 46055 | C43: 0 | D43: 0 | E43: 0 | F43: 0 | G43: 0 | H43: 0 | I43: =+I42+C43+E43+G43+H43+F43+D43 -> 200000
B44: 46056 | C44: 0 | D44: 0 | E44: 0 | F44: 0 | G44: 0 | H44: 0 | I44: =+I43+C44+E44+G44+H44+F44+D44 -> 200000
B45: 46057 | C45: 0 | D45: 0 | E45: 0 | F45: 0 | G45: 0 | H45: 0 | I45: =+I44+C45+E45+G45+H45+F45+D45 -> 200000
B46: 46058 | C46: 0 | D46: 0 | E46: 0 | F46: 0 | G46: 0 | H46: 0 | I46: =+I45+C46+E46+G46+H46+F46+D46 -> 200000
B47: 46059 | C47: 0 | D47: 0 | E47: 0 | F47: 0 | G47: 0 | H47: 0 | I47: =+I46+C47+E47+G47+H47+F47+D47 -> 200000
B48: 46060 | C48: 0 | D48: 0 | E48: 0 | F48: -10062.67 | G48: 0 | H48: 0 | I48: =+I47+C48+E48+G48+H48+F48+D48 -> 189937.33
B49: 46061 | C49: 0 | D49: 0 | E49: 0 | F49: -377.95 | G49: 0 | H49: 0 | I49: =+I48+C49+E49+G49+H49+F49+D49 -> 189559.38
B50: 46062 | C50: 0 | D50: 0 | E50: 0 | F50: -7572.81 | G50: 0 | H50: 0 | I50: =+I49+C50+E50+G50+H50+F50+D50 -> 181986.57
B51: 46063 | C51: 0 | D51: 0 | E51: 0 | F51: -11377.46 | G51: 0 | H51: 0 | I51: =+I50+C51+E51+G51+H51+F51+D51 -> 170609.11
B52: 46064 | C52: 0 | D52: 0 | E52: 0 | F52: -5179.26 | G52: 0 | H52: 0 | I52: =+I51+C52+E52+G52+H52+F52+D52 -> 165429.85
B53: 46065 | C53: 0 | D53: 0 | E53: 0 | F53: -13917.42 | G53: 0 | H53: 0 | I53: =+I52+C53+E53+G53+H53+F53+D53 -> 151512.43
... B60: 46072 | C60: 0 | D60: 0 | E60: 0 | F60: -3905.48 | G60: 0 | H60: 0 | I60: =+I59+C60+E60+G60+H60+F60+D60 -> 90959.14
B61: 46073 | C61: 0 | D61: 0 | E61: 0 | F61: =-(1973+450+40000+8031.05) -> -50454.05 | G61: 0 | H61: 0 | I61: =+I60+C61+E61+G61+H61+F61+D61 -> 40505.09
B62: 46074 | C62: 0 | D62: 0 | E62: 0 | F62: -2198.11 | G62: 0 | H62: 0 | I62: =+I61+C62+E62+G62+H62+F62+D62 -> 38306.98
B63: 46075 | C63: 0 | D63: 0 | E63: 0 | F63: -3304.59 | G63: 0 | H63: 0 | I63: =+I62+C63+E63+G63+H63+F63+D63 -> 35002.39
B64: 46076 | C64: 0 | D64: 0 | E64: 0 | F64: -3678.01 | G64: 0 | H64: 0 | I64: =+I63+C64+E64+G64+H64+F64+D64 -> 31324.38
B65: 46077 | C65: 0 | D65: 0 | E65: 0 | F65: -14281.68 | G65: 0 | H65: 0 | I65: =+I64+C65+E65+G65+H65+F65+D65 -> 17042.7
B66: 46078 | C66: 0 | D66: 0 | E66: 0 | F66: -7000.53 | G66: 0 | H66: 0 | I66: =+I65+C66+E66+G66+H66+F66+D66 -> 10042.17
B67: 46079 | C67: 0 | D67: 0 | E67: 0 | F67: -8416.88 | G67: 0 | H67: 0 | I67: =+I66+C67+E67+G67+H67+F67+D67 -> 1625.29
B68: 46080 | C68: 0 | D68: 0 | E68: 0 | F68: =-(1000+9024.51) -> -10024.51 | G68: 0 | H68: 0 | I68: =+I67+C68+E68+G68+H68+F68+D68 -> -8399.22
B69: 46081 | C69: 0 | D69: 0 | E69: 0 | F69: -6628.49 | G69: 0 | H69: 0 | I69: =+I68+C69+E69+G69+H69+F69+D69 -> -15027.71
B70: TOTAL | C70: =SUM(C42:C69) -> 0 | E70: =SUM(E42:E69) -> 0 | F70: =SUM(F42:F69) -> -215027.71 | H70: =SUM(H42:H69) -> 0
B72: Março-26
B73: DATA
C74: Entradas Realizadas | D74: Resgate apl | E74: Aporte Propietario | F74: Despesas realizadas | G74: Aplicação | H74: Shareholder Remuneration | I74: Saldo do dia
I75: =I69 -> -15027.71
B76: 46082 | C76: 0 | D76: 0 | E76: 0 | F76: 0 | G76: 0 | H76: 0 | I76: =+I75+C76+E76+G76+H76+F76+D76 -> -15027.71
B77: 46083 | C77: 0 | D77: 0 | E77: 0 | F77: 0 | G77: 0 | H77: 0 | I77: =+I76+C77+E77+G77+H77+F77+D77 -> -15027.71
B78: 46084 | C78: 0 | D78: 0 | E78: 0 | F78: 0 | G78: 0 | H78: 0 | I78: =+I77+C78+E78+G78+H78+F78+D78 -> -15027.71
B79: 46085 | C79: 0 | D79: 0 | E79: 0 | F79: 0 | G79: 0 | H79: 0 | I79: =+I78+C79+E79+G79+H79+F79+D79 -> -15027.71
B80: 46086 | C80: 0 | D80: 0 | E80: 0 | F80: =-(9779+20000+2000) -> -31779 | G80: 0 | H80: 0 | I80: =+I79+C80+E80+G80+H80+F80+D80 -> -46806.71
B81: 46087 | C81: 0 | D81: 0 | E81: 0 | F81: 0 | G81: 0 | H81: 0 | I81: =+I80+C81+E81+G81+H81+F81+D81 -> -46806.71
B82: 46088 | C82: 0 | D82: 0 | E82: 0 | F82: 0 | G82: 0 | H82: 0 | I82: =+I81+C82+E82+G82+H82+F82+D82 -> -46806.71
B83: 46089 | C83: 0 | D83: 0 | E83: 0 | F83: 0 | G83: 0 | H83: 0 | I83: =+I82+C83+E83+G83+H83+F83+D83 -> -46806.71
B84: 46090 | C84: 0 | D84: 0 | E84: 0 | F84: 0 | G84: 0 | H84: 0 | I84: =+I83+C84+E84+G84+H84+F84+D84 -> -46806.71
B85: 46091 | C85: 0 | D85: 0 | E85: 0 | F85: =-(2150+850+250+5000+3000) -> -11250 | G85: 0 | H85: 0 | I85: =+I84+C85+E85+G85+H85+F85+D85 -> -58056.71
B86: 46092 | C86: 0 | D86: 0 | E86: 0 | F86: 0 | G86: 0 | H86: 0 | I86: =+I85+C86+E86+G86+H86+F86+D86 -> -58056.71
B87: 46093 | C87: 0 | D87: 0 | E87: 0 | F87: 0 | G87: 0 | H87: 0 | I87: =+I86+C87+E87+G87+H87+F87+D87 -> -58056.71
B88: 46094 | C88: 0 | D88: 0 | E88: 0 | F88: =-6602 -> -6602 | G88: 0 | H88: 0 | I88: =+I87+C88+E88+G88+H88+F88+D88 -> -64658.71
B89: 46095 | C89: 0 | D89: 0 | E89: 0 | F89: 0 | G89: 0 | H89: 0 | I89: =+I88+C89+E89+G89+H89+F89+D89 -> -64658.71
B90: 46096 | C90: 0 | D90: 0 | E90: 0 | F90: 0 | G90: 0 | H90: 0 | I90: =+I89+C90+E90+G90+H90+F90+D90 -> -64658.71
B91: 46097 | C91: 0 | D91: 0 | E91: 0 | F91: 0 | G91: 0 | H91: 0 | I91: =+I90+C91+E91+G91+H91+F91+D91 -> -64658.71
B92: 46098 | C92: 0 | D92: 0 | E92: 0 | F92: 0 | G92: 0 | H92: 0 | I92: =+I91+C92+E92+G92+H92+F92+D92 -> -64658.71
B93: 46099 | C93: 0 | D93: 0 | E93: 0 | F93: 0 | G93: 0 | H93: 0 | I93: =+I92+C93+E93+G93+H93+F93+D93 -> -64658.71
B94: 46100 | C94: 0 | D94: 0 | E94: 0 | F94: 0 | G94: 0 | H94: 0 | I94: =+I93+C94+E94+G94+H94+F94+D94 -> -64658.71
B95: 46101 | C95: 0 | D95: 0 | E95: 0 | F95: =-(1973+450+40000) -> -42423 | G95: 0 | H95: 0 | I95: =+I94+C95+E95+G95+H95+F95+D95 -> -107081.71
B96: 46102 | C96: 0 | D96: 0 | E96: 0 | F96: 0 | G96: 0 | H96: 0 | I96: =+I95+C96+E96+G96+H96+F96+D96 -> -107081.71
B97: 46103 | C97: 0 | D97: 0 | E97: 0 | F97: 0 | G97: 0 | H97: 0 | I97: =+I96+C97+E97+G97+H97+F97+D97 -> -107081.71
B98: 46104 | C98: 0 | D98: 0 | E98: 0 | F98: 0 | G98: 0 | H98: 0 | I98: =+I97+C98+E98+G98+H98+F98+D98 -> -107081.71
B99: 46105 | C99: 0 | D99: 0 | E99: 0 | F99: 0 | G99: 0 | H99: 0 | I99: =+I98+C99+E99+G99+H99+F99+D99 -> -107081.71
B100: 46106 | C100: 0 | D100: 0 | E100: 0 | F100: 0 | G100: 0 | H100: 0 | I100: =+I99+C100+E100+G100+H100+F100+D100 -> -107081.71
B101: 46107 | C101: 0 | D101: 0 | E101: 0 | F101: 0 | G101: 0 | H101: 0 | I101: =+I100+C101+E101+G101+H101+F101+D101 -> -107081.71
B102: 46108 | C102: 0 | D102: 0 | E102: 0 | F102: 0 | G102: 0 | H102: 0 | I102: =+I101+C102+E102+G102+H102+F102+D102 -> -107081.71
B103: 46109 | C103: 0 | D103: 0 | E103: 0 | F103: 0 | G103: 0 | H103: 0 | I103: =+I102+C103+E103+G103+H103+F103+D103 -> -107081.71
B104: 46110 | C104: 0 | D104: 0 | E104: 0 | F104: 0 | G104: 0 | H104: 0 | I104: =+I103+C104+E104+G104+H104+F104+D104 -> -107081.71
B105: 46111 | C105: 0 | D105: 0 | E105: 0 | F105: =-1000 -> -1000 | G105: 0 | H105: 0 | I105: =+I104+C105+E105+G105+H105+F105+D105 -> -108081.71
B106: 46112 | C106: 0 | D106: 0 | E106: 0 | F106: 0 | G106: 0 | H106: 0 | I106: =+I105+C106+E106+G106+H106+F106+D106 -> -108081.71
B107: TOTAL | C107: =SUM(C79:C106) -> 0 | E107: =SUM(E79:E106) -> 0 | F107: =SUM(F79:F106) -> -93054 | H107: =SUM(H79:H106) -> 0
B109: Abril-26
B110: DATA
C111: Entradas Realizadas | D111: Resgate apl | E111: Aporte Propietario | F111: Despesas realizadas | G111: Aplicação | H111: Shareholder Remuneration | I111: Saldo do dia
I112: =I106 -> -108081.71
B113: 46113 | C113: 0 | D113: 0 | E113: 0 | F113: 0 | G113: 0 | H113: 0 | I113: =+I112+C113+E113+G113+H113+F113+D113 -> -108081.71
B114: 46114 | C114: 0 | D114: 0 | E114: 0 | F114: 0 | G114: 0 | H114: 0 | I114: =+I113+C114+E114+G114+H114+F114+D114 -> -108081.71
B115: 46115 | C115: 0 | D115: 0 | E115: 0 | F115: 0 | G115: 0 | H115: 0 | I115: =+I114+C115+E115+G115+H115+F115+D115 -> -108081.71
B116: 46116 | C116: 0 | D116: 0 | E116: 0 | F116: 0 | G116: 0 | H116: 0 | I116: =+I115+C116+E116+G116+H116+F116+D116 -> -108081.71
B117: 46117 | C117: 0 | D117: 0 | E117: 0 | F117: 0 | G117: 0 | H117: 0 | I117: =+I116+C117+E117+G117+H117+F117+D117 -> -108081.71
B118: 46118 | C118: 0 | D118: 0 | E118: 0 | F118: =-(9779+20000+2000) -> -31779 | G118: 0 | H118: 0 | I118: =+I117+C118+E118+G118+H118+F118+D118 -> -139860.71
B119: 46119 | C119: 0 | D119: 0 | E119: 0 | F119: 0 | G119: 0 | H119: 0 | I119: =+I118+C119+E119+G119+H119+F119+D119 -> -139860.71
B120: 46120 | C120: 0 | D120: 0 | E120: 0 | F120: 0 | G120: 0 | H120: 0 | I120: =+I119+C120+E120+G120+H120+F120+D120 -> -139860.71
B121: 46121 | C121: 0 | D121: 0 | E121: 0 | F121: 0 | G121: 0 | H121: 0 | I121: =+I120+C121+E121+G121+H121+F121+D121 -> -139860.71
B122: 46122 | C122: 0 | D122: 0 | E122: 0 | F122: =-(2150+850+250+5000+3250) -> -11500 | G122: 0 | H122: 0 | I122: =+I121+C122+E122+G122+H122+F122+D122 -> -151360.71
B123: 46123 | C123: 0 | D123: 0 | E123: 0 | F123: 0 | G123: 0 | H123: 0 | I123: =+I122+C123+E123+G123+H123+F123+D123 -> -151360.71
B124: 46124 | C124: 0 | D124: 0 | E124: 0 | F124: 0 | G124: 0 | H124: 0 | I124: =+I123+C124+E124+G124+H124+F124+D124 -> -151360.71
B125: 46125 | C125: 0 | D125: 0 | E125: 0 | F125: 0 | G125: 0 | H125: 0 | I125: =+I124+C125+E125+G125+H125+F125+D125 -> -151360.71
B126: 46126 | C126: 0 | D126: 0 | E126: 0 | F126: 0 | G126: 0 | H126: 0 | I126: =+I125+C126+E126+G126+H126+F126+D126 -> -151360.71
B127: 46127 | C127: 0 | D127: 0 | E127: 0 | F127: =-6602 -> -6602 | G127: 0 | H127: 0 | I127: =+I126+C127+E127+G127+H127+F127+D127 -> -157962.71
...

Sheet Fluxo De caixa - VIDAL
B1: JANEIRO-26
B2: DATA
C3: Entradas Realizadas | D3: Resgate apl | E3: Aporte Propietario | F3: Despesas realizadas | G3: Aplicação | H3: Shareholder Remuneration | I3: Saldo do dia
I4: 0
B5: 46023 | C5: 0 | D5: 0 | E5: 0 | F5: -13355.79 | G5: 0 | H5: 0 | I5: =+I4+C5+E5+G5+H5+F5+D5 -> -13355.79
B6: 46024 | C6: 0 | D6: 0 | E6: 0 | F6: -7771.32 | G6: 0 | H6: 0 | I6: =+I5+C6+E6+G6+H6+F6+D6 -> -21127.11
B7: 46025 | C7: 0 | D7: 0 | E7: 0 | F7: -2941.69 | G7: 0 | H7: 0 | I7: =+I6+C7+E7+G7+H7+F7+D7 -> -24068.8
B8: 46026 | C8: 0 | D8: 0 | E8: 0 | F8: -2103.31 | G8: 0 | H8: 0 | I8: =+I7+C8+E8+G8+H8+F8+D8 -> -26172.11
B9: 46027 | C9: 0 | D9: 0 | E9: 0 | F9: =-(9779+17000+2000+3533.7) -> -32312.7 | G9: 0 | H9: 0 | I9: =+I8+C9+E9+G9+H9+F9+D9 -> -58484.81
B10: 46028 | C10: 0 | D10: 0 | E10: 0 | F10: -20097.43 | G10: 0 | H10: 0 | I10: =+I9+C10+E10+G10+H10+F10+D10 -> -78582.24
B11: 46029 | C11: 0 | D11: 0 | E11: 0 | F11: -10346.24 | G11: 0 | H11: 0 | I11: =+I10+C11+E11+G11+H11+F11+D11 -> -88928.48
B12: 46030 | C12: 0 | D12: 0 | E12: 0 | F12: -13283.89 | G12: 0 | H12: 0 | I12: =+I11+C12+E12+G12+H12+F12+D12 -> -102212.37
B13: 46031 | C13: 0 | D13: 0 | E13: 0 | F13: =-(2150+850+250+5000+3000+6840.31) -> -18090.31 | G13: 0 | H13: 0 | I13: =+I12+C13+E13+G13+H13+F13+D13 -> -120302.68
B14: 46032 | C14: 0 | D14: 0 | E14: 0 | F14: -8358.27 | G14: 0 | H14: 0 | I14: =+I13+C14+E14+G14+H14+F14+D14 -> -128660.95
B15: 46033 | C15: 0 | D15: 0 | E15: 0 | F15: -7281.7 | G15: 0 | H15: 0 | I15: =+I14+C15+E15+G15+H15+F15+D15 -> -135942.65
B16: 46034 | C16: 0 | D16: 0 | E16: 0 | F16: -4822.69 | G16: 0 | H16: 0 | I16: =+I15+C16+E16+G16+H16+F16+D16 -> -140765.34
B17: 46035 | C17: 0 | D17: 0 | E17: 0 | F17: -12056.85 | G17: 0 | H17: 0 | I17: =+I16+C17+E17+G17+H17+F17+D17 -> -152822.19
B18: 46036 | C18: 0 | D18: 0 | E18: 0 | F18: -1953.24 | G18: 0 | H18: 0 | I18: =+I17+C18+E18+G18+H18+F18+D18 -> -154775.43
B19: 46037 | C19: 0 | D19: 0 | E19: 0 | F19: =-(6602+4683.06) -> -11285.06 | G19: 0 | H19: 0 | I19: =+I18+C19+E19+G19+H19+F19+D19 -> -166060.49
B20: 46038 | C20: 0 | D20: 0 | E20: 0 | F20: -9768.98 | G20: 0 | H20: 0 | I20: =+I19+C20+E20+G20+H20+F20+D20 -> -175829.47
B21: 46039 | C21: 0 | D21: 0 | E21: 0 | F21: -7181.73 | G21: 0 | H21: 0 | I21: =+I20+C21+E21+G21+H21+F21+D21 -> -183011.2
B22: 46040 | C22: 0 | D22: 0 | E22: 0 | F22: -4401.47 | G22: 0 | H22: 0 | I22: =+I21+C22+E22+G22+H22+F22+D22 -> -187412.67
B23: 46041 | C23: 0 | D23: 0 | E23: 0 | F23: -18370.24 | G23: 0 | H23: 0 | I23: =+I22+C23+E23+G23+H23+F23+D23 -> -205782.91
B24: 46042 | C24: 0 | D24: 0 | E24: 0 | F24: =-(1973+450+40000+7117.18) -> -49540.18 | G24: 0 | H24: 0 | I24: =+I23+C24+E24+G24+H24+F24+D24 -> -255323.09
B25: 46043 | C25: 0 | D25: 0 | E25: 0 | F25: -8604.53 | G25: 0 | H25: 0 | I25: =+I24+C25+E25+G25+H25+F25+D25 -> -263927.62
B26: 46044 | C26: 0 | D26: 0 | E26: 0 | F26: -3392.47 | G26: 0 | H26: 0 | I26: =+I25+C26+E26+G26+H26+F26+D26 -> -267320.09
B27: 46045 | C27: 0 | D27: 0 | E27: 0 | F27: -5848.52 | G27: 0 | H27: 0 | I27: =+I26+C27+E27+G27+H27+F27+D27 -> -273168.61
B28: 46046 | C28: 0 | D28: 0 | E28: 0 | F28: -3958.05 | G28: 0 | H28: 0 | I28: =+I27+C28+E28+G28+H28+F28+D28 -> -277126.66
B29: 46047 | C29: 0 | D29: 0 | E29: 0 | F29: -6206.49 | G29: 0 | H29: 0 | I29: =+I28+C29+E29+G29+H29+F29+D29 -> -283333.15
B30: 46048 | C30: 0 | D30: 0 | E30: 0 | F30: -10448.97 | G30: 0 | H30: 0 | I30: =+I29+C30+E30+G30+H30+F30+D30 -> -293782.12
B31: 46049 | C31: 0 | D31: 0 | E31: 0 | F31: -4945.06 | G31: 0 | H31: 0 | I31: =+I30+C31+E31+G31+H31+F31+D31 -> -298727.18
B32: 46050 | C32: 0 | D32: 0 | E32: 0 | F32: -5272.06 | G32: 0 | H32: 0 | I32: =+I31+C32+E32+G32+H32+F32+D32 -> -303999.24
B33: 46051 | C33: 0 | D33: 0 | E33: 0 | F33: -5055.84 | G33: 0 | H33: 0 | I33: =+I32+C33+E33+G33+H33+F33+D33 -> -309055.08
B34: 46052 | C34: 0 | D34: 0 | E34: 0 | F34: =-(1000+4915.13) -> -5915.13 | G34: 0 | H34: 0 | I34: =+I33+C34+E34+G34+H34+F34+D34 -> -314970.21
B35: 46053 | C35: 0 | D35: 0 | E35: 0 | F35: -9762.83 | G35: 0 | H35: 0 | I35: =+I34+C35+E35+G35+H35+F35+D35 -> -324733.04
B36: TOTAL | C36: =SUM(C5:C35) -> 0 | E36: =SUM(E5:E35) -> 0 | F36: =SUM(F5:F35) -> -324733.04 | G36: =SUM(G5:G35) -> 0 | H36: =SUM(H5:H35) -> 0
B38: Fevereiro-26
B39: DATA
C40: Entradas Realizadas | D40: Resgate apl | E40: Aporte Propietario | F40: Despesas realizadas | G40: Aplicação | H40: Shareholder Remuneration | I40: Saldo do dia
I41: =I35 -> -324733.04
B42: 46054 | C42: 0 | D42: 0 | E42: 0 | F42: -5910.39 | G42: 0 | H42: 0 | I42: =+I41+C42+E42+G42+H42+F42+D42 -> -330643.43
B43: 46055 | C43: 0 | D43: 0 | E43: 0 | F43: -2117.35 | G43: 0 | H43: 0 | I43: =+I42+C43+E43+G43+H43+F43+D43 -> -332760.78
B44: 46056 | C44: 0 | D44: 0 | E44: 0 | F44: -6317.81 | G44: 0 | H44: 0 | I44: =+I43+C44+E44+G44+H44+F44+D44 -> -339078.59
B45: 46057 | C45: 0 | D45: 0 | E45: 0 | F45: -3723.9 | G45: 0 | H45: 0 | I45: =+I44+C45+E45+G45+H45+F45+D45 -> -342802.49
B46: 46058 | C46: 0 | D46: 0 | E46: 0 | F46: =-(9779+17000+2000+12041.38) -> -40820.38 | G46: 0 | H46: 0 | I46: =+I45+C46+E46+G46+H46+F46+D46 -> -383622.87
B47: 46059 | C47: 0 | D47: 0 | E47: 0 | F47: -5104.66 | G47: 0 | H47: 0 | I47: =+I46+C47+E47+G47+H47+F47+D47 -> -388727.53
B48: 46060 | C48: 0 | D48: 0 | E48: 0 | F48: -10062.67 | G48: 0 | H48: 0 | I48: =+I47+C48+E48+G48+H48+F48+D48 -> -398790.2
B49: 46061 | C49: 0 | D49: 0 | E49: 0 | F49: -377.95 | G49: 0 | H49: 0 | I49: =+I48+C49+E49+G49+H49+F49+D49 -> -399168.15
B50: 46062 | C50: 0 | D50: 0 | E50: 0 | F50: -6869.34 | G50: 0 | H50: 0 | I50: =+I49+C50+E50+G50+H50+F50+D50 -> -406037.49
B51: 46063 | C51: 0 | D51: 0 | E51: 0 | F51: =-(2150+850+250+5000+3000+5454.4) -> -16704.4 | G51: 0 | H51: 0 | I51: =+I50+C51+E51+G51+H51+F51+D51 -> -422741.89
B52: 46064 | C52: 0 | D52: 0 | E52: 0 | F52: -4816.19 | G52: 0 | H52: 0 | I52: =+I51+C52+E52+G52+H52+F52+D52 -> -427558.08
B53: 46065 | C53: 0 | D53: 0 | E53: 0 | F53: -4800.4 | G53: 0 | H53: 0 | I53: =+I52+C53+E53+G53+H53+F53+D53 -> -432358.48
B54: 46066 | C54: 0 | D54: 0 | E54: 0 | F54: =-(6602+1251.45) -> -7853.45 | G54: 0 | H54: 0 | I54: =+I53+C54+E54+G54+H54+F54+D54 -> -440211.93
B55: 46067 | C55: 0 | D55: 0 | E55: 0 | F55: -3588.59 | G55: 0 | H55: 0 | I55: =+I54+C55+E55+G55+H55+F55+D55 -> -443800.52
B56: 46068 | C56: 0 | D56: 0 | E56: 0 | F56: -9768.97 | G56: 0 | H56: 0 | I56: =+I55+C56+E56+G56+H56+F56+D56 -> -453569.49
B57: 46069 | C57: 0 | D57: 0 | E57: 0 | F57: -19605.98 | G57: 0 | H57: 0 | I57: =+I56+C57+E57+G57+H57+F57+D57 -> -473175.47
B58: 46070 | C58: 0 | D58: 0 | E58: 0 | F58: -6984.39 | G58: 0 | H58: 0 | I58: =+I57+C58+E58+G58+H58+F58+D58 -> -480159.86
B59: 46071 | C59: 0 | D59: 0 | E59: 0 | F59: 0 | G59: 0 | H59: 0 | I59: =+I58+C59+E59+G59+H59+F59+D59 -> -480159.86
B60: 46072 | C60: 0 | D60: 0 | E60: 0 | F60: -3905.48 | G60: 0 | H60: 0 | I60: =+I59+C60+E60+G60+H60+F60+D60 -> -484065.34
B61: 46073 | C61: 0 | D61: 0 | E61: 0 | F61: =-(1973+450+40000+5085.1) -> -47508.1 | G61: 0 | H61: 0 | I61: =+I60+C61+E61+G61+H61+F61+D61 -> -531573.44
B62: 46074 | C62: 0 | D62: 0 | E62: 0 | F62: -1391.41 | G62: 0 | H62: 0 | I62: =+I61+C62+E62+G62+H62+F62+D62 -> -532964.85
B63: 46075 | C63: 0 | D63: 0 | E63: 0 | F63: -3304.59 | G63: 0 | H63: 0 | I63: =+I62+C63+E63+G63+H63+F63+D63 -> -536269.44
B64: 46076 | C64: 0 | D64: 0 | E64: 0 | F64: -2974.54 | G64: 0 | H64: 0 | I64: =+I63+C64+E64+G64+H64+F64+D64 -> -539243.98
B65: 46077 | C65: 0 | D65: 0 | E65: 0 | F65: -6603.3 | G65: 0 | H65: 0 | I65: =+I64+C65+E65+G65+H65+F65+D65 -> -545847.28
B66: 46078 | C66: 0 | D66: 0 | E66: 0 | F66: -7000.53 | G66: 0 | H66: 0 | I66: =+I65+C66+E66+G66+H66+F66+D66 -> -552847.81
B67: 46079 | C67: 0 | D67: 0 | E67: 0 | F67: -3165.09 | G67: 0 | H67: 0 | I67: =+I66+C67+E67+G67+H67+F67+D67 -> -556012.9
B68: 46080 | C68: 0 | D68: 0 | E68: 0 | F68: =-(1000+3506.08) -> -4506.08 | G68: 0 | H68: 0 | I68: =+I67+C68+E68+G68+H68+F68+D68 -> -560518.98
B69: 46081 | C69: 0 | D69: 0 | E69: 0 | F69: -4353.33 | G69: 0 | H69: 0 | I69: =+I68+C69+E69+G69+H69+F69+D69 -> -564872.31
B70: TOTAL | C70: =SUM(C42:C69) -> 0 | E70: =SUM(E42:E69) -> 0 | F70: =SUM(F42:F69) -> -240139.27 | H70: =SUM(H42:H69) -> 0
B72: Março-26
B73: DATA
C74: Entradas Realizadas | D74: Resgate apl | E74: Aporte Propietario | F74: Despesas realizadas | G74: Aplicação | H74: Shareholder Remuneration | I74: Saldo do dia
I75: =I69 -> -564872.31
B76: 46082 | C76: 0 | D76: 0 | E76: 0 | F76: 0 | G76: 0 | H76: 0 | I76: =+I75+C76+E76+G76+H76+F76+D76 -> -564872.31
B77: 46083 | C77: 0 | D77: 0 | E77: 0 | F77: 0 | G77: 0 | H77: 0 | I77: =+I76+C77+E77+G77+H77+F77+D77 -> -564872.31
B78: 46084 | C78: 0 | D78: 0 | E78: 0 | F78: 0 | G78: 0 | H78: 0 | I78: =+I77+C78+E78+G78+H78+F78+D78 -> -564872.31
B79: 46085 | C79: 0 | D79: 0 | E79: 0 | F79: 0 | G79: 0 | H79: 0 | I79: =+I78+C79+E79+G79+H79+F79+D79 -> -564872.31
B80: 46086 | C80: 0 | D80: 0 | E80: 0 | F80: =-(9779+17000+2000) -> -28779 | G80: 0 | H80: 0 | I80: =+I79+C80+E80+G80+H80+F80+D80 -> -593651.31
B81: 46087 | C81: 0 | D81: 0 | E81: 0 | F81: 0 | G81: 0 | H81: 0 | I81: =+I80+C81+E81+G81+H81+F81+D81 -> -593651.31
B82: 46088 | C82: 0 | D82: 0 | E82: 0 | F82: 0 | G82: 0 | H82: 0 | I82: =+I81+C82+E82+G82+H82+F82+D82 -> -593651.31
B83: 46089 | C83: 0 | D83: 0 | E83: 0 | F83: 0 | G83: 0 | H83: 0 | I83: =+I82+C83+E83+G83+H83+F83+D83 -> -593651.31
B84: 46090 | C84: 0 | D84: 0 | E84: 0 | F84: 0 | G84: 0 | H84: 0 | I84: =+I83+C84+E84+G84+H84+F84+D84 -> -593651.31
B85: 46091 | C85: 0 | D85: 0 | E85: 0 | F85: =-(2150+850+250+5000+3000) -> -11250 | G85: 0 | H85: 0 | I85: =+I84+C85+E85+G85+H85+F85+D85 -> -604901.31
B86: 46092 | C86: 0 | D86: 0 | E86: 0 | F86: 0 | G86: 0 | H86: 0 | I86: =+I85+C86+E86+G86+H86+F86+D86 -> -604901.31
B87: 46093 | C87: 0 | D87: 0 | E87: 0 | F87: 0 | G87: 0 | H87: 0 | I87: =+I86+C87+E87+G87+H87+F87+D87 -> -604901.31
B88: 46094 | C88: 0 | D88: 0 | E88: 0 | F88: =-6602 -> -6602 | G88: 0 | H88: 0 | I88: =+I87+C88+E88+G88+H88+F88+D88 -> -611503.31
B89: 46095 | C89: 0 | D89: 0 | E89: 0 | F89: 0 | G89: 0 | H89: 0 | I89: =+I88+C89+E89+G89+H89+F89+D89 -> -611503.31
B90: 46096 | C90: 0 | D90: 0 | E90: 0 | F90: 0 | G90: 0 | H90: 0 | I90: =+I89+C90+E90+G90+H90+F90+D90 -> -611503.31
B91: 46097 | C91: 0 | D91: 0 | E91: 0 | F91: 0 | G91: 0 | H91: 0 | I91: =+I90+C91+E91+G91+H91+F91+D91 -> -611503.31
B92: 46098 | C92: 0 | D92: 0 | E92: 0 | F92: 0 | G92: 0 | H92: 0 | I92: =+I91+C92+E92+G92+H92+F92+D92 -> -611503.31
B93: 46099 | C93: 0 | D93: 0 | E93: 0 | F93: 0 | G93: 0 | H93: 0 | I93: =+I92+C93+E93+G93+H93+F93+D93 -> -611503.31
B94: 46100 | C94: 0 | D94: 0 | E94: 0 | F94: 0 | G94: 0 | H94: 0 | I94: =+I93+C94+E94+G94+H94+F94+D94 -> -611503.31
B95: 46101 | C95: 0 | D95: 0 | E95: 0 | F95: =-(1973+450+40000) -> -42423 | G95: 0 | H95: 0 | I95: =+I94+C95+E95+G95+H95+F95+D95 -> -653926.31
B96: 46102 | C96: 0 | D96: 0 | E96: 0 | F96: 0 | G96: 0 | H96: 0 | I96: =+I95+C96+E96+G96+H96+F96+D96 -> -653926.31
B97: 46103 | C97: 0 | D97: 0 | E97: 0 | F97: 0 | G97: 0 | H97: 0 | I97: =+I96+C97+E97+G97+H97+F97+D97 -> -653926.31
B98: 46104 | C98: 0 | D98: 0 | E98: 0 | F98: 0 | G98: 0 | H98: 0 | I98: =+I97+C98+E98+G98+H98+F98+D98 -> -653926.31
B99: 46105 | C99: 0 | D99: 0 | E99: 0 | F99: 0 | G99: 0 | H99: 0 | I99: =+I98+C99+E99+G99+H99+F99+D99 -> -653926.31
B100: 46106 | C100: 0 | D100: 0 | E100: 0 | F100: 0 | G100: 0 | H100: 0 | I100: =+I99+C100+E100+G100+H100+F100+D100 -> -653926.31
B101: 46107 | C101: 0 | D101: 0 | E101: 0 | F101: 0 | G101: 0 | H101: 0 | I101: =+I100+C101+E101+G101+H101+F101+D101 -> -653926.31
B102: 46108 | C102: 0 | D102: 0 | E102: 0 | F102: 0 | G102: 0 | H102: 0 | I102: =+I101+C102+E102+G102+H102+F102+D102 -> -653926.31
...

Sheet VIP MX
A3: VIP MX | C3: 2026 | D3: 2026 | E3: 2026 | F3: 2026 | G3: 2026 | H3: 2026 | I3: 2026 | J3: 2026 | K3: 2026 | L3: 2026 | M3: 2026 | N3: 2026 | O3: 2026
C4: jan | D4: fev | E4: mar | F4: abr | G4: mai | H4: jun | I4: jul | J4: ago | K4: set | L4: out | M4: nov | N4: dez | O4: TOTAL
A5: ENTRADAS
A6: MERCADO LIVRE - VIP | O6: =SUM(C6:N6) -> 0
A7: AMAZON - VIP | O7: =SUM(C7:N7) -> 0
A8: SHOPEE - VIP | O8: =SUM(C8:N8) -> 0
A9: LOJA FISICA - VIP | O9: =SUM(C9:N9) -> 0
O11: =SUM(C11:N11) -> 0
O12: =SUM(C12:N12) -> 0
O13: =SUM(C13:N13) -> 0
O14: =SUM(C14:N14) -> 0
A15: TOTAL DE ENTRADAS | C15: =SUM(C6:C14) -> 0 | D15: =SUM(D6:D14) -> 0 | E15: =SUM(E6:E14) -> 0 | F15: =SUM(F6:F14) -> 0 | G15: =SUM(G6:G14) -> 0 | H15: =SUM(H6:H14) -> 0 | I15: =SUM(I6:I14) -> 0 | J15: =SUM(J6:J14) -> 0 | ... N15: =SUM(N6:N14) -> 0 | O15: =SUM(C15:N15) -> 0
A17: Impostos Diretos | C17: =SUM(C18:C25) -> 0 | D17: =SUM(D18:D25) -> 0 | E17: =SUM(E18:E25) -> 0 | F17: =SUM(F18:F25) -> 0 | G17: =SUM(G18:G25) -> 0 | H17: =SUM(H18:H25) -> 0 | I17: =SUM(I18:I25) -> 0 | J17: =SUM(J18:J25) -> 0 | ... N17: =SUM(N18:N25) -> 0 | O17: =SUM(C17:N17) -> 0
A18: PIS | O18: =SUM(C18:N18) -> 0
A19: COFINS | B19: 0.03 | O19: =SUM(C19:N19) -> 0
A20: IPI | O20: =SUM(C20:N20) -> 0
A21: CAMBIO
A22: IOF S/INVESTIMENTO
A23: IR S/INVESTIMENTO
A24: ICMS | O24: =SUM(C24:N24) -> 0
A25: ISS | O25: =SUM(C25:N25) -> 0
A27: DESPESAS COM PESSOAL E ENCARGOS | C27: =SUM(C28,C39,C46,C51,C73,C62,C66) -> 0 | D27: =SUM(D28,D39,D46,D51,D73,D62,D66) -> 0 | E27: =SUM(E28,E39,E46,E51,E73,E62,E66) -> 0 | F27: =SUM(F28,F39,F46,F51,F73,F62,F66) -> 0 | G27: =SUM(G28,G39,G46,G51,G73,G62,G66) -> 0 | H27: =SUM(H28,H39,H46,H51,H73,H62,H66) -> 0 | I27: =SUM(I28,I39,I46,I51,I73,I62,I66) -> 0 | J27: =SUM(J28,J39,J46,J51,J73,J62,J66) -> 0 | ... N27: =SUM(N28,N39,N46,N51,N73,N62,N66) -> 0 | O27: =SUM(C27:N27) -> 0
A28: Salários diretos | C28: =SUM(C29:C38) -> 0 | D28: =SUM(D29:D38) -> 0 | E28: =SUM(E29:E38) -> 0 | F28: =SUM(F29:F38) -> 0 | G28: =SUM(G29:G38) -> 0 | H28: =SUM(H29:H38) -> 0 | I28: =SUM(I29:I38) -> 0 | J28: =SUM(J29:J38) -> 0 | ... N28: =SUM(N29:N38) -> 0 | O28: =SUM(C28:N28) -> 0
A29: Salários diretos | O29: =SUM(C29:N29) -> 0
A30: Adiantamento salarial | O30: =SUM(C30:N30) -> 0
A31: Hora extra | O31: =SUM(C31:N31) -> 0
A32: Adicional noturno | O32: =SUM(C32:N32) -> 0
A33: 13o. salário | O33: =SUM(C33:N33) -> 0
A34: Férias | O34: =SUM(C34:N34) -> 0
A35: Gratificação / prêmio | O35: =SUM(C35:N35) -> 0
A36: Comissões | O36: =SUM(C36:N36) -> 0
A37: Pensão alimentícia | O37: =SUM(C37:N37) -> 0
A38: Transporte de Funcionários | O38: =SUM(C38:N38) -> 0
A39: Encargos trabalhistas | C39: =C40+C41+C42+C43+C44+C45 -> 0 | D39: =D40+D41+D42+D43+D44+D45 -> 0 | E39: =E40+E41+E42+E43+E44+E45 -> 0 | F39: =F40+F41+F42+F43+F44+F45 -> 0 | G39: =G40+G41+G42+G43+G44+G45 -> 0 | H39: =H40+H41+H42+H43+H44+H45 -> 0 | I39: =I40+I41+I42+I43+I44+I45 -> 0 | J39: =J40+J41+J42+J43+J44+J45 -> 0 | ... N39: =N40+N41+N42+N43+N44+N45 -> 0 | O39: =SUM(C39:N39) -> 0
A40: INSS | O40: =SUM(C40:N40) -> 0
A41: FGTS | O41: =SUM(C41:N41) -> 0
A42: IRRF | O42: =SUM(C42:N42) -> 0
A43: Contribuição/taxa sindical - Empregados | O43: =SUM(C43:N43) -> 0
A44: Contribuição/taxa sindical - Empresa | O44: =SUM(C44:N44) -> 0
A45: Dep. Judicial FGTS | O45: =SUM(C45:N45) -> 0
A46: Verbas rescisórias e causas trabalhistas | C46: =C47+C48+C49+C50 -> 0 | D46: =D47+D48+D49+D50 -> 0 | E46: =E47+E48+E49+E50 -> 0 | F46: =F47+F48+F49+F50 -> 0 | G46: =G47+G48+G49+G50 -> 0 | H46: =H47+H48+H49+H50 -> 0 | I46: =I47+I48+I49+I50 -> 0 | J46: =J47+J48+J49+J50 -> 0 | ... N46: =N47+N48+N49+N50 -> 0 | O46: =SUM(C46:N46) -> 0
A47: Parcelas rescisórias (fgts, inss, etc) | O47: =SUM(C47:N47) -> 0
A48: Indenização trabalhista | O48: =SUM(C48:N48) -> 0
A49: Depósito recursal trabalhista | O49: =SUM(C49:N49) -> 0
A50: FGTS Rescisório | O50: =SUM(C50:N50) -> 0
A51: Benefícios | C51: =C52+C53+C54+C55+C56+C57+C58+C59+C60+C61 -> 0 | D51: =D52+D53+D54+D55+D56+D57+D58+D59+D60+D61 -> 0 | E51: =E52+E53+E54+E55+E56+E57+E58+E59+E60+E61 -> 0 | F51: =F52+F53+F54+F55+F56+F57+F58+F59+F60+F61 -> 0 | G51: =G52+G53+G54+G55+G56+G57+G58+G59+G60+G61 -> 0 | H51: =H52+H53+H54+H55+H56+H57+H58+H59+H60+H61 -> 0 | I51: =I52+I53+I54+I55+I56+I57+I58+I59+I60+I61 -> 0 | J51: =J52+J53+J54+J55+J56+J57+J58+J59+J60+J61 -> 0 | ... N51: =N52+N53+N54+N55+N56+N57+N58+N59+N60+N61 -> 0 | O51: =SUM(C51:N51) -> 0
A52: Vale transporte | O52: =SUM(C52:N52) -> 0
A53: Vale transporte para Empresa | O53: =SUM(C53:N53) -> 0
A54: Previdência privada | O54: =SUM(C54:N54) -> 0
A55: Uniformes | O55: =SUM(C55:N55) -> 0
A56: Ticket alimentação | O56: =SUM(C56:N56) -> 0
A57: Seguro de vida | O57: =SUM(C57:N57) -> 0
A58: Convênio médico-hospitalar | O58: =SUM(C58:N58) -> 0
A59: Convênio farmácia | O59: =SUM(C59:N59) -> 0
A60: Medicamentos e primeiros socorros | O60: =SUM(C60:N60) -> 0
A61: Convenio emprestimo consignado p/ funcionario | O61: =SUM(C61:N61) -> 0
A62: Administrativos/Financeiros | C62: =SUM(C63:C65) -> 0 | D62: =SUM(D63:D65) -> 0 | E62: =SUM(E63:E65) -> 0 | F62: =SUM(F63:F65) -> 0 | G62: =SUM(G63:G65) -> 0 | H62: =SUM(H63:H65) -> 0 | I62: =SUM(I63:I65) -> 0 | J62: =SUM(J63:J65) -> 0 | ... N62: =SUM(N63:N65) -> 0 | O62: =SUM(C62:N62) -> 0
A63: Consultorias administrativas e financeiras | O63: =SUM(C63:N63) -> 0
A64: Gestão
A65: Outras prestações de serviços administrativos e financeiros | O65: =SUM(C65:N65) -> 0
A66: Sistemas, informática e telecomunicações | C66: =SUM(C67:C72) -> 0 | D66: =SUM(D67:D72) -> 0 | E66: =SUM(E67:E72) -> 0 | F66: =SUM(F67:F72) -> 0 | G66: =SUM(G67:G72) -> 0 | H66: =SUM(H67:H72) -> 0 | I66: =SUM(I67:I72) -> 0 | J66: =SUM(J67:J72) -> 0 | ... N66: =SUM(N67:N72) -> 0 | O66: =SUM(C66:N66) -> 0
A67: Assessoria Fcamara | O67: =SUM(C67:N67) -> 0
A68: Assessoria Base 2 | O68: =SUM(C68:N68) -> 0
A69: Assessoria meta 3 | O69: =SUM(C69:N69) -> 0
A70: Assessoria Contratos PJS | O70: =SUM(C70:N70) -> 0
A71: Gestão Tecnologia | O71: =SUM(C71:N71) -> 0
A72: Outros serviços de sistemas, informática, telecomunicações | O72: =SUM(C72:N72) -> 0
A73: Outras despesas com pessoal | C73: =SUM(C74:C81) -> 0 | D73: =SUM(D74:D81) -> 0 | E73: =SUM(E74:E81) -> 0 | F73: =SUM(F74:F81) -> 0 | G73: =SUM(G74:G81) -> 0 | H73: =SUM(H74:H81) -> 0 | I73: =SUM(I74:I81) -> 0 | J73: =SUM(J74:J81) -> 0 | ... N73: =SUM(N74:N81) -> 0 | O73: =SUM(C73:N73) -> 0
A74: Laudo psicotécnico | O74: =SUM(C74:N74) -> 0
A75: Recrutamento e seleção | O75: =SUM(C75:N75) -> 0
A76: Treinamentos | O76: =SUM(C76:N76) -> 0
A77: Exame médico | O77: =SUM(C77:N77) -> 0
A78: Cipa e brigada de incêndio | O78: =SUM(C78:N78) -> 0
A79: Estagiários e cooperados | O79: =SUM(C79:N79) -> 0
A80: Serviços de portaria, limpeza, jardinagem, etc | O80: =SUM(C80:N80) -> 0
A81: Pagamento Autonômos | O81: =SUM(C81:N81) -> 0
A82: CONSULTORIAS, ASSESSORIAS ETC. | C82: =SUM(C83,C88,C92,C94,C86) -> 0 | D82: =SUM(D83,D88,D92,D94,D86) -> 0 | E82: =SUM(E83,E88,E92,E94,E86) -> 0 | F82: =SUM(F83,F88,F92,F94,F86) -> 0 | G82: =SUM(G83,G88,G92,G94,G86) -> 0 | H82: =SUM(H83,H88,H92,H94,H86) -> 0 | I82: =SUM(I83,I88,I92,I94,I86) -> 0 | J82: =SUM(J83,J88,J92,J94,J86) -> 0 | ... N82: =SUM(N83,N88,N92,N94,N86) -> 0 | O82: =SUM(C82:N82) -> 0
A83: Comercial Marketing e Comunicação | C83: =SUM(C84:C85) -> 0 | D83: =SUM(D84:D85) -> 0 | E83: =SUM(E84:E85) -> 0 | F83: =SUM(F84:F85) -> 0 | G83: =SUM(G84:G85) -> 0 | H83: =SUM(H84:H85) -> 0 | I83: =SUM(I84:I85) -> 0 | J83: =SUM(J84:J85) -> 0 | ... N83: =SUM(N84:N85) -> 0 | O83: =SUM(C83:N83) -> 0
A84: Consultoria Comercial, Marketing eComunicação | O84: =SUM(C84:N84) -> 0
A85: Prestação Serviços de Produção /Manutenção | O85: =SUM(C85:N85) -> 0
A86: JURÍDICA | C86: =SUM(C87:C87) -> 0 | D86: =SUM(D87:D87) -> 0 | E86: =SUM(E87:E87) -> 0 | F86: =SUM(F87:F87) -> 0 | G86: =SUM(G87:G87) -> 0 | H86: =SUM(H87:H87) -> 0 | I86: =SUM(I87:I87) -> 0 | J86: =SUM(J87:J87) -> 0 | ... N86: =SUM(N87:N87) -> 0 | O86: =SUM(C86:N86) -> 0
A87: Consultoria Juridica | O87: =SUM(C87:N87) -> 0
A88: Contábil, Fiscal e Tributária | C88: =SUM(C89:C91) -> 0 | D88: =SUM(D89:D91) -> 0 | E88: =SUM(E89:E91) -> 0 | F88: =SUM(F89:F91) -> 0 | G88: =SUM(G89:G91) -> 0 | H88: =SUM(H89:H91) -> 0 | I88: =SUM(I89:I91) -> 0 | J88: =SUM(J89:J91) -> 0 | ... N88: =SUM(N89:N91) -> 0 | O88: =SUM(C88:N88) -> 0
A89: Consultoria contábil, fiscal e tributária | O89: =SUM(C89:N89) -> 0
A90: Serviço Contábil (Cont. Filial) | O90: =SUM(C90:N90) -> 0
A91: Outras prestações de serviços contábeis, fiscais e tributárias | O91: =SUM(C91:N91) -> 0
A92: Despachantes | C92: =SUM(C93) -> 0 | D92: =SUM(D93) -> 0 | E92: =SUM(E93) -> 0 | F92: =SUM(F93) -> 0 | G92: =SUM(G93) -> 0 | H92: =SUM(H93) -> 0 | I92: =SUM(I93) -> 0 | J92: =SUM(J93) -> 0 | ... N92: =SUM(N93) -> 0 | O92: =SUM(C92:N92) -> 0
A93: Despachantes | O93: =SUM(C93:N93) -> 0
A94: Consultorias e Assessorias | C94: =SUM(C95:C99) -> 0 | D94: =SUM(D95:D99) -> 0 | E94: =SUM(E95:E99) -> 0 | F94: =SUM(F95:F99) -> 0 | G94: =SUM(G95:G99) -> 0 | H94: =SUM(H95:H99) -> 0 | I94: =SUM(I95:I99) -> 0 | J94: =SUM(J95:J99) -> 0 | ... N94: =SUM(N95:N99) -> 0 | O94: =SUM(C94:N94) -> 0
A95: consultoria/assessoria em gest | O95: =SUM(C95:N95) -> 0
A96: consultorias administrativas | O96: =SUM(C96:N96) -> 0
A97: consultorias financeiras | O97: =SUM(C97:N97) -> 0
A98: consultorias comerciais | O98: =SUM(C98:N98) -> 0
A99: consultorias de sistema | O99: =SUM(C99:N99) -> 0
A100: DESPESAS GERAIS | C100: =SUM(C101,C112,C117,C119,C123,C126,C130,C138,C145) -> 0 | D100: =SUM(D101,D112,D117,D119,D123,D126,D130,D138,D145) -> 0 | E100: =SUM(E101,E112,E117,E119,E123,E126,E130,E138,E145) -> 0 | F100: =SUM(F101,F112,F117,F119,F123,F126,F130,F138,F145) -> 0 | G100: =SUM(G101,G112,G117,G119,G123,G126,G130,G138,G145) -> 0 | H100: =SUM(H101,H112,H117,H119,H123,H126,H130,H138,H145) -> 0 | I100: =SUM(I101,I112,I117,I119,I123,I126,I130,I138,I145) -> 0 | J100: =SUM(J101,J112,J117,J119,J123,J126,J130,J138,J145) -> 0 | ... N100: =SUM(N101,N112,N117,N119,N123,N126,N130,N138,N145) -> 0 | O100: =SUM(C100:N100) -> 0
A101: Despesas correntes | C101: =SUM(C102:C111) -> 0 | D101: =SUM(D102:D111) -> 0 | E101: =SUM(E102:E111) -> 0 | F101: =SUM(F102:F111) -> 0 | G101: =SUM(G102:G111) -> 0 | H101: =SUM(H102:H111) -> 0 | I101: =SUM(I102:I111) -> 0 | J101: =SUM(J102:J111) -> 0 | ... N101: =SUM(N102:N111) -> 0 | O101: =SUM(C101:N101) -> 0
A102: Água | O102: =SUM(C102:N102) -> 0
A103: Energia Elétrica | O103: =SUM(C103:N103) -> 0
A104: Telefonia Tacom | O104: =SUM(C104:N104) -> 0
A105: Internet, links de comunicação, etc | O105: =SUM(C105:N105) -> 0
...

Sheet VIDAL
A3: VIDAL | C3: 2026 | D3: 2026 | E3: 2026 | F3: 2026 | G3: 2026 | H3: 2026 | I3: 2026 | J3: 2026 | K3: 2026 | L3: 2026 | M3: 2026 | N3: 2026 | O3: 2026
C4: jan | D4: fev | E4: mar | F4: abr | G4: mai | H4: jun | I4: jul | J4: ago | K4: set | L4: out | M4: nov | N4: dez | O4: TOTAL
A5: ENTRADAS
A6: MERCADO LIVRE - VIDAL | M6: 0 | N6: 0 | O6: =SUM(C6:N6) -> 0
A7: AMAZON - VIDAL | O7: =SUM(C7:N7) -> 0
A8: SHOPEE - VIDAL | O8: =SUM(C8:N8) -> 0
A9: LOJA FISICA - VIDAL | O9: =SUM(C9:N9) -> 0
O11: =SUM(C11:N11) -> 0
O12: =SUM(C12:N12) -> 0
O13: =SUM(C13:N13) -> 0
O14: =SUM(C14:N14) -> 0
A15: TOTAL DE ENTRADAS | C15: =SUM(C6:C14) -> 0 | D15: =SUM(D6:D14) -> 0 | E15: =SUM(E6:E14) -> 0 | F15: =SUM(F6:F14) -> 0 | G15: =SUM(G6:G14) -> 0 | H15: =SUM(H6:H14) -> 0 | I15: =SUM(I6:I14) -> 0 | J15: =SUM(J6:J14) -> 0 | ... N15: =SUM(N6:N14) -> 0 | O15: =SUM(C15:N15) -> 0
A17: Impostos Diretos | C17: =SUM(C18:C25) -> 0 | D17: =SUM(D18:D25) -> 0 | E17: =SUM(E18:E25) -> 0 | F17: =SUM(F18:F25) -> 0 | G17: =SUM(G18:G25) -> 0 | H17: =SUM(H18:H25) -> 0 | I17: =SUM(I18:I25) -> 0 | J17: =SUM(J18:J25) -> 0 | ... N17: =SUM(N18:N25) -> 0 | O17: =SUM(C17:N17) -> 0
A18: PIS | O18: =SUM(C18:N18) -> 0
A19: COFINS | B19: 0.03 | O19: =SUM(C19:N19) -> 0
A20: IPI | O20: =SUM(C20:N20) -> 0
A21: CAMBIO
A22: IOF S/INVESTIMENTO
A23: IR S/INVESTIMENTO
A24: ICMS | O24: =SUM(C24:N24) -> 0
A25: ISS | O25: =SUM(C25:N25) -> 0
A27: DESPESAS COM PESSOAL E ENCARGOS | C27: =SUM(C28,C39,C46,C51,C73,C62,C66) -> 0 | D27: =SUM(D28,D39,D46,D51,D73,D62,D66) -> 0 | E27: =SUM(E28,E39,E46,E51,E73,E62,E66) -> 0 | F27: =SUM(F28,F39,F46,F51,F73,F62,F66) -> 0 | G27: =SUM(G28,G39,G46,G51,G73,G62,G66) -> 0 | H27: =SUM(H28,H39,H46,H51,H73,H62,H66) -> 0 | I27: =SUM(I28,I39,I46,I51,I73,I62,I66) -> 0 | J27: =SUM(J28,J39,J46,J51,J73,J62,J66) -> 0 | ... N27: =SUM(N28,N39,N46,N51,N73,N62,N66) -> 0 | O27: =SUM(C27:N27) -> 0
A28: Salários diretos | C28: =SUM(C29:C38) -> 0 | D28: =SUM(D29:D38) -> 0 | E28: =SUM(E29:E38) -> 0 | F28: =SUM(F29:F38) -> 0 | G28: =SUM(G29:G38) -> 0 | H28: =SUM(H29:H38) -> 0 | I28: =SUM(I29:I38) -> 0 | J28: =SUM(J29:J38) -> 0 | ... N28: =SUM(N29:N38) -> 0 | O28: =SUM(C28:N28) -> 0
A29: Salários diretos | O29: =SUM(C29:N29) -> 0
A30: Adiantamento salarial | O30: =SUM(C30:N30) -> 0
A31: Hora extra | O31: =SUM(C31:N31) -> 0
A32: Adicional noturno | O32: =SUM(C32:N32) -> 0
A33: 13o. salário | O33: =SUM(C33:N33) -> 0
A34: Férias | O34: =SUM(C34:N34) -> 0
A35: Gratificação / prêmio | O35: =SUM(C35:N35) -> 0
A36: Comissões | O36: =SUM(C36:N36) -> 0
A37: Pensão alimentícia | O37: =SUM(C37:N37) -> 0
A38: Transporte de Funcionários | O38: =SUM(C38:N38) -> 0
A39: Encargos trabalhistas | C39: =C40+C41+C42+C43+C44+C45 -> 0 | D39: =D40+D41+D42+D43+D44+D45 -> 0 | E39: =E40+E41+E42+E43+E44+E45 -> 0 | F39: =F40+F41+F42+F43+F44+F45 -> 0 | G39: =G40+G41+G42+G43+G44+G45 -> 0 | H39: =H40+H41+H42+H43+H44+H45 -> 0 | I39: =I40+I41+I42+I43+I44+I45 -> 0 | J39: =J40+J41+J42+J43+J44+J45 -> 0 | ... N39: =N40+N41+N42+N43+N44+N45 -> 0 | O39: =SUM(C39:N39) -> 0
A40: INSS | O40: =SUM(C40:N40) -> 0
A41: FGTS | O41: =SUM(C41:N41) -> 0
A42: IRRF | O42: =SUM(C42:N42) -> 0
A43: Contribuição/taxa sindical - Empregados | O43: =SUM(C43:N43) -> 0
A44: Contribuição/taxa sindical - Empresa | O44: =SUM(C44:N44) -> 0
A45: Dep. Judicial FGTS | O45: =SUM(C45:N45) -> 0
A46: Verbas rescisórias e causas trabalhistas | C46: =C47+C48+C49+C50 -> 0 | D46: =D47+D48+D49+D50 -> 0 | E46: =E47+E48+E49+E50 -> 0 | F46: =F47+F48+F49+F50 -> 0 | G46: =G47+G48+G49+G50 -> 0 | H46: =H47+H48+H49+H50 -> 0 | I46: =I47+I48+I49+I50 -> 0 | J46: =J47+J48+J49+J50 -> 0 | ... N46: =N47+N48+N49+N50 -> 0 | O46: =SUM(C46:N46) -> 0
A47: Parcelas rescisórias (fgts, inss, etc) | O47: =SUM(C47:N47) -> 0
A48: Indenização trabalhista | O48: =SUM(C48:N48) -> 0
A49: Depósito recursal trabalhista | O49: =SUM(C49:N49) -> 0
A50: FGTS Rescisório | O50: =SUM(C50:N50) -> 0
A51: Benefícios | C51: =C52+C53+C54+C55+C56+C57+C58+C59+C60+C61 -> 0 | D51: =D52+D53+D54+D55+D56+D57+D58+D59+D60+D61 -> 0 | E51: =E52+E53+E54+E55+E56+E57+E58+E59+E60+E61 -> 0 | F51: =F52+F53+F54+F55+F56+F57+F58+F59+F60+F61 -> 0 | G51: =G52+G53+G54+G55+G56+G57+G58+G59+G60+G61 -> 0 | H51: =H52+H53+H54+H55+H56+H57+H58+H59+H60+H61 -> 0 | I51: =I52+I53+I54+I55+I56+I57+I58+I59+I60+I61 -> 0 | J51: =J52+J53+J54+J55+J56+J57+J58+J59+J60+J61 -> 0 | ... N51: =N52+N53+N54+N55+N56+N57+N58+N59+N60+N61 -> 0 | O51: =SUM(C51:N51) -> 0
A52: Vale transporte | O52: =SUM(C52:N52) -> 0
A53: Vale transporte para Empresa | O53: =SUM(C53:N53) -> 0
A54: Previdência privada | O54: =SUM(C54:N54) -> 0
A55: Uniformes | O55: =SUM(C55:N55) -> 0
A56: Ticket alimentação | O56: =SUM(C56:N56) -> 0
A57: Seguro de vida | O57: =SUM(C57:N57) -> 0
A58: Convênio médico-hospitalar | O58: =SUM(C58:N58) -> 0
A59: Convênio farmácia | O59: =SUM(C59:N59) -> 0
A60: Medicamentos e primeiros socorros | O60: =SUM(C60:N60) -> 0
A61: Convenio emprestimo consignado p/ funcionario | O61: =SUM(C61:N61) -> 0
A62: Administrativos/Financeiros | C62: =SUM(C63:C65) -> 0 | D62: =SUM(D63:D65) -> 0 | E62: =SUM(E63:E65) -> 0 | F62: =SUM(F63:F65) -> 0 | G62: =SUM(G63:G65) -> 0 | H62: =SUM(H63:H65) -> 0 | I62: =SUM(I63:I65) -> 0 | J62: =SUM(J63:J65) -> 0 | ... N62: =SUM(N63:N65) -> 0 | O62: =SUM(C62:N62) -> 0
A63: Consultorias administrativas e financeiras | O63: =SUM(C63:N63) -> 0
A64: Gestão
A65: Outras prestações de serviços administrativos e financeiros | O65: =SUM(C65:N65) -> 0
A66: Sistemas, informática e telecomunicações | C66: =SUM(C67:C72) -> 0 | D66: =SUM(D67:D72) -> 0 | E66: =SUM(E67:E72) -> 0 | F66: =SUM(F67:F72) -> 0 | G66: =SUM(G67:G72) -> 0 | H66: =SUM(H67:H72) -> 0 | I66: =SUM(I67:I72) -> 0 | J66: =SUM(J67:J72) -> 0 | ... N66: =SUM(N67:N72) -> 0 | O66: =SUM(C66:N66) -> 0
A67: Assessoria Fcamara | O67: =SUM(C67:N67) -> 0
A68: Assessoria Base 2 | O68: =SUM(C68:N68) -> 0
A69: Assessoria meta 3 | O69: =SUM(C69:N69) -> 0
A70: Assessoria Contratos PJS | O70: =SUM(C70:N70) -> 0
A71: Gestão Tecnologia | O71: =SUM(C71:N71) -> 0
A72: Outros serviços de sistemas, informática, telecomunicações | O72: =SUM(C72:N72) -> 0
A73: Outras despesas com pessoal | C73: =SUM(C74:C81) -> 0 | D73: =SUM(D74:D81) -> 0 | E73: =SUM(E74:E81) -> 0 | F73: =SUM(F74:F81) -> 0 | G73: =SUM(G74:G81) -> 0 | H73: =SUM(H74:H81) -> 0 | I73: =SUM(I74:I81) -> 0 | J73: =SUM(J74:J81) -> 0 | ... N73: =SUM(N74:N81) -> 0 | O73: =SUM(C73:N73) -> 0
A74: Laudo psicotécnico | O74: =SUM(C74:N74) -> 0
A75: Recrutamento e seleção | O75: =SUM(C75:N75) -> 0
A76: Treinamentos | O76: =SUM(C76:N76) -> 0
A77: Exame médico | O77: =SUM(C77:N77) -> 0
A78: Cipa e brigada de incêndio | O78: =SUM(C78:N78) -> 0
A79: Estagiários e cooperados | O79: =SUM(C79:N79) -> 0
A80: Serviços de portaria, limpeza, jardinagem, etc | O80: =SUM(C80:N80) -> 0
A81: Pagamento Autonômos | O81: =SUM(C81:N81) -> 0
A82: CONSULTORIAS, ASSESSORIAS ETC. | C82: =SUM(C83,C88,C92,C94,C86) -> 0 | D82: =SUM(D83,D88,D92,D94,D86) -> 0 | E82: =SUM(E83,E88,E92,E94,E86) -> 0 | F82: =SUM(F83,F88,F92,F94,F86) -> 0 | G82: =SUM(G83,G88,G92,G94,G86) -> 0 | H82: =SUM(H83,H88,H92,H94,H86) -> 0 | I82: =SUM(I83,I88,I92,I94,I86) -> 0 | J82: =SUM(J83,J88,J92,J94,J86) -> 0 | ... N82: =SUM(N83,N88,N92,N94,N86) -> 0 | O82: =SUM(C82:N82) -> 0
A83: Comercial Marketing e Comunicação | C83: =SUM(C84:C85) -> 0 | D83: =SUM(D84:D85) -> 0 | E83: =SUM(E84:E85) -> 0 | F83: =SUM(F84:F85) -> 0 | G83: =SUM(G84:G85) -> 0 | H83: =SUM(H84:H85) -> 0 | I83: =SUM(I84:I85) -> 0 | J83: =SUM(J84:J85) -> 0 | ... N83: =SUM(N84:N85) -> 0 | O83: =SUM(C83:N83) -> 0
A84: Consultoria Comercial, Marketing eComunicação | O84: =SUM(C84:N84) -> 0
A85: Prestação Serviços de Produção /Manutenção | O85: =SUM(C85:N85) -> 0
A86: JURÍDICA | C86: =SUM(C87:C87) -> 0 | D86: =SUM(D87:D87) -> 0 | E86: =SUM(E87:E87) -> 0 | F86: =SUM(F87:F87) -> 0 | G86: =SUM(G87:G87) -> 0 | H86: =SUM(H87:H87) -> 0 | I86: =SUM(I87:I87) -> 0 | J86: =SUM(J87:J87) -> 0 | ... N86: =SUM(N87:N87) -> 0 | O86: =SUM(C86:N86) -> 0
A87: Consultoria Juridica | O87: =SUM(C87:N87) -> 0
A88: Contábil, Fiscal e Tributária | C88: =SUM(C89:C91) -> 0 | D88: =SUM(D89:D91) -> 0 | E88: =SUM(E89:E91) -> 0 | F88: =SUM(F89:F91) -> 0 | G88: =SUM(G89:G91) -> 0 | H88: =SUM(H89:H91) -> 0 | I88: =SUM(I89:I91) -> 0 | J88: =SUM(J89:J91) -> 0 | ... N88: =SUM(N89:N91) -> 0 | O88: =SUM(C88:N88) -> 0
A89: Consultoria contábil, fiscal e tributária | O89: =SUM(C89:N89) -> 0
A90: Serviço Contábil (Cont. Filial) | O90: =SUM(C90:N90) -> 0
A91: Outras prestações de serviços contábeis, fiscais e tributárias | O91: =SUM(C91:N91) -> 0
A92: Despachantes | C92: =SUM(C93) -> 0 | D92: =SUM(D93) -> 0 | E92: =SUM(E93) -> 0 | F92: =SUM(F93) -> 0 | G92: =SUM(G93) -> 0 | H92: =SUM(H93) -> 0 | I92: =SUM(I93) -> 0 | J92: =SUM(J93) -> 0 | ... N92: =SUM(N93) -> 0 | O92: =SUM(C92:N92) -> 0
A93: Despachantes | O93: =SUM(C93:N93) -> 0
A94: Consultorias e Assessorias | C94: =SUM(C95:C99) -> 0 | D94: =SUM(D95:D99) -> 0 | E94: =SUM(E95:E99) -> 0 | F94: =SUM(F95:F99) -> 0 | G94: =SUM(G95:G99) -> 0 | H94: =SUM(H95:H99) -> 0 | I94: =SUM(I95:I99) -> 0 | J94: =SUM(J95:J99) -> 0 | ... N94: =SUM(N95:N99) -> 0 | O94: =SUM(C94:N94) -> 0
A95: consultoria/assessoria em gest | O95: =SUM(C95:N95) -> 0
A96: consultorias administrativas | O96: =SUM(C96:N96) -> 0
A97: consultorias financeiras | O97: =SUM(C97:N97) -> 0
A98: consultorias comerciais | O98: =SUM(C98:N98) -> 0
A99: consultorias de sistema | O99: =SUM(C99:N99) -> 0
A100: DESPESAS GERAIS | C100: =SUM(C101,C112,C117,C119,C123,C126,C130,C138,C145) -> 0 | D100: =SUM(D101,D112,D117,D119,D123,D126,D130,D138,D145) -> 0 | E100: =SUM(E101,E112,E117,E119,E123,E126,E130,E138,E145) -> 0 | F100: =SUM(F101,F112,F117,F119,F123,F126,F130,F138,F145) -> 0 | G100: =SUM(G101,G112,G117,G119,G123,G126,G130,G138,G145) -> 0 | H100: =SUM(H101,H112,H117,H119,H123,H126,H130,H138,H145) -> 0 | I100: =SUM(I101,I112,I117,I119,I123,I126,I130,I138,I145) -> 0 | J100: =SUM(J101,J112,J117,J119,J123,J126,J130,J138,J145) -> 0 | ... N100: =SUM(N101,N112,N117,N119,N123,N126,N130,N138,N145) -> 0 | O100: =SUM(C100:N100) -> 0
A101: Despesas correntes | C101: =SUM(C102:C111) -> 0 | D101: =SUM(D102:D111) -> 0 | E101: =SUM(E102:E111) -> 0 | F101: =SUM(F102:F111) -> 0 | G101: =SUM(G102:G111) -> 0 | H101: =SUM(H102:H111) -> 0 | I101: =SUM(I102:I111) -> 0 | J101: =SUM(J102:J111) -> 0 | ... N101: =SUM(N102:N111) -> 0 | O101: =SUM(C101:N101) -> 0
A102: Água | O102: =SUM(C102:N102) -> 0
A103: Energia Elétrica | O103: =SUM(C103:N103) -> 0
A104: Telefonia Tacom | O104: =SUM(C104:N104) -> 0
A105: Internet, links de comunicação, etc | O105: =SUM(C105:N105) -> 0
...

Sheet V3
A3: V3 | C3: 2026 | D3: 2026 | E3: 2026 | F3: 2026 | G3: 2026 | H3: 2026 | I3: 2026 | J3: 2026 | K3: 2026 | L3: 2026 | M3: 2026 | N3: 2026 | O3: 2026
C4: jan | D4: fev | E4: mar | F4: abr | G4: mai | H4: jun | I4: jul | J4: ago | K4: set | L4: out | M4: nov | N4: dez | O4: TOTAL
A5: ENTRADAS
A6: MERCADO LIVRE - V3 | O6: =SUM(C6:N6) -> 0
A7: AMAZON - V3 | O7: =SUM(C7:N7) -> 0
A8: SHOPEE - V3 | O8: =SUM(C8:N8) -> 0
A9: LOJA FISICA - V3 | O9: =SUM(C9:N9) -> 0
O11: =SUM(C11:N11) -> 0
O12: =SUM(C12:N12) -> 0
O13: =SUM(C13:N13) -> 0
O14: =SUM(C14:N14) -> 0
A15: TOTAL DE ENTRADAS | C15: =SUM(C6:C14) -> 0 | D15: =SUM(D6:D14) -> 0 | E15: =SUM(E6:E14) -> 0 | F15: =SUM(F6:F14) -> 0 | G15: =SUM(G6:G14) -> 0 | H15: =SUM(H6:H14) -> 0 | I15: =SUM(I6:I14) -> 0 | J15: =SUM(J6:J14) -> 0 | ... N15: =SUM(N6:N14) -> 0 | O15: =SUM(C15:N15) -> 0
A17: Impostos Diretos | C17: =SUM(C18:C25) -> 0 | D17: =SUM(D18:D25) -> 0 | E17: =SUM(E18:E25) -> 0 | F17: =SUM(F18:F25) -> 0 | G17: =SUM(G18:G25) -> 0 | H17: =SUM(H18:H25) -> 0 | I17: =SUM(I18:I25) -> 0 | J17: =SUM(J18:J25) -> 0 | ... N17: =SUM(N18:N25) -> 0 | O17: =SUM(C17:N17) -> 0
A18: PIS | O18: =SUM(C18:N18) -> 0
A19: COFINS | B19: 0.03 | O19: =SUM(C19:N19) -> 0
A20: IPI | O20: =SUM(C20:N20) -> 0
A21: CAMBIO
A22: IOF S/INVESTIMENTO
A23: IR S/INVESTIMENTO
A24: ICMS | O24: =SUM(C24:N24) -> 0
A25: ISS | O25: =SUM(C25:N25) -> 0
A27: DESPESAS COM PESSOAL E ENCARGOS | C27: =SUM(C28,C39,C46,C51,C73,C62,C66) -> 0 | D27: =SUM(D28,D39,D46,D51,D73,D62,D66) -> 0 | E27: =SUM(E28,E39,E46,E51,E73,E62,E66) -> 0 | F27: =SUM(F28,F39,F46,F51,F73,F62,F66) -> 0 | G27: =SUM(G28,G39,G46,G51,G73,G62,G66) -> 0 | H27: =SUM(H28,H39,H46,H51,H73,H62,H66) -> 0 | I27: =SUM(I28,I39,I46,I51,I73,I62,I66) -> 0 | J27: =SUM(J28,J39,J46,J51,J73,J62,J66) -> 0 | ... N27: =SUM(N28,N39,N46,N51,N73,N62,N66) -> 0 | O27: =SUM(C27:N27) -> 0
A28: Salários diretos | C28: =SUM(C29:C38) -> 0 | D28: =SUM(D29:D38) -> 0 | E28: =SUM(E29:E38) -> 0 | F28: =SUM(F29:F38) -> 0 | G28: =SUM(G29:G38) -> 0 | H28: =SUM(H29:H38) -> 0 | I28: =SUM(I29:I38) -> 0 | J28: =SUM(J29:J38) -> 0 | ... N28: =SUM(N29:N38) -> 0 | O28: =SUM(C28:N28) -> 0
A29: Salários diretos | O29: =SUM(C29:N29) -> 0
A30: Adiantamento salarial | O30: =SUM(C30:N30) -> 0
A31: Hora extra | O31: =SUM(C31:N31) -> 0
A32: Adicional noturno | O32: =SUM(C32:N32) -> 0
A33: 13o. salário | O33: =SUM(C33:N33) -> 0
A34: Férias | O34: =SUM(C34:N34) -> 0
A35: Gratificação / prêmio | O35: =SUM(C35:N35) -> 0
A36: Comissões | O36: =SUM(C36:N36) -> 0
A37: Pensão alimentícia | O37: =SUM(C37:N37) -> 0
A38: Transporte de Funcionários | O38: =SUM(C38:N38) -> 0
A39: Encargos trabalhistas | C39: =C40+C41+C42+C43+C44+C45 -> 0 | D39: =D40+D41+D42+D43+D44+D45 -> 0 | E39: =E40+E41+E42+E43+E44+E45 -> 0 | F39: =F40+F41+F42+F43+F44+F45 -> 0 | G39: =G40+G41+G42+G43+G44+G45 -> 0 | H39: =H40+H41+H42+H43+H44+H45 -> 0 | I39: =I40+I41+I42+I43+I44+I45 -> 0 | J39: =J40+J41+J42+J43+J44+J45 -> 0 | ... N39: =N40+N41+N42+N43+N44+N45 -> 0 | O39: =SUM(C39:N39) -> 0
A40: INSS | O40: =SUM(C40:N40) -> 0
A41: FGTS | O41: =SUM(C41:N41) -> 0
A42: IRRF | O42: =SUM(C42:N42) -> 0
A43: Contribuição/taxa sindical - Empregados | O43: =SUM(C43:N43) -> 0
A44: Contribuição/taxa sindical - Empresa | O44: =SUM(C44:N44) -> 0
A45: Dep. Judicial FGTS | O45: =SUM(C45:N45) -> 0
A46: Verbas rescisórias e causas trabalhistas | C46: =C47+C48+C49+C50 -> 0 | D46: =D47+D48+D49+D50 -> 0 | E46: =E47+E48+E49+E50 -> 0 | F46: =F47+F48+F49+F50 -> 0 | G46: =G47+G48+G49+G50 -> 0 | H46: =H47+H48+H49+H50 -> 0 | I46: =I47+I48+I49+I50 -> 0 | J46: =J47+J48+J49+J50 -> 0 | ... N46: =N47+N48+N49+N50 -> 0 | O46: =SUM(C46:N46) -> 0
A47: Parcelas rescisórias (fgts, inss, etc) | O47: =SUM(C47:N47) -> 0
A48: Indenização trabalhista | O48: =SUM(C48:N48) -> 0
A49: Depósito recursal trabalhista | O49: =SUM(C49:N49) -> 0
A50: FGTS Rescisório | O50: =SUM(C50:N50) -> 0
A51: Benefícios | C51: =C52+C53+C54+C55+C56+C57+C58+C59+C60+C61 -> 0 | D51: =D52+D53+D54+D55+D56+D57+D58+D59+D60+D61 -> 0 | E51: =E52+E53+E54+E55+E56+E57+E58+E59+E60+E61 -> 0 | F51: =F52+F53+F54+F55+F56+F57+F58+F59+F60+F61 -> 0 | G51: =G52+G53+G54+G55+G56+G57+G58+G59+G60+G61 -> 0 | H51: =H52+H53+H54+H55+H56+H57+H58+H59+H60+H61 -> 0 | I51: =I52+I53+I54+I55+I56+I57+I58+I59+I60+I61 -> 0 | J51: =J52+J53+J54+J55+J56+J57+J58+J59+J60+J61 -> 0 | ... N51: =N52+N53+N54+N55+N56+N57+N58+N59+N60+N61 -> 0 | O51: =SUM(C51:N51) -> 0
A52: Vale transporte | O52: =SUM(C52:N52) -> 0
A53: Vale transporte para Empresa | O53: =SUM(C53:N53) -> 0
A54: Previdência privada | O54: =SUM(C54:N54) -> 0
A55: Uniformes | O55: =SUM(C55:N55) -> 0
A56: Ticket alimentação | O56: =SUM(C56:N56) -> 0
A57: Seguro de vida | O57: =SUM(C57:N57) -> 0
A58: Convênio médico-hospitalar | O58: =SUM(C58:N58) -> 0
A59: Convênio farmácia | O59: =SUM(C59:N59) -> 0
A60: Medicamentos e primeiros socorros | O60: =SUM(C60:N60) -> 0
A61: Convenio emprestimo consignado p/ funcionario | O61: =SUM(C61:N61) -> 0
A62: Administrativos/Financeiros | C62: =SUM(C63:C65) -> 0 | D62: =SUM(D63:D65) -> 0 | E62: =SUM(E63:E65) -> 0 | F62: =SUM(F63:F65) -> 0 | G62: =SUM(G63:G65) -> 0 | H62: =SUM(H63:H65) -> 0 | I62: =SUM(I63:I65) -> 0 | J62: =SUM(J63:J65) -> 0 | ... N62: =SUM(N63:N65) -> 0 | O62: =SUM(C62:N62) -> 0
A63: Consultorias administrativas e financeiras | O63: =SUM(C63:N63) -> 0
A64: Gestão
A65: Outras prestações de serviços administrativos e financeiros | O65: =SUM(C65:N65) -> 0
A66: Sistemas, informática e telecomunicações | C66: =SUM(C67:C72) -> 0 | D66: =SUM(D67:D72) -> 0 | E66: =SUM(E67:E72) -> 0 | F66: =SUM(F67:F72) -> 0 | G66: =SUM(G67:G72) -> 0 | H66: =SUM(H67:H72) -> 0 | I66: =SUM(I67:I72) -> 0 | J66: =SUM(J67:J72) -> 0 | ... N66: =SUM(N67:N72) -> 0 | O66: =SUM(C66:N66) -> 0
A67: Assessoria Fcamara | O67: =SUM(C67:N67) -> 0
A68: Assessoria Base 2 | O68: =SUM(C68:N68) -> 0
A69: Assessoria meta 3 | O69: =SUM(C69:N69) -> 0
A70: Assessoria Contratos PJS | O70: =SUM(C70:N70) -> 0
A71: Gestão Tecnologia | O71: =SUM(C71:N71) -> 0
A72: Outros serviços de sistemas, informática, telecomunicações | O72: =SUM(C72:N72) -> 0
A73: Outras despesas com pessoal | C73: =SUM(C74:C81) -> 0 | D73: =SUM(D74:D81) -> 0 | E73: =SUM(E74:E81) -> 0 | F73: =SUM(F74:F81) -> 0 | G73: =SUM(G74:G81) -> 0 | H73: =SUM(H74:H81) -> 0 | I73: =SUM(I74:I81) -> 0 | J73: =SUM(J74:J81) -> 0 | ... N73: =SUM(N74:N81) -> 0 | O73: =SUM(C73:N73) -> 0
A74: Laudo psicotécnico | O74: =SUM(C74:N74) -> 0
A75: Recrutamento e seleção | O75: =SUM(C75:N75) -> 0
A76: Treinamentos | O76: =SUM(C76:N76) -> 0
A77: Exame médico | O77: =SUM(C77:N77) -> 0
A78: Cipa e brigada de incêndio | O78: =SUM(C78:N78) -> 0
A79: Estagiários e cooperados | O79: =SUM(C79:N79) -> 0
A80: Serviços de portaria, limpeza, jardinagem, etc | O80: =SUM(C80:N80) -> 0
A81: Pagamento Autonômos | O81: =SUM(C81:N81) -> 0
A82: CONSULTORIAS, ASSESSORIAS ETC. | C82: =SUM(C83,C88,C92,C94,C86) -> 0 | D82: =SUM(D83,D88,D92,D94,D86) -> 0 | E82: =SUM(E83,E88,E92,E94,E86) -> 0 | F82: =SUM(F83,F88,F92,F94,F86) -> 0 | G82: =SUM(G83,G88,G92,G94,G86) -> 0 | H82: =SUM(H83,H88,H92,H94,H86) -> 0 | I82: =SUM(I83,I88,I92,I94,I86) -> 0 | J82: =SUM(J83,J88,J92,J94,J86) -> 0 | ... N82: =SUM(N83,N88,N92,N94,N86) -> 0 | O82: =SUM(C82:N82) -> 0
A83: Comercial Marketing e Comunicação | C83: =SUM(C84:C85) -> 0 | D83: =SUM(D84:D85) -> 0 | E83: =SUM(E84:E85) -> 0 | F83: =SUM(F84:F85) -> 0 | G83: =SUM(G84:G85) -> 0 | H83: =SUM(H84:H85) -> 0 | I83: =SUM(I84:I85) -> 0 | J83: =SUM(J84:J85) -> 0 | ... N83: =SUM(N84:N85) -> 0 | O83: =SUM(C83:N83) -> 0
A84: Consultoria Comercial, Marketing eComunicação | O84: =SUM(C84:N84) -> 0
A85: Prestação Serviços de Produção /Manutenção | O85: =SUM(C85:N85) -> 0
A86: JURÍDICA | C86: =SUM(C87:C87) -> 0 | D86: =SUM(D87:D87) -> 0 | E86: =SUM(E87:E87) -> 0 | F86: =SUM(F87:F87) -> 0 | G86: =SUM(G87:G87) -> 0 | H86: =SUM(H87:H87) -> 0 | I86: =SUM(I87:I87) -> 0 | J86: =SUM(J87:J87) -> 0 | ... N86: =SUM(N87:N87) -> 0 | O86: =SUM(C86:N86) -> 0
A87: Consultoria Juridica | O87: =SUM(C87:N87) -> 0
A88: Contábil, Fiscal e Tributária | C88: =SUM(C89:C91) -> 0 | D88: =SUM(D89:D91) -> 0 | E88: =SUM(E89:E91) -> 0 | F88: =SUM(F89:F91) -> 0 | G88: =SUM(G89:G91) -> 0 | H88: =SUM(H89:H91) -> 0 | I88: =SUM(I89:I91) -> 0 | J88: =SUM(J89:J91) -> 0 | ... N88: =SUM(N89:N91) -> 0 | O88: =SUM(C88:N88) -> 0
A89: Consultoria contábil, fiscal e tributária | O89: =SUM(C89:N89) -> 0
A90: Serviço Contábil (Cont. Filial) | O90: =SUM(C90:N90) -> 0
A91: Outras prestações de serviços contábeis, fiscais e tributárias | O91: =SUM(C91:N91) -> 0
A92: Despachantes | C92: =SUM(C93) -> 0 | D92: =SUM(D93) -> 0 | E92: =SUM(E93) -> 0 | F92: =SUM(F93) -> 0 | G92: =SUM(G93) -> 0 | H92: =SUM(H93) -> 0 | I92: =SUM(I93) -> 0 | J92: =SUM(J93) -> 0 | ... N92: =SUM(N93) -> 0 | O92: =SUM(C92:N92) -> 0
A93: Despachantes | O93: =SUM(C93:N93) -> 0
A94: Consultorias e Assessorias | C94: =SUM(C95:C99) -> 0 | D94: =SUM(D95:D99) -> 0 | E94: =SUM(E95:E99) -> 0 | F94: =SUM(F95:F99) -> 0 | G94: =SUM(G95:G99) -> 0 | H94: =SUM(H95:H99) -> 0 | I94: =SUM(I95:I99) -> 0 | J94: =SUM(J95:J99) -> 0 | ... N94: =SUM(N95:N99) -> 0 | O94: =SUM(C94:N94) -> 0
A95: consultoria/assessoria em gest | O95: =SUM(C95:N95) -> 0
A96: consultorias administrativas | O96: =SUM(C96:N96) -> 0
A97: consultorias financeiras | O97: =SUM(C97:N97) -> 0
A98: consultorias comerciais | O98: =SUM(C98:N98) -> 0
A99: consultorias de sistema | O99: =SUM(C99:N99) -> 0
A100: DESPESAS GERAIS | C100: =SUM(C101,C112,C117,C119,C123,C126,C130,C138,C145) -> 0 | D100: =SUM(D101,D112,D117,D119,D123,D126,D130,D138,D145) -> 0 | E100: =SUM(E101,E112,E117,E119,E123,E126,E130,E138,E145) -> 0 | F100: =SUM(F101,F112,F117,F119,F123,F126,F130,F138,F145) -> 0 | G100: =SUM(G101,G112,G117,G119,G123,G126,G130,G138,G145) -> 0 | H100: =SUM(H101,H112,H117,H119,H123,H126,H130,H138,H145) -> 0 | I100: =SUM(I101,I112,I117,I119,I123,I126,I130,I138,I145) -> 0 | J100: =SUM(J101,J112,J117,J119,J123,J126,J130,J138,J145) -> 0 | ... N100: =SUM(N101,N112,N117,N119,N123,N126,N130,N138,N145) -> 0 | O100: =SUM(C100:N100) -> 0
A101: Despesas correntes | C101: =SUM(C102:C111) -> 0 | D101: =SUM(D102:D111) -> 0 | E101: =SUM(E102:E111) -> 0 | F101: =SUM(F102:F111) -> 0 | G101: =SUM(G102:G111) -> 0 | H101: =SUM(H102:H111) -> 0 | I101: =SUM(I102:I111) -> 0 | J101: =SUM(J102:J111) -> 0 | ... N101: =SUM(N102:N111) -> 0 | O101: =SUM(C101:N101) -> 0
A102: Água | O102: =SUM(C102:N102) -> 0
A103: Energia Elétrica | O103: =SUM(C103:N103) -> 0
A104: Telefonia Tacom | O104: =SUM(C104:N104) -> 0
A105: Internet, links de comunicação, etc | O105: =SUM(C105:N105) -> 0
...

Sheet Fluxo De caixa - VIP 12-2025
B1: DEZEMBRO-2025
B2: DATA
C3: Entradas Realizadas | D3: Resgate apl | E3: Aporte Propietario | F3: Despesas realizadas | G3: Aplicação | H3: Shareholder Remuneration | I3: Saldo do dia
I4: =30408.29+4336.3 -> 34744.59
B5: 46013 | C5: 45000 | D5: 0 | E5: 0 | F5: =-(29955.91+28232.08+600) -> -58787.99 | G5: 0 | H5: 0 | I5: =+I4+C5+E5+G5+H5+F5+D5 -> 20956.6
B6: 46014 | C6: 0 | D6: 0 | E6: 0 | F6: -6927.9 | G6: 0 | H6: 0 | I6: =+I5+C6+E6+G6+H6+F6+D6 -> 14028.7
B7: 46015 | C7: 0 | D7: 0 | E7: 0 | F7: -6890.19 | G7: 0 | H7: 0 | I7: =+I6+C7+E7+G7+H7+F7+D7 -> 7138.51
B8: 46016 | C8: 0 | D8: 0 | E8: 0 | F8: -10708.48 | G8: 0 | H8: 0 | I8: =+I7+C8+E8+G8+H8+F8+D8 -> -3569.97
B9: 46017 | C9: 0 | D9: 0 | E9: 0 | F9: -10740.8 | G9: 0 | H9: 0 | I9: =+I8+C9+E9+G9+H9+F9+D9 -> -14310.77
B10: 46018 | C10: 0 | D10: 0 | E10: 0 | F10: -9988.89 | G10: 0 | H10: 0 | I10: =+I9+C10+E10+G10+H10+F10+D10 -> -24299.66
B11: 46019 | C11: 0 | D11: 0 | E11: 0 | F11: -4414.47 | G11: 0 | H11: 0 | I11: =+I10+C11+E11+G11+H11+F11+D11 -> -28714.13
B12: 46020 | C12: =30147.01+33984.23 -> 64131.24 | D12: 0 | E12: 0 | F12: -10476.48 | G12: 0 | H12: 0 | I12: =+I11+C12+E12+G12+H12+F12+D12 -> 24940.63
B13: 46021 | C13: 0 | D13: 0 | E13: 0 | F13: =-(1000+11215.16) -> -12215.16 | G13: 0 | H13: 0 | I13: =+I12+C13+E13+G13+H13+F13+D13 -> 12725.47
B14: 46022 | C14: 0 | D14: 0 | E14: 0 | F14: -8066.43 | G14: 0 | H14: 0 | I14: =+I13+C14+E14+G14+H14+F14+D14 -> 4659.04
B15: TOTAL | C15: =SUM(C6:C14) -> 64131.24 | E15: =SUM(E6:E14) -> 0 | F15: =SUM(F6:F14) -> -80428.8 | G15: =SUM(G6:G14) -> 0 | H15: =SUM(H6:H14) -> 0

Sheet Ações 2026
B3: AÇÕES IMPORTANTES
B5: Mês | C5: Ação | D5: Status | E5: Definição | F5: Gasto Previsto | G5: Gasto Realizado
B7: 46023 | C7: Definição da contabilidade | D7: Finalizado | E7: Manter a contabilidade atual até o fim de Junho. | F7: 0 | G7: 0
B8: 46023 | C8: Definição de instituição bancaria para o Grupo | D8: Finalizado | E8: Brasil e Sicoob | F8: 0 | G8: 0
B9: 46023 | C9: Abertura de Conta VIP | D9: Finalizado | E9: Banco Brasil | F9: 0 | G9: 0
B10: 46023 | C10: Abertura de Conta Vidal | D10: Finalizado | E10: Banco Sicoob | F10: 0 | G10: 0
B11: 46023 | C11: Definição de empresa de alavancagem de vendas ML | D11: Não Iniciado | F11: 0 | G11: 0
B12: 46023 | C12: Preparação novo colaborador | D12: Não Iniciado | F12: =180+230+900+150 -> 1460 | G12: 0
B13: 46023 | C13: Criação e Validação do Relatorio de vendas | D13: Não Iniciado | F13: 0 | G13: 0
B14: 46023 | C14: Fechamento Caixa LF | D14: Não Iniciado | F14: 0 | G14: 0
B15: 46023 | C15: Alteração ponto Fisico de Vip para Vidal | D15: Não Iniciado | E15: Vidal para Dolomita5 | F15: 0 | G15: 0
B16: 46023 | C16: Criação perfil vaga de Auxiliar administrativo | D16: Não Iniciado | F16: 0 | G16: 0
B17: 46023 | C17: Validação com o Bling processo de estoque | D17: Não Iniciado | F17: 0 | G17: 0
B18: 46054 | C18: Implementar Registro de Ponto | D18: Não Iniciado | F18: 250 | G18: 0
F19: =SUM(F7:F18) -> 1710 | G19: =SUM(G7:G18) -> 0
B21: 46054 | C21: Processo Seletivo Novo Colaborador | D21: Não Iniciado | F21: 0 | G21: 0
B22: 46054 | C22: Contratação | D22: Não Iniciado | F22: 0 | G22: 0
B23: 46054 | C23: Inventario Estoque | D23: Não Iniciado | F23: 0 | G23: 0
B24: 46054 | C24: Separação Estoque VIP e VIDAL | D24: Não Iniciado | F24: 0 | G24: 0
B25: 46054 | C25: Definição de Metas - Equipe | D25: Não Iniciado | F25: 0 | G25: 0
F30: =SUM(F21:F29) -> 0 | G30: =SUM(G21:G29) -> 0

Sheet Divida Fornecedores
B2: CONTAS PAGAS | K2: CONTAS A PAGAR
B4: VIP | F4: VIDAL | K4: VIP | O4: VIDAL
B6: Mês | C6: Valor | F6: Mês | G6: Valor | K6: Mês | L6: Valor | O6: Mês | P6: Valor
B7: 46023 | C7: 252772.95 | F7: 46023 | G7: 0 | K7: 46023 | L7: 0 | O7: 46023 | P7: 0
B8: 46054 | C8: 228525.11 | F8: 46054 | G8: 3059 | K8: 46054 | L8: 0 | O8: 46054 | P8: 0
B9: 46082 | C9: 268703.5 | F9: 46082 | G9: 10570.07 | K9: 46082 | L9: 0 | O9: 46082 | P9: 1116.63
B10: 46113 | C10: 223982.07 | F10: 46113 | G10: 30495.45 | K10: 46113 | L10: 0 | O10: 46113 | P10: 0
B11: 46143 | C11: 319945.38 | F11: 46143 | G11: 52752.71 | K11: 46143 | L11: 0 | O11: 46143 | P11: 0
B12: 46174 | C12: 71959.33 | F12: 46174 | G12: 4702.05 | K12: 46174 | L12: 242737.6 | O12: 46174 | P12: 34120.22
B13: 46204 | C13: 0 | F13: 46204 | G13: 0 | K13: 46204 | L13: 279660.9 | O13: 46204 | P13: 26388.28
B14: 46235 | C14: 0 | F14: 46235 | G14: 0 | K14: 46235 | L14: 193891.55 | O14: 46235 | P14: 0
B15: 46266 | C15: 0 | F15: 46266 | G15: 0 | K15: 46266 | L15: 112354.99 | O15: 46266 | P15: 0
B16: 46296 | C16: 0 | F16: 46296 | G16: 0 | K16: 46296 | L16: 50055.49 | O16: 46296 | P16: 0
B17: 46327 | C17: 0 | F17: 46327 | G17: 0 | K17: 46327 | L17: 18763.44 | O17: 46327 | P17: 0
B18: 46357 | C18: 0 | F18: 46357 | G18: 0 | K18: 46357 | L18: 0 | O18: 46357 | P18: 0
B19: Total: | C19: =SUM(C7:C18) -> 1365888.3 | F19: Total: | G19: =SUM(G7:G18) -> 101579.28 | K19: Total: | L19: =SUM(L7:L18) -> 897463.97 | O19: Total: | P19: =SUM(P7:P18) -> 61625.13

Sheet Feira Santana
B3: FEIRA DE SANTANA | D3: Acumulado até 2017 | E3: 2018 | F3: 2018 | G3: 2018 | H3: 2018 | I3: 2018 | J3: 2018 | K3: 2018 | L3: 2018 | M3: 2018 | N3: 2018 | O3: 2018 | P3: 2018 | Q3: 2018 | S3: Acumulado desde início do projeto
E4: jan | F4: fev | G4: mar | H4: abr | I4: mai | J4: jun | K4: jul | L4: ago | M4: set | N4: out | O4: nov | P4: dez | Q4: TOTAL
B5: ENTRADAS
B6: Módulos / Seviços | Q6: =SUM(E6:P6) -> 0 | S6: =D6+Q6 -> 0
B7: Receita de Venda de cartões | Q7: =SUM(E7:P7) -> 0 | S7: =D7+Q7 -> 0
B8: Receita de Venda de créditos | Q8: =SUM(E8:P8) -> 0 | S8: =D8+Q8 -> 0
B9: Repasse VT Direto Dealer | Q9: =SUM(E9:P9) -> 0 | S9: =D9+Q9 -> 0
B10: Comissionamento Ticket | Q10: =SUM(E10:P10) -> 0 | S10: =D10+Q10 -> 0
B11: SSA - Estudante
B12: SSA - E-commerce
B13: TOTAL DE ENTRADAS | D13: =SUM(D6:D10) -> 0 | E13: =SUM(E6:E10) -> 0 | F13: =SUM(F6:F10) -> 0 | G13: =SUM(G6:G10) -> 0 | H13: =SUM(H6:H10) -> 0 | I13: =SUM(I6:I10) -> 0 | J13: =SUM(J6:J10) -> 0 | K13: =SUM(K6:K10) -> 0 | ... P13: =SUM(P6:P10) -> 0 | Q13: =SUM(Q5:Q10) -> 0 | S13: =D13+Q13 -> 0
A15: 2.01 | B15: DESPESAS COM PESSOAL E ENCARGOS | D15: =SUM(D16,D27,D34,D39,D50) -> 0 | E15: =SUM(E16,E27,E34,E39,E50) -> 0 | F15: =SUM(F16,F27,F34,F39,F50) -> 0 | G15: =SUM(G16,G27,G34,G39,G50) -> 0 | H15: =SUM(H16,H27,H34,H39,H50) -> 0 | I15: =SUM(I16,I27,I34,I39,I50) -> 0 | J15: =SUM(J16,J27,J34,J39,J50) -> 0 | K15: =SUM(K16,K27,K34,K39,K50) -> 0 | ... Q15: =SUM(Q16,Q27,Q34,Q39,Q50) -> 0 | S15: =SUM(S16,S27,S34,S39,S50) -> 0
A16: 2.01.01 | B16: Salários diretos | D16: =SUM(D17:D26) -> 0 | E16: =SUM(E17:E26) -> 0 | F16: =SUM(F17:F26) -> 0 | G16: =SUM(G17:G26) -> 0 | H16: =SUM(H17:H26) -> 0 | I16: =SUM(I17:I26) -> 0 | J16: =SUM(J17:J26) -> 0 | K16: =SUM(K17:K26) -> 0 | ... P16: =SUM(P17:P26) -> 0 | Q16: =SUM(Q17:Q25) -> 0 | S16: =SUM(S17:S25) -> 0
A17: 2.01.01.01 | B17: Salários diretos | Q17: =SUM(E17:P17) -> 0 | S17: =D17+Q17 -> 0
A18: 2.01.01.02 | B18: Adiantamento salarial | Q18: =SUM(E18:P18) -> 0 | S18: =D18+Q18 -> 0
A19: 2.01.01.05 | B19: Hora extra | Q19: =SUM(E19:P19) -> 0 | S19: =D19+Q19 -> 0
A20: 2.01.01.06 | B20: Adicional noturno | Q20: =SUM(E20:P20) -> 0 | S20: =D20+Q20 -> 0
A21: 2.01.01.07 | B21: 13o. salário | Q21: =SUM(E21:P21) -> 0 | S21: =D21+Q21 -> 0
A22: 2.01.01.08 | B22: Férias | Q22: =SUM(E22:P22) -> 0 | S22: =D22+Q22 -> 0
A23: 2.01.01.09 | B23: Gratificação / prêmio | Q23: =SUM(E23:P23) -> 0 | S23: =D23+Q23 -> 0
A24: 2.01.01.10 | B24: Comissões | Q24: =SUM(E24:P24) -> 0 | S24: =D24+Q24 -> 0
A25: 2.01.01.11 | B25: Pensão alimentícia | Q25: =SUM(E25:P25) -> 0 | S25: =D25+Q25 -> 0
A26: 2.01.01.12 | B26: Transporte de Funcionários
A27: 2.01.02 | B27: Encargos trabalhistas | D27: =SUM(D28:D33) -> 0 | E27: =SUM(E28:E33) -> 0 | F27: =SUM(F28:F33) -> 0 | G27: =SUM(G28:G33) -> 0 | H27: =SUM(H28:H33) -> 0 | I27: =SUM(I28:I33) -> 0 | J27: =SUM(J28:J33) -> 0 | K27: =SUM(K28:K33) -> 0 | ... Q27: =SUM(Q28:Q33) -> 0 | S27: =SUM(S28:S33) -> 0
A28: 2.01.02.01 | B28: INSS | Q28: =SUM(E28:P28) -> 0 | S28: =D28+Q28 -> 0
A29: 2.01.02.03 | B29: FGTS | Q29: =SUM(E29:P29) -> 0 | S29: =D29+Q29 -> 0
A30: 2.01.02.04 | B30: IRRF | Q30: =SUM(E30:P30) -> 0 | S30: =D30+Q30 -> 0
A31: 2.01.02.05 | B31: Contribuição/taxa sindical - Empregados | Q31: =SUM(E31:P31) -> 0 | S31: =D31+Q31 -> 0
A32: 2.01.02.06 | B32: Contribuição/taxa sindical - Empresa | Q32: =SUM(E32:P32) -> 0 | S32: =D32+Q32 -> 0
A33: 2.01.02.07 | B33: Dep. Judicial FGTS | Q33: =SUM(E33:P33) -> 0 | S33: =D33+Q33 -> 0
A34: 2.01.03 | B34: Verbas rescisórias e causas trabalhistas | D34: =SUM(D35:D38) -> 0 | E34: =SUM(E35:E38) -> 0 | F34: =SUM(F35:F38) -> 0 | G34: =SUM(G35:G38) -> 0 | H34: =SUM(H35:H38) -> 0 | I34: =SUM(I35:I38) -> 0 | J34: =SUM(J35:J38) -> 0 | K34: =SUM(K35:K38) -> 0 | ... P34: =SUM(P35:P38) -> 0 | Q34: =SUM(Q35:Q37) -> 0 | S34: =SUM(S35:S37) -> 0
A35: 2.01.03.01 | B35: Parcelas rescisórias (fgts, inss, etc) | Q35: =SUM(E35:P35) -> 0 | S35: =D35+Q35 -> 0
A36: 2.01.03.02 | B36: Indenização trabalhista | Q36: =SUM(E36:P36) -> 0 | S36: =D36+Q36 -> 0
A37: 2.01.03.03 | B37: Depósito recursal trabalhista | Q37: =SUM(E37:P37) -> 0 | S37: =D37+Q37 -> 0
A38: 2.01.03.04 | B38: FGTS Rescisório
A39: 2.01.04 | B39: Benefícios | D39: =SUM(D40:D49) -> 0 | E39: =SUM(E40:E49) -> 0 | F39: =SUM(F40:F49) -> 0 | G39: =SUM(G40:G49) -> 0 | H39: =SUM(H40:H49) -> 0 | I39: =SUM(I40:I49) -> 0 | J39: =SUM(J40:J49) -> 0 | K39: =SUM(K40:K49) -> 0 | ... Q39: =SUM(Q40:Q49) -> 0 | S39: =SUM(S40:S49) -> 0
A40: 2.01.04.01 | B40: Vale transporte | Q40: =SUM(E40:P40) -> 0 | S40: =D40+Q40 -> 0
A41: 2.01.04.02 | B41: Vale transporte para Empresa | Q41: =SUM(E41:P41) -> 0 | S41: =D41+Q41 -> 0
A42: 2.01.04.03 | B42: Previdência privada | Q42: =SUM(E42:P42) -> 0 | S42: =D42+Q42 -> 0
A43: 2.01.04.04 | B43: Uniformes | Q43: =SUM(E43:P43) -> 0 | S43: =D43+Q43 -> 0
A44: 2.01.04.05 | B44: Ticket alimentação | Q44: =SUM(E44:P44) -> 0 | S44: =D44+Q44 -> 0
A45: 2.01.04.06 | B45: Seguro de vida | Q45: =SUM(E45:P45) -> 0 | S45: =D45+Q45 -> 0
A46: 2.01.04.07 | B46: Convênio médico-hospitalar | Q46: =SUM(E46:P46) -> 0 | S46: =D46+Q46 -> 0
A47: 2.01.04.08 | B47: Convênio farmácia | Q47: =SUM(E47:P47) -> 0 | S47: =D47+Q47 -> 0
A48: 2.01.04.10 | B48: Medicamentos e primeiros socorros | Q48: =SUM(E48:P48) -> 0 | S48: =D48+Q48 -> 0
A49: 2.01.04.11 | B49: Convenio emprestimo consignado p/ funcionario | Q49: =SUM(E49:P49) -> 0 | S49: =D49+Q49 -> 0
A50: 2.01.05 | B50: Outras despesas com pessoal | D50: =SUM(D51:D58) -> 0 | E50: =SUM(E51:E58) -> 0 | F50: =SUM(F51:F58) -> 0 | G50: =SUM(G51:G58) -> 0 | H50: =SUM(H51:H58) -> 0 | I50: =SUM(I51:I58) -> 0 | J50: =SUM(J51:J58) -> 0 | K50: =SUM(K51:K58) -> 0 | ... Q50: =SUM(Q51:Q58) -> 0 | S50: =SUM(S51:S58) -> 0
A51: 2.01.05.01 | B51: Laudo psicotécnico | Q51: =SUM(E51:P51) -> 0 | S51: =D51+Q51 -> 0
A52: 2.01.05.02 | B52: Recrutamento e seleção | Q52: =SUM(E52:P52) -> 0 | S52: =D52+Q52 -> 0
A53: 2.01.05.03 | B53: Treinamentos | Q53: =SUM(E53:P53) -> 0 | S53: =D53+Q53 -> 0
A54: 2.01.05.04 | B54: Exame médico | Q54: =SUM(E54:P54) -> 0 | S54: =D54+Q54 -> 0
A55: 2.01.05.05 | B55: Cipa e brigada de incêndio | Q55: =SUM(E55:P55) -> 0 | S55: =D55+Q55 -> 0
A56: 2.01.05.06 | B56: Estagiários e cooperados | Q56: =SUM(E56:P56) -> 0 | S56: =D56+Q56 -> 0
A57: 2.01.05.07 | B57: Serviços de portaria, limpeza, jardinagem, etc | Q57: =SUM(E57:P57) -> 0 | S57: =D57+Q57 -> 0
A58: 2.01.05.08 | B58: Pagamento Autonômos | Q58: =SUM(E58:P58) -> 0 | S58: =D58+Q58 -> 0
A59: 2.02 | B59: CONSULTORIAS, ASSESSORIAS ETC. | D59: =SUM(D60,D63,D66,D70,D73,D75) -> 0 | E59: =SUM(E60,E63,E66,E70,E73,E75) -> 0 | F59: =SUM(F60,F63,F66,F70,F73,F75) -> 0 | G59: =SUM(G60,G63,G66,G70,G73,G75) -> 0 | H59: =SUM(H60,H63,H66,H70,H73,H75) -> 0 | I59: =SUM(I60,I63,I66,I70,I73,I75) -> 0 | J59: =SUM(J60,J63,J66,J70,J73,J75) -> 0 | K59: =SUM(K60,K63,K66,K70,K73,K75) -> 0 | ... P59: =SUM(P60,P63,P66,P70,P73,P75) -> 0 | Q59: =SUM(Q60,Q66,Q70,Q73) -> 0 | S59: =SUM(S60,S66,S70,S73) -> 0
A60: 2.02.01 | B60: Sistemas, informática e telecomunicações | D60: =SUM(D61:D62) -> 0 | E60: =SUM(E61:E62) -> 0 | F60: =SUM(F61:F62) -> 0 | G60: =SUM(G61:G62) -> 0 | H60: =SUM(H61:H62) -> 0 | I60: =SUM(I61:I62) -> 0 | J60: =SUM(J61:J62) -> 0 | K60: =SUM(K61:K62) -> 0 | ... Q60: =SUM(Q61:Q62) -> 0 | S60: =SUM(S61:S62) -> 0
A61: 2.02.01.01 | B61: Consultorias de sistemas , informática e telecomunicações | Q61: =SUM(E61:P61) -> 0 | S61: =D61+Q61 -> 0
A62: 2.02.01.99 | B62: Outros serviços de sistemas, informática, telecomunicações | Q62: =SUM(E62:P62) -> 0 | S62: =D62+Q62 -> 0
A63: 2.02.04 | B63: Comercial Marketing e Comunicação | D63: =SUM(D64:D65) -> 0 | E63: =SUM(E64:E65) -> 0 | F63: =SUM(F64:F65) -> 0 | G63: =SUM(G64:G65) -> 0 | H63: =SUM(H64:H65) -> 0 | I63: =SUM(I64:I65) -> 0 | J63: =SUM(J64:J65) -> 0 | K63: =SUM(K64:K65) -> 0 | ... P63: =SUM(P64:P65) -> 0 | Q63: =SUM(E63:P63) -> 0 | S63: =D63+Q63 -> 0
A64: 2.02.04.01 | B64: Consultoria Comercial, Marketing eComunicação | Q64: =SUM(E64:P64) -> 0 | S64: =D64+Q64 -> 0
A65: 2.02.04.99 | B65: Prestação Serviços de Produção /Manutenção | Q65: =SUM(E65:P65) -> 0 | S65: =D65+Q65 -> 0
A66: 2.02.06 | B66: Contábil, Fiscal e Tributária | D66: =SUM(D67:D69) -> 0 | E66: =SUM(E67:E69) -> 0 | F66: =SUM(F67:F69) -> 0 | G66: =SUM(G67:G69) -> 0 | H66: =SUM(H67:H69) -> 0 | I66: =SUM(I67:I69) -> 0 | J66: =SUM(J67:J69) -> 0 | K66: =SUM(K67:K69) -> 0 | ... P66: =SUM(P67:P69) -> 0 | Q66: =SUM(E66:P66) -> 0 | S66: =D66+Q66 -> 0
A67: 2.02.06.01 | B67: Consultoria contábil, fiscal e tributária | Q67: =SUM(E67:P67) -> 0 | S67: =D67+Q67 -> 0
A68: 2.02.06.02 | B68: Serviço Contábil (Cont. Filial) | Q68: =SUM(E68:P68) -> 0 | S68: =D68+Q68 -> 0
A69: 2.02.06.99 | B69: Outras prestações de serviços contábeis, fiscais e tributárias | Q69: =SUM(E69:P69) -> 0 | S69: =D69+Q69 -> 0
A70: 2.02.07 | B70: Administrativos/Financeiros | D70: =SUM(D71:D72) -> 0 | E70: =SUM(E71:E72) -> 0 | F70: =SUM(F71:F72) -> 0 | G70: =SUM(G71:G72) -> 0 | H70: =SUM(H71:H72) -> 0 | I70: =SUM(I71:I72) -> 0 | J70: =SUM(J71:J72) -> 0 | K70: =SUM(K71:K72) -> 0 | ... Q70: =SUM(Q71:Q72) -> 0 | S70: =SUM(S71:S72) -> 0
A71: 2.02.07.01 | B71: Consultorias administrativas e financeiras | E71: 0 | Q71: =SUM(E71:P71) -> 0 | S71: =D71+Q71 -> 0
A72: 2.02.07.99 | B72: Outras prestações de serviços administrativos e financeiros | E72: 0 | Q72: =SUM(E72:P72) -> 0 | S72: =D72+Q72 -> 0
A73: 2.02.10 | B73: Despachantes | D73: =SUM(D74) -> 0 | E73: =SUM(E74) -> 0 | F73: =SUM(F74) -> 0 | G73: =SUM(G74) -> 0 | H73: =SUM(H74) -> 0 | I73: =SUM(I74) -> 0 | J73: =SUM(J74) -> 0 | K73: =SUM(K74) -> 0 | ... Q73: =SUM(Q74) -> 0 | S73: =SUM(S74) -> 0
A74: 2.02.10.01 | B74: Despachantes | E74: 0 | Q74: =SUM(E74:P74) -> 0 | S74: =D74+Q74 -> 0
A75: 2.02.12 | B75: Consultorias e Assessorias | D75: =SUM(D76:D80) -> 0 | E75: =SUM(E76:E80) -> 0 | F75: =SUM(F76:F80) -> 0 | G75: =SUM(G76:G80) -> 0 | H75: =SUM(H76:H80) -> 0 | I75: =SUM(I76:I80) -> 0 | J75: =SUM(J76:J80) -> 0 | K75: =SUM(K76:K80) -> 0 | ... P75: =SUM(P76:P80) -> 0 | Q75: =SUM(Q76,Q79,Q83,Q86) -> 0 | S75: =SUM(S76,S79,S83,S86) -> 0
A76: 2.02.12.01 | B76: consultoria/assessoria em gest | Q76: =SUM(E76:P76) -> 0 | S76: =D76+Q76 -> 0
A77: 2.02.13.01 | B77: consultorias administrativas | Q77: =SUM(E77:P77) -> 0 | S77: =D77+Q77 -> 0
A78: 2.02.13.02 | B78: consultorias financeiras | Q78: =SUM(E78:P78) -> 0 | S78: =D78+Q78 -> 0
A79: 2.02.13.03 | B79: consultorias comerciais | Q79: =SUM(E79:P79) -> 0 | S79: =D79+Q79 -> 0
A80: 2.02.13.04 | B80: consultorias de sistema | Q80: =SUM(E80:P80) -> 0 | S80: =D80+Q80 -> 0
A81: 2.03 | B81: DESPESAS GERAIS | D81: =SUM(D82,D93,D98,D100,D104,D107,D111,D113,D121) -> 0 | E81: =SUM(E82,E93,E98,E100,E104,E107,E111,E113,E121) -> 0 | F81: =SUM(F82,F93,F98,F100,F104,F107,F111,F113,F121) -> 0 | G81: =SUM(G82,G93,G98,G100,G104,G107,G111,G113,G121) -> 0 | H81: =SUM(H82,H93,H98,H100,H104,H107,H111,H113,H121) -> 0 | I81: =SUM(I82,I93,I98,I100,I104,I107,I111,I113,I121) -> 0 | J81: =SUM(J82,J93,J98,J100,J104,J107,J111,J113,J121) -> 0 | K81: =SUM(K82,K93,K98,K100,K104,K107,K111,K113,K121) -> 0 | ... Q81: =SUM(Q82,Q93,Q98,Q100,Q104,Q107,Q111,Q113,Q121) -> 0 | S81: =SUM(S82,S93,S98,S100,S104,S107,S111,S113,S121) -> 0
A82: 2.03.01 | B82: Despesas correntes | D82: =SUM(D83:D92) -> 0 | E82: =SUM(E83:E92) -> 0 | F82: =SUM(F83:F92) -> 0 | G82: =SUM(G83:G92) -> 0 | H82: =SUM(H83:H92) -> 0 | I82: =SUM(I83:I92) -> 0 | J82: =SUM(J83:J92) -> 0 | K82: =SUM(K83:K92) -> 0 | ... Q82: =SUM(Q83:Q92) -> 0 | S82: =SUM(S83:S92) -> 0
A83: 2.03.01.01 | B83: Água | Q83: =SUM(E83:P83) -> 0 | S83: =D83+Q83 -> 0
A84: 2.03.01.02 | B84: Energia Elétrica | Q84: =SUM(E84:P84) -> 0 | S84: =D84+Q84 -> 0
A85: 2.03.01.03 | B85: Telefonia | Q85: =SUM(E85:P85) -> 0 | S85: =D85+Q85 -> 0
A86: 2.03.01.04 | B86: Internet, links de comunicação, etc | Q86: =SUM(E86:P86) -> 0 | S86: =D86+Q86 -> 0
A87: 2.03.01.05 | B87: Correios / malotes / postagens | Q87: =SUM(E87:P87) -> 0 | S87: =D87+Q87 -> 0
A88: 2.03.01.06 | B88: Lavanderia, toalheiros, etc | Q88: =SUM(E88:P88) -> 0 | S88: =D88+Q88 -> 0
A89: 2.03.01.07 | B89: Despesas com cartório | Q89: =SUM(E89:P89) -> 0 | S89: =D89+Q89 -> 0
A90: 2.03.01.08 | B90: Material limpeza e conservação | Q90: =SUM(E90:P90) -> 0 | S90: =D90+Q90 -> 0
A91: 2.03.01.09 | B91: Lanches e alimentação | Q91: =SUM(E91:P91) -> 0 | S91: =D91+Q91 -> 0
A92: 2.03.01.99 | B92: Outras despesas gerais | Q92: =SUM(E92:P92) -> 0 | S92: =D92+Q92 -> 0
A93: 2.03.02 | B93: Material de escritório e consumo | D93: =SUM(D94:D97) -> 0 | E93: =SUM(E94:E97) -> 0 | F93: =SUM(F94:F97) -> 0 | G93: =SUM(G94:G97) -> 0 | H93: =SUM(H94:H97) -> 0 | I93: =SUM(I94:I97) -> 0 | J93: =SUM(J94:J97) -> 0 | K93: =SUM(K94:K97) -> 0 | ... Q93: =SUM(Q94:Q97) -> 0 | S93: =SUM(S94:S97) -> 0
A94: 2.03.02.01 | B94: Papelaria | Q94: =SUM(E94:P94) -> 0 | S94: =D94+Q94 -> 0
A95: 2.03.02.02 | B95: Suprimento de informática | Q95: =SUM(E95:P95) -> 0 | S95: =D95+Q95 -> 0
A96: 2.03.02.03 | B96: Fotocópias | Q96: =SUM(E96:P96) -> 0 | S96: =D96+Q96 -> 0
A97: 2.03.02.04 | B97: Material gráfico, fotográfico, etc | Q97: =SUM(E97:P97) -> 0 | S97: =D97+Q97 -> 0
A98: 2.03.03 | B98: Bens de curta duração | D98: =SUM(D99) -> 0 | E98: =SUM(E99) -> 0 | F98: =SUM(F99) -> 0 | G98: =SUM(G99) -> 0 | H98: =SUM(H99) -> 0 | I98: =SUM(I99) -> 0 | J98: =SUM(J99) -> 0 | K98: =SUM(K99) -> 0 | ... Q98: =SUM(Q99) -> 0 | S98: =SUM(S99) -> 0
A99: 2.03.03.01 | B99: Bens de curta duração | Q99: =SUM(E99:P99) -> 0 | S99: =D99+Q99 -> 0
A100: 2.03.04 | B100: Publicações, assinaturas e periódicos | D100: =SUM(D101:D103) -> 0 | E100: =SUM(E101:E103) -> 0 | F100: =SUM(F101:F103) -> 0 | G100: =SUM(G101:G103) -> 0 | H100: =SUM(H101:H103) -> 0 | I100: =SUM(I101:I103) -> 0 | J100: =SUM(J101:J103) -> 0 | K100: =SUM(K101:K103) -> 0 | ... Q100: =SUM(Q101:Q103) -> 0 | S100: =SUM(S101:S103) -> 0
A101: 2.03.04.01 | B101: Assinat. jornais, revistas, publicações e periódicos | Q101: =SUM(E101:P101) -> 0 | S101: =D101+Q101 -> 0
A102: 2.03.04.02 | B102: Compra de livros, jornais, revistas e publicações | Q102: =SUM(E102:P102) -> 0 | S102: =D102+Q102 -> 0
A103: 2.03.04.03 | B103: Compra de Editais/Concorrencias | Q103: =SUM(E103:P103) -> 0 | S103: =D103+Q103 -> 0
...

Sheet Vendas
B1: Receitas Projetadas vs realizadas
C2: COMPORTAMENTO DE VENDAS E RECEITAS - CRÉDITOS DE TRANSPORTE
C3: Previsto | D3: Realizado | E3: Previsto | F3: Realizado | G3: Previsto | H3: Realizado | I3: Previsto | J3: Realizado | K3: Previsto | L3: Realizado | M3: Previsto | N3: Realizado | O3: Previsto | P3: Realizado | Q3: Previsto | R3: Realizado | S3: Previsto | T3: Realizado | U3: Previsto | V3: Realizado | W3: Previsto | X3: Realizado | Y3: Previsto | Z3: Realizado | AA3: Realizado | BC3: Realizado
C4: 45292 | D4: 45292 | E4: 45323 | F4: 45323 | G4: 45352 | H4: 45352 | I4: 45383 | J4: 45383 | K4: 45413 | L4: 45413 | M4: 45444 | N4: 45444 | O4: 45474 | P4: 45474 | Q4: 45505 | R4: 45505 | S4: 45536 | T4: 45536 | U4: 45566 | V4: 45566 | W4: 45597 | X4: 45597 | Y4: 45627 | Z4: 45627 | AA4: 44927 | AB4: 44958 | AC4: 44986 | AD4: 45017 | AE4: 45047 | AF4: 45078 | AG4: 45108 | AH4: 45139 | AJ4: Mês 20 | AK4: Mês 21 | AL4: Mês 22 | AM4: Mês 23 | AN4: Mês 24 | AO4: Ano 2 | AP4: Mês 25 | AQ4: Mês 26 | AR4: Mês 27 | AS4: Mês 28 | AT4: Mês 29 | AU4: Mês 30 | AV4: Mês 31 | AW4: Mês 32 | AX4: Mês 33 | AY4: Mês 34 | AZ4: Mês 35 | BA4: Mês 36 | BB4: Ano 3 | BC4: 44896
B5: Salvadorcard/SSA
B6: Vendas Totais | D6: =SUM(D7:D14) -> 12478916 | F6: =SUM(F7:F14) -> 0 | H6: =SUM(H7:H14) -> 0 | J6: =SUM(J7:J14) -> 0 | L6: =SUM(L7:L14) -> 0 | N6: =SUM(N7:N14) -> 0 | P6: =SUM(P7:P14) -> 0 | R6: =SUM(R7:R14) -> 0 | T6: =SUM(T7:T14) -> 0 | V6: =SUM(V7:V14) -> 0 | X6: =SUM(X7:X14) -> 0 | Z6: =SUM(Z7:Z14) -> 0 | AA6: 0 | AB6: 0 | AC6: 0 | AD6: 0 | AE6: 0 | AF6: 0 | AG6: 0 | AH6: 0 | AJ6: 0 | AK6: 0 | AL6: 0 | AM6: 0 | AN6: 0 | AO6: 0 | AP6: 0 | AQ6: 0 | AR6: 0 | AS6: 0 | AT6: 0 | AU6: 0 | AV6: 0 | AW6: 0 | AX6: 0 | AY6: 0 | AZ6: 0 | BA6: 0 | BB6: 0 | BC6: =SUM(BC7:BC14) -> 0
B7: Vendas por meio de Pgto
A8: 0.25345 | B8: Cartão de Crédito | D8: 917226.32 | AA8: =AA6*$A$8 -> 0 | AB8: =AB6*$A$8 -> 0 | AC8: =AC6*$A$8 -> 0 | AD8: =AD6*$A$8 -> 0 | AE8: =AE6*$A$8 -> 0 | AF8: =AF6*$A$8 -> 0 | AG8: =AG6*$A$8 -> 0 | AH8: =AH6*$A$8 -> 0 | AJ8: =AJ6*$A$8 -> 0 | AK8: =AK6*$A$8 -> 0 | AL8: =AL6*$A$8 -> 0 | AM8: =AM6*$A$8 -> 0 | AN8: =AN6*$A$8 -> 0 | AO8: =SUM(AB8:AN8) -> 0 | AP8: =AP6*$A$8 -> 0 | AQ8: =AQ6*$A$8 -> 0 | AR8: =AR6*$A$8 -> 0 | AS8: =AS6*$A$8 -> 0 | AT8: =AT6*$A$8 -> 0 | AU8: =AU6*$A$8 -> 0 | AV8: =AV6*$A$8 -> 0 | AW8: =AW6*$A$8 -> 0 | ... BA8: =BA6*$A$8 -> 0 | BB8: =SUM(AP8:BA8) -> 0
A9: 0 | B9: Cartão de Débito | AA9: =AA6*$A$9 -> 0 | AB9: =AB6*$A$9 -> 0 | AC9: =AC6*$A$9 -> 0 | AD9: =AD6*$A$9 -> 0 | AE9: =AE6*$A$9 -> 0 | AF9: =AF6*$A$9 -> 0 | AG9: =AG6*$A$9 -> 0 | AH9: =AH6*$A$9 -> 0 | AJ9: =AJ6*$A$9 -> 0 | AK9: =AK6*$A$9 -> 0 | AL9: =AL6*$A$9 -> 0 | AM9: =AM6*$A$9 -> 0 | AN9: =AN6*$A$9 -> 0 | AO9: =SUM(AB9:AN9) -> 0 | AP9: =AP6*$A$9 -> 0 | AQ9: =AQ6*$A$9 -> 0 | AR9: =AR6*$A$9 -> 0 | AS9: =AS6*$A$9 -> 0 | AT9: =AT6*$A$9 -> 0 | AU9: =AU6*$A$9 -> 0 | AV9: =AV6*$A$9 -> 0 | AW9: =AW6*$A$9 -> 0 | ... BA9: =BA6*$A$9 -> 0 | BB9: =SUM(AP9:BA9) -> 0
A10: =71.058%+0.015% -> 0.71073 | B10: Pix | D10: 11561689 | AA10: =AA6*$A$10 -> 0 | AB10: =AB6*$A$10 -> 0 | AC10: =AC6*$A$10 -> 0 | AD10: =AD6*$A$10 -> 0 | AE10: =AE6*$A$10 -> 0 | AF10: =AF6*$A$10 -> 0 | AG10: =AG6*$A$10 -> 0 | AH10: =AH6*$A$10 -> 0 | AJ10: =AJ6*$A$10 -> 0 | AK10: =AK6*$A$10 -> 0 | AL10: =AL6*$A$10 -> 0 | AM10: =AM6*$A$10 -> 0 | AN10: =AN6*$A$10 -> 0 | AO10: =SUM(AB10:AN10) -> 0 | AP10: =AP6*$A$10 -> 0 | AQ10: =AQ6*$A$10 -> 0 | AR10: =AR6*$A$10 -> 0 | AS10: =AS6*$A$10 -> 0 | AT10: =AT6*$A$10 -> 0 | AU10: =AU6*$A$10 -> 0 | AV10: =AV6*$A$10 -> 0 | AW10: =AW6*$A$10 -> 0 | ... BA10: =BA6*$A$10 -> 0 | BB10: =SUM(AP10:BA10) -> 0
A11: 0 | B11: Carteira Digital KIM+ | AA11: =AA6*$A$11 -> 0 | AB11: =AB6*$A$11 -> 0 | AC11: =AC6*$A$11 -> 0 | AD11: =AD6*$A$11 -> 0 | AE11: =AE6*$A$11 -> 0 | AF11: =AF6*$A$11 -> 0 | AG11: =AG6*$A$11 -> 0 | AH11: =AH6*$A$11 -> 0 | AJ11: =AJ6*$A$11 -> 0 | AK11: =AK6*$A$11 -> 0 | AL11: =AL6*$A$11 -> 0 | AM11: =AM6*$A$11 -> 0 | AN11: =AN6*$A$11 -> 0 | AO11: =SUM(AB11:AN11) -> 0 | AP11: =AP6*$A$11 -> 0 | AQ11: =AQ6*$A$11 -> 0 | AR11: =AR6*$A$11 -> 0 | AS11: =AS6*$A$11 -> 0 | AT11: =AT6*$A$11 -> 0 | AU11: =AU6*$A$11 -> 0 | AV11: =AV6*$A$11 -> 0 | AW11: =AW6*$A$11 -> 0 | ... BA11: =BA6*$A$11 -> 0 | BB11: =SUM(AP11:BA11) -> 0
A12: 0.01438 | B12: Transferência | AA12: =AA6*$A$12 -> 0 | AB12: =AB6*$A$12 -> 0 | AC12: =AC6*$A$12 -> 0 | AD12: =AD6*$A$12 -> 0 | AE12: =AE6*$A$12 -> 0 | AF12: =AF6*$A$12 -> 0 | AG12: =AG6*$A$12 -> 0 | AH12: =AH6*$A$12 -> 0 | AJ12: =AJ6*$A$12 -> 0 | AK12: =AK6*$A$12 -> 0 | AL12: =AL6*$A$12 -> 0 | AM12: =AM6*$A$12 -> 0 | AN12: =AN6*$A$12 -> 0 | AO12: =SUM(AB12:AN12) -> 0 | AP12: =AP6*$A$12 -> 0 | AQ12: =AQ6*$A$12 -> 0 | AR12: =AR6*$A$12 -> 0 | AS12: =AS6*$A$12 -> 0 | AT12: =AT6*$A$12 -> 0 | AU12: =AU6*$A$12 -> 0 | AV12: =AV6*$A$12 -> 0 | AW12: =AW6*$A$12 -> 0 | ... BA12: =BA6*$A$12 -> 0 | BB12: =SUM(AP12:BA12) -> 0
B13: Depósito | AA13: =AA6*$A$13 -> 0 | AB13: =AB6*$A$13 -> 0 | AC13: =AC6*$A$13 -> 0 | AD13: =AD6*$A$13 -> 0 | AE13: =AE6*$A$13 -> 0 | AF13: =AF6*$A$13 -> 0 | AG13: =AG6*$A$13 -> 0 | AH13: =AH6*$A$13 -> 0 | AJ13: =AJ6*$A$13 -> 0 | AK13: =AK6*$A$13 -> 0 | AL13: =AL6*$A$13 -> 0 | AM13: =AM6*$A$13 -> 0 | AN13: =AN6*$A$13 -> 0 | AO13: =SUM(AB13:AN13) -> 0 | AP13: =AP6*$A$13 -> 0 | AQ13: =AQ6*$A$13 -> 0 | AR13: =AR6*$A$13 -> 0 | AS13: =AS6*$A$13 -> 0 | AT13: =AT6*$A$13 -> 0 | AU13: =AU6*$A$13 -> 0 | AV13: =AV6*$A$13 -> 0 | AW13: =AW6*$A$13 -> 0 | ... BA13: =BA6*$A$13 -> 0 | BB13: =SUM(AP13:BA13) -> 0
A14: 0.02081 | B14: Boleto Bancário | AA14: =AA6*$A$14 -> 0 | AB14: =AB6*$A$14 -> 0 | AC14: =AC6*$A$14 -> 0 | AD14: =AD6*$A$14 -> 0 | AE14: =AE6*$A$14 -> 0 | AF14: =AF6*$A$14 -> 0 | AG14: =AG6*$A$14 -> 0 | AH14: =AH6*$A$14 -> 0 | AJ14: =AJ6*$A$14 -> 0 | AK14: =AK6*$A$14 -> 0 | AL14: =AL6*$A$14 -> 0 | AM14: =AM6*$A$14 -> 0 | AN14: =AN6*$A$14 -> 0 | AO14: =SUM(AB14:AN14) -> 0 | AP14: =AP6*$A$14 -> 0 | AQ14: =AQ6*$A$14 -> 0 | AR14: =AR6*$A$14 -> 0 | AS14: =AS6*$A$14 -> 0 | AT14: =AT6*$A$14 -> 0 | AU14: =AU6*$A$14 -> 0 | AV14: =AV6*$A$14 -> 0 | AW14: =AW6*$A$14 -> 0 | ... BA14: =BA6*$A$14 -> 0 | BB14: =SUM(AP14:BA14) -> 0
B15: Receitas
A16: 0 | B16: Receita de Usuários | C16: =C6*$A$16 -> 0 | E16: =E6*$A$16 -> 0 | G16: =G6*$A$16 -> 0 | I16: =I6*$A$16 -> 0 | K16: =K6*$A$16 -> 0 | M16: =M6*$A$16 -> 0 | O16: =O6*$A$16 -> 0 | Q16: =Q6*$A$16 -> 0 | S16: =S6*$A$16 -> 0 | U16: =U6*$A$16 -> 0 | W16: =W6*$A$16 -> 0 | Y16: =Y6*$A$16 -> 0 | AA16: =AA6*$A$16 -> 0 | AB16: =AB6*$A$16 -> 0 | AC16: =AC6*$A$16 -> 0 | AD16: =AD6*$A$16 -> 0 | AE16: =AE6*$A$16 -> 0 | AF16: =AF6*$A$16 -> 0 | AG16: =AG6*$A$16 -> 0 | AH16: =AH6*$A$16 -> 0 | AJ16: =AJ6*$A$16 -> 0 | AK16: =AK6*$A$16 -> 0 | AL16: =AL6*$A$16 -> 0 | AM16: =AM6*$A$16 -> 0 | AN16: =AN6*$A$16 -> 0 | AO16: =SUM(AB16:AN16) -> 0 | AP16: =AP6*$A$16 -> 0 | AQ16: =AQ6*$A$16 -> 0 | AR16: =AR6*$A$16 -> 0 | AS16: =AS6*$A$16 -> 0 | AT16: =AT6*$A$16 -> 0 | AU16: =AU6*$A$16 -> 0 | AV16: =AV6*$A$16 -> 0 | AW16: =AW6*$A$16 -> 0 | ... BA16: =BA6*$A$16 -> 0 | BB16: =SUM(AP16:BA16) -> 0
A17: 0.014 | B17: Receita de Operadora | C17: =C6*$A$17 -> 0 | D17: =D6*$A$17 -> 174704.82 | E17: =E6*$A$17 -> 0 | F17: =F6*$A$17 -> 0 | G17: =G6*$A$17 -> 0 | H17: =H6*$A$17 -> 0 | I17: =I6*$A$17 -> 0 | J17: =J6*$A$17 -> 0 | ... Y17: =Y6*$A$17 -> 0 | Z17: =Z6*1.4% -> 0 | AA17: =AA6*$A$17 -> 0 | AB17: =AB6*$A$17 -> 0 | AC17: =AC6*$A$17 -> 0 | AD17: =AD6*$A$17 -> 0 | AE17: =AE6*$A$17 -> 0 | AF17: =AF6*$A$17 -> 0 | AG17: =AG6*$A$17 -> 0 | AH17: =AH6*$A$17 -> 0 | AJ17: =AJ6*$A$17 -> 0 | AK17: =AK6*$A$17 -> 0 | AL17: =AL6*$A$17 -> 0 | AM17: =AM6*$A$17 -> 0 | AN17: =AN6*$A$17 -> 0 | AO17: =SUM(AB17:AN17) -> 0 | AP17: =AP6*$A$17 -> 0 | AQ17: =AQ6*$A$17 -> 0 | AR17: =AR6*$A$17 -> 0 | AS17: =AS6*$A$17 -> 0 | AT17: =AT6*$A$17 -> 0 | AU17: =AU6*$A$17 -> 0 | AV17: =AV6*$A$17 -> 0 | AW17: =AW6*$A$17 -> 0 | ... BA17: =BA6*$A$17 -> 0 | BB17: =SUM(AP17:BA17) -> 0
B18: Receitas Totais | C18: =SUM(C16:C17) -> 0 | D18: =SUM(D16:D17) -> 174704.82 | E18: =SUM(E16:E17) -> 0 | F18: =SUM(F16:F17) -> 0 | G18: =SUM(G16:G17) -> 0 | H18: =SUM(H16:H17) -> 0 | I18: =SUM(I16:I17) -> 0 | J18: =SUM(J16:J17) -> 0 | ... AH18: =SUM(AH16:AH17) -> 0 | AJ18: =SUM(AJ16:AJ17) -> 0 | AK18: =SUM(AK16:AK17) -> 0 | AL18: =SUM(AL16:AL17) -> 0 | AM18: =SUM(AM16:AM17) -> 0 | AN18: =SUM(AN16:AN17) -> 0 | AO18: =SUM(AB18:AN18) -> 0 | AP18: =SUM(AP16:AP17) -> 0 | AQ18: =SUM(AQ16:AQ17) -> 0 | AR18: =SUM(AR16:AR17) -> 0 | AS18: =SUM(AS16:AS17) -> 0 | AT18: =SUM(AT16:AT17) -> 0 | AU18: =SUM(AU16:AU17) -> 0 | AV18: =SUM(AV16:AV17) -> 0 | AW18: =SUM(AW16:AW17) -> 0 | ... BA18: =SUM(BA16:BA17) -> 0 | BB18: =SUM(AP18:BA18) -> 0
B20: Metropasse/SSA
B21: Vendas Totais | D21: =SUM(D22:D29) -> 118036.99 | F21: =SUM(F22:F29) -> 0 | H21: =SUM(H22:H29) -> 0 | J21: =SUM(J22:J29) -> 0 | L21: =SUM(L22:L29) -> 0 | N21: =SUM(N22:N29) -> 0 | P21: =SUM(P22:P29) -> 0 | R21: =SUM(R22:R29) -> 0 | T21: =SUM(T22:T29) -> 0 | V21: =SUM(V22:V29) -> 0 | X21: =SUM(X22:X29) -> 0 | Z21: =SUM(Z22:Z29) -> 0 | AA21: 0 | AB21: 0 | AC21: 0 | AD21: 0 | AE21: 0 | AF21: 0 | AG21: 0 | AH21: 0 | AK21: #REF! | AL21: #REF! | AM21: #REF! | AN21: #REF! | AO21: #REF! | AP21: #REF! | AQ21: #REF! | AR21: #REF! | AS21: #REF! | AT21: #REF! | AU21: #REF! | AV21: #REF! | AW21: #REF! | AX21: #REF! | AY21: #REF! | AZ21: #REF! | BA21: #REF! | BB21: #REF!
B22: Vendas por meio de Pgto
A23: 0.25345 | B23: Cartão de Crédito | D23: 22979.3 | AH23: =AH21*$A$23 -> 0 | AJ23: =AJ21*$A$23 -> 0 | AK23: =AK21*$A$23 -> #REF! | AL23: =AL21*$A$23 -> #REF! | AM23: =AM21*$A$23 -> #REF! | AN23: =AN21*$A$23 -> #REF! | AO23: =SUM(AB23:AN23) -> #REF! | AP23: =AP21*$A$23 -> #REF! | AQ23: =AQ21*$A$23 -> #REF! | AR23: =AR21*$A$23 -> #REF! | AS23: =AS21*$A$23 -> #REF! | AT23: =AT21*$A$23 -> #REF! | AU23: =AU21*$A$23 -> #REF! | AV23: =AV21*$A$23 -> #REF! | AW23: =AW21*$A$23 -> #REF! | ... BA23: =BA21*$A$23 -> #REF! | BB23: =SUM(AP23:BA23) -> #REF!
A24: 0 | B24: Cartão de Débito | AH24: =AH21*$A$24 -> 0 | AJ24: =AJ21*$A$24 -> 0 | AK24: =AK21*$A$24 -> #REF! | AL24: =AL21*$A$24 -> #REF! | AM24: =AM21*$A$24 -> #REF! | AN24: =AN21*$A$24 -> #REF! | AO24: =SUM(AB24:AN24) -> #REF! | AP24: =AP21*$A$24 -> #REF! | AQ24: =AQ21*$A$24 -> #REF! | AR24: =AR21*$A$24 -> #REF! | AS24: =AS21*$A$24 -> #REF! | AT24: =AT21*$A$24 -> #REF! | AU24: =AU21*$A$24 -> #REF! | AV24: =AV21*$A$24 -> #REF! | AW24: =AW21*$A$24 -> #REF! | ... BA24: =BA21*$A$24 -> #REF! | BB24: =SUM(AP24:BA24) -> #REF!
A25: =71.058%+0.015% -> 0.71073 | B25: Pix | D25: 95057.69 | AH25: =AH21*$A$25 -> 0 | AJ25: =AJ21*$A$25 -> 0 | AK25: =AK21*$A$25 -> #REF! | AL25: =AL21*$A$25 -> #REF! | AM25: =AM21*$A$25 -> #REF! | AN25: =AN21*$A$25 -> #REF! | AO25: =SUM(AB25:AN25) -> #REF! | AP25: =AP21*$A$25 -> #REF! | AQ25: =AQ21*$A$25 -> #REF! | AR25: =AR21*$A$25 -> #REF! | AS25: =AS21*$A$25 -> #REF! | AT25: =AT21*$A$25 -> #REF! | AU25: =AU21*$A$25 -> #REF! | AV25: =AV21*$A$25 -> #REF! | AW25: =AW21*$A$25 -> #REF! | ... BA25: =BA21*$A$25 -> #REF! | BB25: =SUM(AP25:BA25) -> #REF!
A26: 0 | B26: Carteira Digital KIM+ | AH26: =AH21*$A$26 -> 0 | AJ26: =AJ21*$A$26 -> 0 | AK26: =AK21*$A$26 -> #REF! | AL26: =AL21*$A$26 -> #REF! | AM26: =AM21*$A$26 -> #REF! | AN26: =AN21*$A$26 -> #REF! | AO26: =SUM(AB26:AN26) -> #REF! | AP26: =AP21*$A$26 -> #REF! | AQ26: =AQ21*$A$26 -> #REF! | AR26: =AR21*$A$26 -> #REF! | AS26: =AS21*$A$26 -> #REF! | AT26: =AT21*$A$26 -> #REF! | AU26: =AU21*$A$26 -> #REF! | AV26: =AV21*$A$26 -> #REF! | AW26: =AW21*$A$26 -> #REF! | ... BA26: =BA21*$A$26 -> #REF! | BB26: =SUM(AP26:BA26) -> #REF!
A27: 0.01438 | B27: Transferência | AH27: =AH21*$A$27 -> 0 | AJ27: =AJ21*$A$27 -> 0 | AK27: =AK21*$A$27 -> #REF! | AL27: =AL21*$A$27 -> #REF! | AM27: =AM21*$A$27 -> #REF! | AN27: =AN21*$A$27 -> #REF! | AO27: =SUM(AB27:AN27) -> #REF! | AP27: =AP21*$A$27 -> #REF! | AQ27: =AQ21*$A$27 -> #REF! | AR27: =AR21*$A$27 -> #REF! | AS27: =AS21*$A$27 -> #REF! | AT27: =AT21*$A$27 -> #REF! | AU27: =AU21*$A$27 -> #REF! | AV27: =AV21*$A$27 -> #REF! | AW27: =AW21*$A$27 -> #REF! | ... BA27: =BA21*$A$27 -> #REF! | BB27: =SUM(AP27:BA27) -> #REF!
A28: 0.00063 | B28: Depósito | AH28: =AH21*$A$28 -> 0 | AJ28: =AJ21*$A$28 -> 0 | AK28: =AK21*$A$28 -> #REF! | AL28: =AL21*$A$28 -> #REF! | AM28: =AM21*$A$28 -> #REF! | AN28: =AN21*$A$28 -> #REF! | AO28: =SUM(AB28:AN28) -> #REF! | AP28: =AP21*$A$28 -> #REF! | AQ28: =AQ21*$A$28 -> #REF! | AR28: =AR21*$A$28 -> #REF! | AS28: =AS21*$A$28 -> #REF! | AT28: =AT21*$A$28 -> #REF! | AU28: =AU21*$A$28 -> #REF! | AV28: =AV21*$A$28 -> #REF! | AW28: =AW21*$A$28 -> #REF! | ... BA28: =BA21*$A$28 -> #REF! | BB28: =SUM(AP28:BA28) -> #REF!
A29: 0.02081 | B29: Boleto Bancário | AH29: =AH21*$A$29 -> 0 | AJ29: =AJ21*$A$29 -> 0 | AK29: =AK21*$A$29 -> #REF! | AL29: =AL21*$A$29 -> #REF! | AM29: =AM21*$A$29 -> #REF! | AN29: =AN21*$A$29 -> #REF! | AO29: =SUM(AB29:AN29) -> #REF! | AP29: =AP21*$A$29 -> #REF! | AQ29: =AQ21*$A$29 -> #REF! | AR29: =AR21*$A$29 -> #REF! | AS29: =AS21*$A$29 -> #REF! | AT29: =AT21*$A$29 -> #REF! | AU29: =AU21*$A$29 -> #REF! | AV29: =AV21*$A$29 -> #REF! | AW29: =AW21*$A$29 -> #REF! | ... BA29: =BA21*$A$29 -> #REF! | BB29: =SUM(AP29:BA29) -> #REF!
B30: Receitas
A31: 0 | B31: Receita de Usuários | C31: =C21*$A$31 -> 0 | E31: =E21*$A$31 -> 0 | G31: =G21*$A$31 -> 0 | I31: =I21*$A$31 -> 0 | K31: =K21*$A$31 -> 0 | M31: =M21*$A$31 -> 0 | O31: =O21*$A$31 -> 0 | Q31: =Q21*$A$31 -> 0 | S31: =S21*$A$31 -> 0 | U31: =U21*$A$31 -> 0 | W31: =W21*$A$31 -> 0 | Y31: =Y21*$A$31 -> 0 | AA31: =AA21*$A$31 -> 0 | AB31: =AB21*$A$31 -> 0 | AC31: =AC21*$A$31 -> 0 | AD31: =AD21*$A$31 -> 0 | AE31: =AE21*$A$31 -> 0 | AF31: =AF21*$A$31 -> 0 | AG31: =AG21*$A$31 -> 0 | AH31: =AH21*$A$31 -> 0 | AJ31: =AJ21*$A$31 -> 0 | AK31: =AK21*$A$31 -> #REF! | AL31: =AL21*$A$31 -> #REF! | AM31: =AM21*$A$31 -> #REF! | AN31: =AN21*$A$31 -> #REF! | AO31: =SUM(AB31:AN31) -> #REF! | AP31: =AP21*$A$31 -> #REF! | AQ31: =AQ21*$A$31 -> #REF! | AR31: =AR21*$A$31 -> #REF! | AS31: =AS21*$A$31 -> #REF! | AT31: =AT21*$A$31 -> #REF! | AU31: =AU21*$A$31 -> #REF! | AV31: =AV21*$A$31 -> #REF! | AW31: =AW21*$A$31 -> #REF! | ... BA31: =BA21*$A$31 -> #REF! | BB31: =SUM(AP31:BA31) -> #REF!
A32: 0.015 | B32: Receita de Operadora | C32: =C21*$A$32 -> 0 | D32: =D21*$A$32 -> 1770.5548 | E32: =E21*$A$32 -> 0 | F32: =F21*$A$32 -> 0 | G32: =G21*$A$32 -> 0 | H32: =H21*$A$32 -> 0 | I32: =I21*$A$32 -> 0 | J32: =J21*$A$32 -> 0 | ... AH32: =AH21*$A$32 -> 0 | AJ32: =AJ21*$A$32 -> 0 | AK32: =AK21*$A$32 -> #REF! | AL32: =AL21*$A$32 -> #REF! | AM32: =AM21*$A$32 -> #REF! | AN32: =AN21*$A$32 -> #REF! | AO32: =SUM(AB32:AN32) -> #REF! | AP32: =AP21*$A$32 -> #REF! | AQ32: =AQ21*$A$32 -> #REF! | AR32: =AR21*$A$32 -> #REF! | AS32: =AS21*$A$32 -> #REF! | AT32: =AT21*$A$32 -> #REF! | AU32: =AU21*$A$32 -> #REF! | AV32: =AV21*$A$32 -> #REF! | AW32: =AW21*$A$32 -> #REF! | ... BA32: =BA21*$A$32 -> #REF! | BB32: =SUM(AP32:BA32) -> #REF!
B33: Receitas Totais | C33: =SUM(C31:C32) -> 0 | D33: =SUM(D31:D32) -> 1770.5548 | E33: =SUM(E31:E32) -> 0 | F33: =SUM(F31:F32) -> 0 | G33: =SUM(G31:G32) -> 0 | H33: =SUM(H31:H32) -> 0 | I33: =SUM(I31:I32) -> 0 | J33: =SUM(J31:J32) -> 0 | ... AH33: =SUM(AH31:AH32) -> 0 | AJ33: =SUM(AJ31:AJ32) -> 0 | AK33: =SUM(AK31:AK32) -> #REF! | AL33: =SUM(AL31:AL32) -> #REF! | AM33: =SUM(AM31:AM32) -> #REF! | AN33: =SUM(AN31:AN32) -> #REF! | AO33: =SUM(AB33:AN33) -> #REF! | AP33: =SUM(AP31:AP32) -> #REF! | AQ33: =SUM(AQ31:AQ32) -> #REF! | AR33: =SUM(AR31:AR32) -> #REF! | AS33: =SUM(AS31:AS32) -> #REF! | AT33: =SUM(AT31:AT32) -> #REF! | AU33: =SUM(AU31:AU32) -> #REF! | AV33: =SUM(AV31:AV32) -> #REF! | AW33: =SUM(AW31:AW32) -> #REF! | ... BA33: =SUM(BA31:BA32) -> #REF! | BB33: =SUM(AP33:BA33) -> #REF!
B35: GVBus/VIX
B36: Vendas Totais | D36: =SUM(D37:D44) -> 1267527.9 | F36: =SUM(F37:F44) -> 0 | H36: =SUM(H37:H44) -> 0 | J36: =SUM(J37:J44) -> 0 | L36: =SUM(L37:L44) -> 0 | N36: =SUM(N37:N44) -> 0 | P36: =SUM(P37:P44) -> 0 | R36: =SUM(R37:R44) -> 0 | T36: =SUM(T37:T44) -> 0 | V36: =SUM(V37:V44) -> 0 | X36: =SUM(X37:X44) -> 0 | Z36: =SUM(Z37:Z44) -> 0 | AA36: 0 | AB36: 0 | AC36: 0 | AD36: 0 | AE36: 0 | AF36: 0 | AG36: 0 | AH36: 0 | AJ36: 0 | AK36: 0 | AL36: 0 | AM36: 0 | AN36: 0 | AO36: 0 | AP36: 0 | AQ36: 0 | AR36: 0 | AS36: 0 | AT36: 0 | AU36: 0 | AV36: 0 | AW36: 0 | AX36: 0 | AY36: 0 | AZ36: 0 | BA36: 0 | BB36: 0
B37: Vendas por meio de Pgto
A38: 0.25345 | B38: Cartão de Crédito | D38: 70690.5 | AA38: =AA36*$A$38 -> 0 | AB38: =AB36*$A$38 -> 0 | AC38: =AC36*$A$38 -> 0 | AD38: =AD36*$A$38 -> 0 | AE38: =AE36*$A$38 -> 0 | AF38: =AF36*$A$38 -> 0 | AG38: =AG36*$A$38 -> 0 | AH38: =AH36*$A$38 -> 0 | AJ38: =AJ36*$A$38 -> 0 | AK38: =AK36*$A$38 -> 0 | AL38: =AL36*$A$38 -> 0 | AM38: =AM36*$A$38 -> 0 | AN38: =AN36*$A$38 -> 0 | AO38: =SUM(AB38:AN38) -> 0 | AP38: =AP36*$A$38 -> 0 | AQ38: =AQ36*$A$38 -> 0 | AR38: =AR36*$A$38 -> 0 | AS38: =AS36*$A$38 -> 0 | AT38: =AT36*$A$38 -> 0 | AU38: =AU36*$A$38 -> 0 | AV38: =AV36*$A$38 -> 0 | AW38: =AW36*$A$38 -> 0 | ... BA38: =BA36*$A$38 -> 0 | BB38: =SUM(AP38:BA38) -> 0
A39: 0 | B39: Cartão de Débito | AA39: =AA36*$A$39 -> 0 | AB39: =AB36*$A$39 -> 0 | AC39: =AC36*$A$39 -> 0 | AD39: =AD36*$A$39 -> 0 | AE39: =AE36*$A$39 -> 0 | AF39: =AF36*$A$39 -> 0 | AG39: =AG36*$A$39 -> 0 | AH39: =AH36*$A$39 -> 0 | AJ39: =AJ36*$A$39 -> 0 | AK39: =AK36*$A$39 -> 0 | AL39: =AL36*$A$39 -> 0 | AM39: =AM36*$A$39 -> 0 | AN39: =AN36*$A$39 -> 0 | AO39: =SUM(AB39:AN39) -> 0 | AP39: =AP36*$A$39 -> 0 | AQ39: =AQ36*$A$39 -> 0 | AR39: =AR36*$A$39 -> 0 | AS39: =AS36*$A$39 -> 0 | AT39: =AT36*$A$39 -> 0 | AU39: =AU36*$A$39 -> 0 | AV39: =AV36*$A$39 -> 0 | AW39: =AW36*$A$39 -> 0 | ... BA39: =BA36*$A$39 -> 0 | BB39: =SUM(AP39:BA39) -> 0
A40: =71.058%+0.015% -> 0.71073 | B40: Pix | D40: 1196837.4 | AA40: =AA36*$A$40 -> 0 | AB40: =AB36*$A$40 -> 0 | AC40: =AC36*$A$40 -> 0 | AD40: =AD36*$A$40 -> 0 | AE40: =AE36*$A$40 -> 0 | AF40: =AF36*$A$40 -> 0 | AG40: =AG36*$A$40 -> 0 | AH40: =AH36*$A$40 -> 0 | AJ40: =AJ36*$A$40 -> 0 | AK40: =AK36*$A$40 -> 0 | AL40: =AL36*$A$40 -> 0 | AM40: =AM36*$A$40 -> 0 | AN40: =AN36*$A$40 -> 0 | AO40: =SUM(AB40:AN40) -> 0 | AP40: =AP36*$A$40 -> 0 | AQ40: =AQ36*$A$40 -> 0 | AR40: =AR36*$A$40 -> 0 | AS40: =AS36*$A$40 -> 0 | AT40: =AT36*$A$40 -> 0 | AU40: =AU36*$A$40 -> 0 | AV40: =AV36*$A$40 -> 0 | AW40: =AW36*$A$40 -> 0 | ... BA40: =BA36*$A$40 -> 0 | BB40: =SUM(AP40:BA40) -> 0
A41: 0 | B41: Carteira Digital KIM+ | AA41: =AA36*$A$41 -> 0 | AB41: =AB36*$A$41 -> 0 | AC41: =AC36*$A$41 -> 0 | AD41: =AD36*$A$41 -> 0 | AE41: =AE36*$A$41 -> 0 | AF41: =AF36*$A$41 -> 0 | AG41: =AG36*$A$41 -> 0 | AH41: =AH36*$A$41 -> 0 | AJ41: =AJ36*$A$41 -> 0 | AK41: =AK36*$A$41 -> 0 | AL41: =AL36*$A$41 -> 0 | AM41: =AM36*$A$41 -> 0 | AN41: =AN36*$A$41 -> 0 | AO41: =SUM(AB41:AN41) -> 0 | AP41: =AP36*$A$41 -> 0 | AQ41: =AQ36*$A$41 -> 0 | AR41: =AR36*$A$41 -> 0 | AS41: =AS36*$A$41 -> 0 | AT41: =AT36*$A$41 -> 0 | AU41: =AU36*$A$41 -> 0 | AV41: =AV36*$A$41 -> 0 | AW41: =AW36*$A$41 -> 0 | ... BA41: =BA36*$A$41 -> 0 | BB41: =SUM(AP41:BA41) -> 0
A42: 0.01438 | B42: Transferência | AA42: =AA36*$A$42 -> 0 | AB42: =AB36*$A$42 -> 0 | AC42: =AC36*$A$42 -> 0 | AD42: =AD36*$A$42 -> 0 | AE42: =AE36*$A$42 -> 0 | AF42: =AF36*$A$42 -> 0 | AG42: =AG36*$A$42 -> 0 | AH42: =AH36*$A$42 -> 0 | AJ42: =AJ36*$A$42 -> 0 | AK42: =AK36*$A$42 -> 0 | AL42: =AL36*$A$42 -> 0 | AM42: =AM36*$A$42 -> 0 | AN42: =AN36*$A$42 -> 0 | AO42: =SUM(AB42:AN42) -> 0 | AP42: =AP36*$A$42 -> 0 | AQ42: =AQ36*$A$42 -> 0 | AR42: =AR36*$A$42 -> 0 | AS42: =AS36*$A$42 -> 0 | AT42: =AT36*$A$42 -> 0 | AU42: =AU36*$A$42 -> 0 | AV42: =AV36*$A$42 -> 0 | AW42: =AW36*$A$42 -> 0 | ... BA42: =BA36*$A$42 -> 0 | BB42: =SUM(AP42:BA42) -> 0
A43: 0.00063 | B43: Depósito | AA43: =AA36*$A$43 -> 0 | AB43: =AB36*$A$43 -> 0 | AC43: =AC36*$A$43 -> 0 | AD43: =AD36*$A$43 -> 0 | AE43: =AE36*$A$43 -> 0 | AF43: =AF36*$A$43 -> 0 | AG43: =AG36*$A$43 -> 0 | AH43: =AH36*$A$43 -> 0 | AJ43: =AJ36*$A$43 -> 0 | AK43: =AK36*$A$43 -> 0 | AL43: =AL36*$A$43 -> 0 | AM43: =AM36*$A$43 -> 0 | AN43: =AN36*$A$43 -> 0 | AO43: =SUM(AB43:AN43) -> 0 | AP43: =AP36*$A$43 -> 0 | AQ43: =AQ36*$A$43 -> 0 | AR43: =AR36*$A$43 -> 0 | AS43: =AS36*$A$43 -> 0 | AT43: =AT36*$A$43 -> 0 | AU43: =AU36*$A$43 -> 0 | AV43: =AV36*$A$43 -> 0 | AW43: =AW36*$A$43 -> 0 | ... BA43: =BA36*$A$43 -> 0 | BB43: =SUM(AP43:BA43) -> 0
A44: 0.02081 | B44: Boleto Bancário | AA44: =AA36*$A$44 -> 0 | AB44: =AB36*$A$44 -> 0 | AC44: =AC36*$A$44 -> 0 | AD44: =AD36*$A$44 -> 0 | AE44: =AE36*$A$44 -> 0 | AF44: =AF36*$A$44 -> 0 | AG44: =AG36*$A$44 -> 0 | AH44: =AH36*$A$44 -> 0 | AJ44: =AJ36*$A$44 -> 0 | AK44: =AK36*$A$44 -> 0 | AL44: =AL36*$A$44 -> 0 | AM44: =AM36*$A$44 -> 0 | AN44: =AN36*$A$44 -> 0 | AO44: =SUM(AB44:AN44) -> 0 | AP44: =AP36*$A$44 -> 0 | AQ44: =AQ36*$A$44 -> 0 | AR44: =AR36*$A$44 -> 0 | AS44: =AS36*$A$44 -> 0 | AT44: =AT36*$A$44 -> 0 | AU44: =AU36*$A$44 -> 0 | AV44: =AV36*$A$44 -> 0 | AW44: =AW36*$A$44 -> 0 | ... BA44: =BA36*$A$44 -> 0 | BB44: =SUM(AP44:BA44) -> 0
B45: Receitas
A46: 0 | B46: Receita de Usuários | C46: =C36*$A$46 -> 0 | E46: =E36*$A$46 -> 0 | G46: =G36*$A$46 -> 0 | I46: =I36*$A$46 -> 0 | K46: =K36*$A$46 -> 0 | M46: =M36*$A$46 -> 0 | O46: =O36*$A$46 -> 0 | Q46: =Q36*$A$46 -> 0 | S46: =S36*$A$46 -> 0 | U46: =U36*$A$46 -> 0 | W46: =W36*$A$46 -> 0 | Y46: =Y36*$A$46 -> 0 | AA46: =AA36*$A$46 -> 0 | AB46: =AB36*$A$46 -> 0 | AC46: =AC36*$A$46 -> 0 | AD46: =AD36*$A$46 -> 0 | AE46: =AE36*$A$46 -> 0 | AF46: =AF36*$A$46 -> 0 | AG46: =AG36*$A$46 -> 0 | AH46: =AH36*$A$46 -> 0 | AJ46: =AJ36*$A$46 -> 0 | AK46: =AK36*$A$46 -> 0 | AL46: =AL36*$A$46 -> 0 | AM46: =AM36*$A$46 -> 0 | AN46: =AN36*$A$46 -> 0 | AO46: =SUM(AB46:AN46) -> 0 | AP46: =AP36*$A$46 -> 0 | AQ46: =AQ36*$A$46 -> 0 | AR46: =AR36*$A$46 -> 0 | AS46: =AS36*$A$46 -> 0 | AT46: =AT36*$A$46 -> 0 | AU46: =AU36*$A$46 -> 0 | AV46: =AV36*$A$46 -> 0 | AW46: =AW36*$A$46 -> 0 | ... BA46: =BA36*$A$46 -> 0 | BB46: =SUM(AP46:BA46) -> 0
A47: 0.0248 | B47: Receita de Operadora | C47: =C36*$A$47 -> 0 | D47: =D36*$A$47 -> 31434.693 | E47: =E36*$A$47 -> 0 | F47: =F36*$A$47 -> 0 | G47: =G36*$A$47 -> 0 | H47: =H36*$A$47 -> 0 | I47: =I36*$A$47 -> 0 | J47: =J36*$A$47 -> 0 | ... AH47: =AH36*$A$47 -> 0 | AJ47: =AJ36*$A$47 -> 0 | AK47: =AK36*$A$47 -> 0 | AL47: =AL36*$A$47 -> 0 | AM47: =AM36*$A$47 -> 0 | AN47: =AN36*$A$47 -> 0 | AO47: =SUM(AB47:AN47) -> 0 | AP47: =AP36*$A$47 -> 0 | AQ47: =AQ36*$A$47 -> 0 | AR47: =AR36*$A$47 -> 0 | AS47: =AS36*$A$47 -> 0 | AT47: =AT36*$A$47 -> 0 | AU47: =AU36*$A$47 -> 0 | AV47: =AV36*$A$47 -> 0 | AW47: =AW36*$A$47 -> 0 | ... BA47: =BA36*$A$47 -> 0 | BB47: =SUM(AP47:BA47) -> 0
B48: Receitas Totais | C48: =SUM(C46:C47) -> 0 | D48: =SUM(D46:D47) -> 31434.693 | E48: =SUM(E46:E47) -> 0 | F48: =SUM(F46:F47) -> 0 | G48: =SUM(G46:G47) -> 0 | H48: =SUM(H46:H47) -> 0 | I48: =SUM(I46:I47) -> 0 | J48: =SUM(J46:J47) -> 0 | ... AH48: =SUM(AH46:AH47) -> 0 | AJ48: =SUM(AJ46:AJ47) -> 0 | AK48: =SUM(AK46:AK47) -> 0 | AL48: =SUM(AL46:AL47) -> 0 | AM48: =SUM(AM46:AM47) -> 0 | AN48: =SUM(AN46:AN47) -> 0 | AO48: =SUM(AB48:AN48) -> 0 | AP48: =SUM(AP46:AP47) -> 0 | AQ48: =SUM(AQ46:AQ47) -> 0 | AR48: =SUM(AR46:AR47) -> 0 | AS48: =SUM(AS46:AS47) -> 0 | AT48: =SUM(AT46:AT47) -> 0 | AU48: =SUM(AU46:AU47) -> 0 | AV48: =SUM(AV46:AV47) -> 0 | AW48: =SUM(AW46:AW47) -> 0 | ... BA48: =SUM(BA46:BA47) -> 0 | BB48: =SUM(AP48:BA48) -> 0
B50: Teu/POA
B51: Vendas Totais | D51: =SUM(D52:D59) -> 1520269.3 | F51: =SUM(F52:F59) -> 0 | H51: =SUM(H52:H59) -> 0 | J51: =SUM(J52:J59) -> 0 | L51: =SUM(L52:L59) -> 0 | N51: =SUM(N52:N59) -> 0 | P51: =SUM(P52:P59) -> 0 | R51: =SUM(R52:R59) -> 0 | T51: =SUM(T52:T59) -> 0 | V51: =SUM(V52:V59) -> 0 | X51: =SUM(X52:X59) -> 0 | Z51: =SUM(Z52:Z59) -> 0 | AA51: 0 | AB51: 0 | AC51: 0 | AD51: 0 | AE51: 0 | AF51: 0 | AG51: 0 | AH51: 0 | AJ51: 0 | AK51: 0 | AL51: 0 | AM51: 0 | AN51: 0 | AO51: 0 | AP51: 0 | AQ51: 0 | AR51: 0 | AS51: 0 | AT51: 0 | AU51: 0 | AV51: 0 | AW51: 0 | AX51: 0 | AY51: 0 | AZ51: 0 | BA51: 0 | BB51: 0
B52: Vendas por meio de Pgto
A53: 0.25345 | B53: Cartão de Crédito | D53: 279453.84 | AA53: =AA51*$A$53 -> 0 | AB53: =AB51*$A$53 -> 0 | AC53: =AC51*$A$53 -> 0 | AD53: =AD51*$A$53 -> 0 | AE53: =AE51*$A$53 -> 0 | AF53: =AF51*$A$53 -> 0 | AG53: =AG51*$A$53 -> 0 | AH53: =AH51*$A$53 -> 0 | AJ53: =AJ51*$A$53 -> 0 | AK53: =AK51*$A$53 -> 0 | AL53: =AL51*$A$53 -> 0 | AM53: =AM51*$A$53 -> 0 | AN53: =AN51*$A$53 -> 0 | AO53: =SUM(AB53:AN53) -> 0 | AP53: =AP51*$A$53 -> 0 | AQ53: =AQ51*$A$53 -> 0 | AR53: =AR51*$A$53 -> 0 | AS53: =AS51*$A$53 -> 0 | AT53: =AT51*$A$53 -> 0 | AU53: =AU51*$A$53 -> 0 | AV53: =AV51*$A$53 -> 0 | AW53: =AW51*$A$53 -> 0 | ... BA53: =BA51*$A$53 -> 0 | BB53: =SUM(AP53:BA53) -> 0
A54: 0 | B54: Cartão de Débito | AA54: =AA51*$A$54 -> 0 | AB54: =AB51*$A$54 -> 0 | AC54: =AC51*$A$54 -> 0 | AD54: =AD51*$A$54 -> 0 | AE54: =AE51*$A$54 -> 0 | AF54: =AF51*$A$54 -> 0 | AG54: =AG51*$A$54 -> 0 | AH54: =AH51*$A$54 -> 0 | AJ54: =AJ51*$A$54 -> 0 | AK54: =AK51*$A$54 -> 0 | AL54: =AL51*$A$54 -> 0 | AM54: =AM51*$A$54 -> 0 | AN54: =AN51*$A$54 -> 0 | AO54: =SUM(AB54:AN54) -> 0 | AP54: =AP51*$A$54 -> 0 | AQ54: =AQ51*$A$54 -> 0 | AR54: =AR51*$A$54 -> 0 | AS54: =AS51*$A$54 -> 0 | AT54: =AT51*$A$54 -> 0 | AU54: =AU51*$A$54 -> 0 | AV54: =AV51*$A$54 -> 0 | AW54: =AW51*$A$54 -> 0 | ... BA54: =BA51*$A$54 -> 0 | BB54: =SUM(AP54:BA54) -> 0
A55: =71.058%+0.015% -> 0.71073 | B55: Pix | D55: 1240815.5 | AA55: =AA51*$A$55 -> 0 | AB55: =AB51*$A$55 -> 0 | AC55: =AC51*$A$55 -> 0 | AD55: =AD51*$A$55 -> 0 | AE55: =AE51*$A$55 -> 0 | AF55: =AF51*$A$55 -> 0 | AG55: =AG51*$A$55 -> 0 | AH55: =AH51*$A$55 -> 0 | AJ55: =AJ51*$A$55 -> 0 | AK55: =AK51*$A$55 -> 0 | AL55: =AL51*$A$55 -> 0 | AM55: =AM51*$A$55 -> 0 | AN55: =AN51*$A$55 -> 0 | AO55: =SUM(AB55:AN55) -> 0 | AP55: =AP51*$A$55 -> 0 | AQ55: =AQ51*$A$55 -> 0 | AR55: =AR51*$A$55 -> 0 | AS55: =AS51*$A$55 -> 0 | AT55: =AT51*$A$55 -> 0 | AU55: =AU51*$A$55 -> 0 | AV55: =AV51*$A$55 -> 0 | AW55: =AW51*$A$55 -> 0 | ... BA55: =BA51*$A$55 -> 0 | BB55: =SUM(AP55:BA55) -> 0
A56: 0 | B56: Carteira Digital KIM+ | AA56: =AA51*$A$56 -> 0 | AB56: =AB51*$A$56 -> 0 | AC56: =AC51*$A$56 -> 0 | AD56: =AD51*$A$56 -> 0 | AE56: =AE51*$A$56 -> 0 | AF56: =AF51*$A$56 -> 0 | AG56: =AG51*$A$56 -> 0 | AH56: =AH51*$A$56 -> 0 | AJ56: =AJ51*$A$56 -> 0 | AK56: =AK51*$A$56 -> 0 | AL56: =AL51*$A$56 -> 0 | AM56: =AM51*$A$56 -> 0 | AN56: =AN51*$A$56 -> 0 | AO56: =SUM(AB56:AN56) -> 0 | AP56: =AP51*$A$56 -> 0 | AQ56: =AQ51*$A$56 -> 0 | AR56: =AR51*$A$56 -> 0 | AS56: =AS51*$A$56 -> 0 | AT56: =AT51*$A$56 -> 0 | AU56: =AU51*$A$56 -> 0 | AV56: =AV51*$A$56 -> 0 | AW56: =AW51*$A$56 -> 0 | ... BA56: =BA51*$A$56 -> 0 | BB56: =SUM(AP56:BA56) -> 0
A57: 0.01438 | B57: Transferência | AA57: =AA51*$A$57 -> 0 | AB57: =AB51*$A$57 -> 0 | AC57: =AC51*$A$57 -> 0 | AD57: =AD51*$A$57 -> 0 | AE57: =AE51*$A$57 -> 0 | AF57: =AF51*$A$57 -> 0 | AG57: =AG51*$A$57 -> 0 | AH57: =AH51*$A$57 -> 0 | AJ57: =AJ51*$A$57 -> 0 | AK57: =AK51*$A$57 -> 0 | AL57: =AL51*$A$57 -> 0 | AM57: =AM51*$A$57 -> 0 | AN57: =AN51*$A$57 -> 0 | AO57: =SUM(AB57:AN57) -> 0 | AP57: =AP51*$A$57 -> 0 | AQ57: =AQ51*$A$57 -> 0 | AR57: =AR51*$A$57 -> 0 | AS57: =AS51*$A$57 -> 0 | AT57: =AT51*$A$57 -> 0 | AU57: =AU51*$A$57 -> 0 | AV57: =AV51*$A$57 -> 0 | AW57: =AW51*$A$57 -> 0 | ... BA57: =BA51*$A$57 -> 0 | BB57: =SUM(AP57:BA57) -> 0
A58: 0.00063 | B58: Depósito | AA58: =AA51*$A$58 -> 0 | AB58: =AB51*$A$58 -> 0 | AC58: =AC51*$A$58 -> 0 | AD58: =AD51*$A$58 -> 0 | AE58: =AE51*$A$58 -> 0 | AF58: =AF51*$A$58 -> 0 | AG58: =AG51*$A$58 -> 0 | AH58: =AH51*$A$58 -> 0 | AJ58: =AJ51*$A$58 -> 0 | AK58: =AK51*$A$58 -> 0 | AL58: =AL51*$A$58 -> 0 | AM58: =AM51*$A$58 -> 0 | AN58: =AN51*$A$58 -> 0 | AO58: =SUM(AB58:AN58) -> 0 | AP58: =AP51*$A$58 -> 0 | AQ58: =AQ51*$A$58 -> 0 | AR58: =AR51*$A$58 -> 0 | AS58: =AS51*$A$58 -> 0 | AT58: =AT51*$A$58 -> 0 | AU58: =AU51*$A$58 -> 0 | AV58: =AV51*$A$58 -> 0 | AW58: =AW51*$A$58 -> 0 | ... BA58: =BA51*$A$58 -> 0 | BB58: =SUM(AP58:BA58) -> 0
A59: 0.02081 | B59: Boleto Bancário | AA59: =AA51*$A$59 -> 0 | AB59: =AB51*$A$59 -> 0 | AC59: =AC51*$A$59 -> 0 | AD59: =AD51*$A$59 -> 0 | AE59: =AE51*$A$59 -> 0 | AF59: =AF51*$A$59 -> 0 | AG59: =AG51*$A$59 -> 0 | AH59: =AH51*$A$59 -> 0 | AJ59: =AJ51*$A$59 -> 0 | AK59: =AK51*$A$59 -> 0 | AL59: =AL51*$A$59 -> 0 | AM59: =AM51*$A$59 -> 0 | AN59: =AN51*$A$59 -> 0 | AO59: =SUM(AB59:AN59) -> 0 | AP59: =AP51*$A$59 -> 0 | AQ59: =AQ51*$A$59 -> 0 | AR59: =AR51*$A$59 -> 0 | AS59: =AS51*$A$59 -> 0 | AT59: =AT51*$A$59 -> 0 | AU59: =AU51*$A$59 -> 0 | AV59: =AV51*$A$59 -> 0 | AW59: =AW51*$A$59 -> 0 | ... BA59: =BA51*$A$59 -> 0 | BB59: =SUM(AP59:BA59) -> 0
B60: Receitas
A61: 0 | B61: Receita de Usuários | C61: =((C53+C59)*2%)+(SUM(C54:C58)*1%) -> 0 | D61: 17995.99 | AA61: =((AA53+AA59)*2%)+(SUM(AA54:AA58)*1%) -> 0 | AB61: =((AB53+AB59)*2%)+(SUM(AB54:AB58)*1%) -> 0 | AC61: =((AC53+AC59)*2%)+(SUM(AC54:AC58)*1%) -> 0 | AD61: =((AD53+AD59)*2%)+(SUM(AD54:AD58)*1%) -> 0 | AE61: =((AE53+AE59)*2%)+(SUM(AE54:AE58)*1%) -> 0 | AF61: =((AF53+AF59)*2%)+(SUM(AF54:AF58)*1%) -> 0 | AG61: =((AG53+AG59)*2%)+(SUM(AG54:AG58)*1%) -> 0 | AH61: =((AH53+AH59)*2%)+(SUM(AH54:AH58)*1%) -> 0 | AJ61: =((AJ53+AJ59)*2%)+(SUM(AJ54:AJ58)*1%) -> 0 | AK61: =((AK53+AK59)*2%)+(SUM(AK54:AK58)*1%) -> 0 | AL61: =((AL53+AL59)*2%)+(SUM(AL54:AL58)*1%) -> 0 | AM61: =((AM53+AM59)*2%)+(SUM(AM54:AM58)*1%) -> 0 | AN61: =((AN53+AN59)*2%)+(SUM(AN54:AN58)*1%) -> 0 | AO61: =SUM(AB61:AN61) -> 0 | AP61: =((AP53+AP59)*2%)+(SUM(AP54:AP58)*1%) -> 0 | AQ61: =((AQ53+AQ59)*2%)+(SUM(AQ54:AQ58)*1%) -> 0 | AR61: =((AR53+AR59)*2%)+(SUM(AR54:AR58)*1%) -> 0 | AS61: =((AS53+AS59)*2%)+(SUM(AS54:AS58)*1%) -> 0 | AT61: =((AT53+AT59)*2%)+(SUM(AT54:AT58)*1%) -> 0 | AU61: =((AU53+AU59)*2%)+(SUM(AU54:AU58)*1%) -> 0 | AV61: =((AV53+AV59)*2%)+(SUM(AV54:AV58)*1%) -> 0 | AW61: =((AW53+AW59)*2%)+(SUM(AW54:AW58)*1%) -> 0 | ... BA61: =((BA53+BA59)*2%)+(SUM(BA54:BA58)*1%) -> 0 | BB61: =SUM(AP61:BA61) -> 0
A62: 0 | B62: Receita de Operadora | C62: =C51*$A$62 -> 0 | D62: =D51*$A$62 -> 0 | E62: =E51*$A$62 -> 0 | G62: =G51*$A$62 -> 0 | I62: =I51*$A$62 -> 0 | K62: =K51*$A$62 -> 0 | M62: =M51*$A$62 -> 0 | O62: =O51*$A$62 -> 0 | Q62: =Q51*$A$62 -> 0 | S62: =S51*$A$62 -> 0 | U62: =U51*$A$62 -> 0 | W62: =W51*$A$62 -> 0 | Y62: =Y51*$A$62 -> 0 | AA62: =AA51*$A$62 -> 0 | AB62: =AB51*$A$62 -> 0 | AC62: =AC51*$A$62 -> 0 | AD62: =AD51*$A$62 -> 0 | AE62: =AE51*$A$62 -> 0 | AF62: =AF51*$A$62 -> 0 | AG62: =AG51*$A$62 -> 0 | AH62: =AH51*$A$62 -> 0 | AJ62: =AJ51*$A$62 -> 0 | AK62: =AK51*$A$62 -> 0 | AL62: =AL51*$A$62 -> 0 | AM62: =AM51*$A$62 -> 0 | AN62: =AN51*$A$62 -> 0 | AO62: =SUM(AB62:AN62) -> 0 | AP62: =AP51*$A$62 -> 0 | AQ62: =AQ51*$A$62 -> 0 | AR62: =AR51*$A$62 -> 0 | AS62: =AS51*$A$62 -> 0 | AT62: =AT51*$A$62 -> 0 | AU62: =AU51*$A$62 -> 0 | AV62: =AV51*$A$62 -> 0 | AW62: =AW51*$A$62 -> 0 | ... BA62: =BA51*$A$62 -> 0 | BB62: =SUM(AP62:BA62) -> 0
B63: Receitas Totais | C63: =SUM(C61:C62) -> 0 | D63: =SUM(D61:D62) -> 17995.99 | E63: =SUM(E61:E62) -> 0 | F63: =SUM(F61:F62) -> 0 | G63: =SUM(G61:G62) -> 0 | H63: =SUM(H61:H62) -> 0 | I63: =SUM(I61:I62) -> 0 | J63: =SUM(J61:J62) -> 0 | ... AH63: =SUM(AH61:AH62) -> 0 | AJ63: =SUM(AJ61:AJ62) -> 0 | AK63: =SUM(AK61:AK62) -> 0 | AL63: =SUM(AL61:AL62) -> 0 | AM63: =SUM(AM61:AM62) -> 0 | AN63: =SUM(AN61:AN62) -> 0 | AO63: =SUM(AB63:AN63) -> 0 | AP63: =SUM(AP61:AP62) -> 0 | AQ63: =SUM(AQ61:AQ62) -> 0 | AR63: =SUM(AR61:AR62) -> 0 | AS63: =SUM(AS61:AS62) -> 0 | AT63: =SUM(AT61:AT62) -> 0 | AU63: =SUM(AU61:AU62) -> 0 | AV63: =SUM(AV61:AV62) -> 0 | AW63: =SUM(AW61:AW62) -> 0 | ... BA63: =SUM(BA61:BA62) -> 0 | BB63: =SUM(AP63:BA63) -> 0
B65: Transfácil/BHZ
B66: Vendas Totais | D66: =SUM(D67:D74) -> 872491.33 | F66: =SUM(F67:F74) -> 0 | H66: =SUM(H67:H74) -> 0 | J66: =SUM(J67:J74) -> 0 | L66: =SUM(L67:L74) -> 0 | N66: =SUM(N67:N74) -> 0 | P66: =SUM(P67:P74) -> 0 | R66: =SUM(R67:R74) -> 0 | T66: =SUM(T67:T74) -> 0 | V66: =SUM(V67:V74) -> 0 | X66: =SUM(X67:X74) -> 0 | Z66: =SUM(Z67:Z74) -> 0 | AA66: 0 | AB66: 0 | AC66: 0 | AD66: 0 | AE66: 0 | AF66: 0 | AG66: 0 | AH66: 0 | AJ66: 0 | AK66: 0 | AL66: 0 | AM66: 0 | AN66: 0 | AO66: 0 | AP66: 0 | AQ66: 0 | AR66: 0 | AS66: 0 | AT66: 0 | AU66: 0 | AV66: 0 | AW66: 0 | AX66: 0 | AY66: 0 | AZ66: 0 | BA66: 0 | BB66: 0
B67: Vendas por meio de Pgto
A68: 0.25345 | B68: Cartão de Crédito | D68: 126846.29 | AA68: =AA66*$A$68 -> 0 | AB68: =AB66*$A$68 -> 0 | AC68: =AC66*$A$68 -> 0 | AD68: =AD66*$A$68 -> 0 | AE68: =AE66*$A$68 -> 0 | AF68: =AF66*$A$68 -> 0 | AG68: =AG66*$A$68 -> 0 | AH68: =AH66*$A$68 -> 0 | AJ68: =AJ66*$A$68 -> 0 | AK68: =AK66*$A$68 -> 0 | AL68: =AL66*$A$68 -> 0 | AM68: =AM66*$A$68 -> 0 | AN68: =AN66*$A$68 -> 0 | AO68: =SUM(AB68:AN68) -> 0 | AP68: =AP66*$A$68 -> 0 | AQ68: =AQ66*$A$68 -> 0 | AR68: =AR66*$A$68 -> 0 | AS68: =AS66*$A$68 -> 0 | AT68: =AT66*$A$68 -> 0 | AU68: =AU66*$A$68 -> 0 | AV68: =AV66*$A$68 -> 0 | AW68: =AW66*$A$68 -> 0 | ... BA68: =BA66*$A$68 -> 0 | BB68: =SUM(AP68:BA68) -> 0
A69: 0 | B69: Cartão de Débito | AA69: =AA66*$A$69 -> 0 | AB69: =AB66*$A$69 -> 0 | AC69: =AC66*$A$69 -> 0 | AD69: =AD66*$A$69 -> 0 | AE69: =AE66*$A$69 -> 0 | AF69: =AF66*$A$69 -> 0 | AG69: =AG66*$A$69 -> 0 | AH69: =AH66*$A$69 -> 0 | AJ69: =AJ66*$A$69 -> 0 | AK69: =AK66*$A$69 -> 0 | AL69: =AL66*$A$69 -> 0 | AM69: =AM66*$A$69 -> 0 | AN69: =AN66*$A$69 -> 0 | AO69: =SUM(AB69:AN69) -> 0 | AP69: =AP66*$A$69 -> 0 | AQ69: =AQ66*$A$69 -> 0 | AR69: =AR66*$A$69 -> 0 | AS69: =AS66*$A$69 -> 0 | AT69: =AT66*$A$69 -> 0 | AU69: =AU66*$A$69 -> 0 | AV69: =AV66*$A$69 -> 0 | AW69: =AW66*$A$69 -> 0 | ... BA69: =BA66*$A$69 -> 0 | BB69: =SUM(AP69:BA69) -> 0
A70: =71.058%+0.015% -> 0.71073 | B70: Pix | D70: 745645.04 | AA70: =AA66*$A$70 -> 0 | AB70: =AB66*$A$70 -> 0 | AC70: =AC66*$A$70 -> 0 | AD70: =AD66*$A$70 -> 0 | AE70: =AE66*$A$70 -> 0 | AF70: =AF66*$A$70 -> 0 | AG70: =AG66*$A$70 -> 0 | AH70: =AH66*$A$70 -> 0 | AJ70: =AJ66*$A$70 -> 0 | AK70: =AK66*$A$70 -> 0 | AL70: =AL66*$A$70 -> 0 | AM70: =AM66*$A$70 -> 0 | AN70: =AN66*$A$70 -> 0 | AO70: =SUM(AB70:AN70) -> 0 | AP70: =AP66*$A$70 -> 0 | AQ70: =AQ66*$A$70 -> 0 | AR70: =AR66*$A$70 -> 0 | AS70: =AS66*$A$70 -> 0 | AT70: =AT66*$A$70 -> 0 | AU70: =AU66*$A$70 -> 0 | AV70: =AV66*$A$70 -> 0 | AW70: =AW66*$A$70 -> 0 | ... BA70: =BA66*$A$70 -> 0 | BB70: =SUM(AP70:BA70) -> 0
A71: 0 | B71: Carteira Digital KIM+ | AA71: =AA66*$A$71 -> 0 | AB71: =AB66*$A$71 -> 0 | AC71: =AC66*$A$71 -> 0 | AD71: =AD66*$A$71 -> 0 | AE71: =AE66*$A$71 -> 0 | AF71: =AF66*$A$71 -> 0 | AG71: =AG66*$A$71 -> 0 | AH71: =AH66*$A$71 -> 0 | AJ71: =AJ66*$A$71 -> 0 | AK71: =AK66*$A$71 -> 0 | AL71: =AL66*$A$71 -> 0 | AM71: =AM66*$A$71 -> 0 | AN71: =AN66*$A$71 -> 0 | AO71: =SUM(AB71:AN71) -> 0 | AP71: =AP66*$A$71 -> 0 | AQ71: =AQ66*$A$71 -> 0 | AR71: =AR66*$A$71 -> 0 | AS71: =AS66*$A$71 -> 0 | AT71: =AT66*$A$71 -> 0 | AU71: =AU66*$A$71 -> 0 | AV71: =AV66*$A$71 -> 0 | AW71: =AW66*$A$71 -> 0 | ... BA71: =BA66*$A$71 -> 0 | BB71: =SUM(AP71:BA71) -> 0
A72: 0.01438 | B72: Transferência | AA72: =AA66*$A$72 -> 0 | AB72: =AB66*$A$72 -> 0 | AC72: =AC66*$A$72 -> 0 | AD72: =AD66*$A$72 -> 0 | AE72: =AE66*$A$72 -> 0 | AF72: =AF66*$A$72 -> 0 | AG72: =AG66*$A$72 -> 0 | AH72: =AH66*$A$72 -> 0 | AJ72: =AJ66*$A$72 -> 0 | AK72: =AK66*$A$72 -> 0 | AL72: =AL66*$A$72 -> 0 | AM72: =AM66*$A$72 -> 0 | AN72: =AN66*$A$72 -> 0 | AO72: =SUM(AB72:AN72) -> 0 | AP72: =AP66*$A$72 -> 0 | AQ72: =AQ66*$A$72 -> 0 | AR72: =AR66*$A$72 -> 0 | AS72: =AS66*$A$72 -> 0 | AT72: =AT66*$A$72 -> 0 | AU72: =AU66*$A$72 -> 0 | AV72: =AV66*$A$72 -> 0 | AW72: =AW66*$A$72 -> 0 | ... BA72: =BA66*$A$72 -> 0 | BB72: =SUM(AP72:BA72) -> 0
A73: 0.00063 | B73: Depósito | AA73: =AA66*$A$73 -> 0 | AB73: =AB66*$A$73 -> 0 | AC73: =AC66*$A$73 -> 0 | AD73: =AD66*$A$73 -> 0 | AE73: =AE66*$A$73 -> 0 | AF73: =AF66*$A$73 -> 0 | AG73: =AG66*$A$73 -> 0 | AH73: =AH66*$A$73 -> 0 | AJ73: =AJ66*$A$73 -> 0 | AK73: =AK66*$A$73 -> 0 | AL73: =AL66*$A$73 -> 0 | AM73: =AM66*$A$73 -> 0 | AN73: =AN66*$A$73 -> 0 | AO73: =SUM(AB73:AN73) -> 0 | AP73: =AP66*$A$73 -> 0 | AQ73: =AQ66*$A$73 -> 0 | AR73: =AR66*$A$73 -> 0 | AS73: =AS66*$A$73 -> 0 | AT73: =AT66*$A$73 -> 0 | AU73: =AU66*$A$73 -> 0 | AV73: =AV66*$A$73 -> 0 | AW73: =AW66*$A$73 -> 0 | ... BA73: =BA66*$A$73 -> 0 | BB73: =SUM(AP73:BA73) -> 0
A74: 0.02081 | B74: Boleto Bancário | AA74: =AA66*$A$74 -> 0 | AB74: =AB66*$A$74 -> 0 | AC74: =AC66*$A$74 -> 0 | AD74: =AD66*$A$74 -> 0 | AE74: =AE66*$A$74 -> 0 | AF74: =AF66*$A$74 -> 0 | AG74: =AG66*$A$74 -> 0 | AH74: =AH66*$A$74 -> 0 | AJ74: =AJ66*$A$74 -> 0 | AK74: =AK66*$A$74 -> 0 | AL74: =AL66*$A$74 -> 0 | AM74: =AM66*$A$74 -> 0 | AN74: =AN66*$A$74 -> 0 | AO74: =SUM(AB74:AN74) -> 0 | AP74: =AP66*$A$74 -> 0 | AQ74: =AQ66*$A$74 -> 0 | AR74: =AR66*$A$74 -> 0 | AS74: =AS66*$A$74 -> 0 | AT74: =AT66*$A$74 -> 0 | AU74: =AU66*$A$74 -> 0 | AV74: =AV66*$A$74 -> 0 | AW74: =AW66*$A$74 -> 0 | ... BA74: =BA66*$A$74 -> 0 | BB74: =SUM(AP74:BA74) -> 0
B75: Receitas
A76: 0 | B76: Receita de Usuários | C76: =C66*$A$76 -> 0 | E76: =E66*$A$76 -> 0 | G76: =G66*$A$76 -> 0 | I76: =I66*$A$76 -> 0 | K76: =K66*$A$76 -> 0 | M76: =M66*$A$76 -> 0 | O76: =O66*$A$76 -> 0 | Q76: =Q66*$A$76 -> 0 | S76: =S66*$A$76 -> 0 | U76: =U66*$A$76 -> 0 | W76: =W66*$A$76 -> 0 | Y76: =Y66*$A$76 -> 0 | AA76: =AA66*$A$76 -> 0 | AB76: =AB66*$A$76 -> 0 | AC76: =AC66*$A$76 -> 0 | AD76: =AD66*$A$76 -> 0 | AE76: =AE66*$A$76 -> 0 | AF76: =AF66*$A$76 -> 0 | AG76: =AG66*$A$76 -> 0 | AH76: =AH66*$A$76 -> 0 | AJ76: =AJ66*$A$76 -> 0 | AK76: =AK66*$A$76 -> 0 | AL76: =AL66*$A$76 -> 0 | AM76: =AM66*$A$76 -> 0 | AN76: =AN66*$A$76 -> 0 | AO76: =SUM(AB76:AN76) -> 0 | AP76: =AP66*$A$76 -> 0 | AQ76: =AQ66*$A$76 -> 0 | AR76: =AR66*$A$76 -> 0 | AS76: =AS66*$A$76 -> 0 | AT76: =AT66*$A$76 -> 0 | AU76: =AU66*$A$76 -> 0 | AV76: =AV66*$A$76 -> 0 | AW76: =AW66*$A$76 -> 0 | ... BA76: =BA66*$A$76 -> 0 | BB76: =SUM(AP76:BA76) -> 0
A77: 0.009 | B77: Receita de Operadora | C77: =C66*$A$77 -> 0 | D77: =D66*$A$77 -> 7852.422 | E77: =E66*$A$77 -> 0 | F77: =F66*$A$77 -> 0 | G77: =G66*$A$77 -> 0 | H77: =H66*$A$77 -> 0 | I77: =I66*$A$77 -> 0 | J77: =J66*$A$77 -> 0 | ... AH77: =AH66*$A$77 -> 0 | AJ77: =AJ66*$A$77 -> 0 | AK77: =AK66*$A$77 -> 0 | AL77: =AL66*$A$77 -> 0 | AM77: =AM66*$A$77 -> 0 | AN77: =AN66*$A$77 -> 0 | AO77: =SUM(AB77:AN77) -> 0 | AP77: =AP66*$A$77 -> 0 | AQ77: =AQ66*$A$77 -> 0 | AR77: =AR66*$A$77 -> 0 | AS77: =AS66*$A$77 -> 0 | AT77: =AT66*$A$77 -> 0 | AU77: =AU66*$A$77 -> 0 | AV77: =AV66*$A$77 -> 0 | AW77: =AW66*$A$77 -> 0 | ... BA77: =BA66*$A$77 -> 0 | BB77: =SUM(AP77:BA77) -> 0
B78: Receitas Totais | C78: =SUM(C76:C77) -> 0 | D78: =SUM(D76:D77) -> 7852.422 | E78: =SUM(E76:E77) -> 0 | F78: =SUM(F76:F77) -> 0 | G78: =SUM(G76:G77) -> 0 | H78: =SUM(H76:H77) -> 0 | I78: =SUM(I76:I77) -> 0 | J78: =SUM(J76:J77) -> 0 | ... AH78: =SUM(AH76:AH77) -> 0 | AJ78: =SUM(AJ76:AJ77) -> 0 | AK78: =SUM(AK76:AK77) -> 0 | AL78: =SUM(AL76:AL77) -> 0 | AM78: =SUM(AM76:AM77) -> 0 | AN78: =SUM(AN76:AN77) -> 0 | AO78: =SUM(AB78:AN78) -> 0 | AP78: =SUM(AP76:AP77) -> 0 | AQ78: =SUM(AQ76:AQ77) -> 0 | AR78: =SUM(AR76:AR77) -> 0 | AS78: =SUM(AS76:AS77) -> 0 | AT78: =SUM(AT76:AT77) -> 0 | AU78: =SUM(AU76:AU77) -> 0 | AV78: =SUM(AV76:AV77) -> 0 | AW78: =SUM(AW76:AW77) -> 0 | ... BA78: =SUM(BA76:BA77) -> 0 | BB78: =SUM(AP78:BA78) -> 0
B80: Biguaçú-Jotur-Santa Terezinha/Florianopolis
B81: Vendas Totais | C81: 0 | D81: =SUM(D82:D89) -> 925610.36 | F81: =SUM(F82:F89) -> 0 | H81: =SUM(H82:H89) -> 0 | J81: =SUM(J82:J89) -> 0 | L81: =SUM(L82:L89) -> 0 | N81: =SUM(N82:N89) -> 0 | P81: =SUM(P82:P89) -> 0 | R81: =SUM(R82:R89) -> 0 | T81: =SUM(T82:T89) -> 0 | V81: =SUM(V82:V89) -> 0 | X81: =SUM(X82:X89) -> 0 | Z81: =SUM(Z82:Z89) -> 0 | AA81: 0 | AB81: 0 | AC81: 0 | AD81: 0 | AE81: 0 | AF81: 0 | AG81: 0 | AH81: 0 | AJ81: 0 | AK81: 0 | AL81: 0 | AM81: 0 | AN81: 0 | AO81: 0 | AP81: 0 | AQ81: 0 | AR81: 0 | AS81: 0 | AT81: 0 | AU81: 0 | AV81: 0 | AW81: 0 | AX81: 0 | AY81: 0 | AZ81: 0 | BA81: 0 | BB81: 0
B82: Vendas por meio de Pgto
A83: 0.25345 | B83: Cartão de Crédito | C83: =C81*$A$83 -> 0 | D83: 130178.58 | AA83: =AA81*$A$83 -> 0 | AB83: =AB81*$A$83 -> 0 | AC83: =AC81*$A$83 -> 0 | AD83: =AD81*$A$83 -> 0 | AE83: =AE81*$A$83 -> 0 | AF83: =AF81*$A$83 -> 0 | AG83: =AG81*$A$83 -> 0 | AH83: =AH81*$A$83 -> 0 | AJ83: =AJ81*$A$83 -> 0 | AK83: =AK81*$A$83 -> 0 | AL83: =AL81*$A$83 -> 0 | AM83: =AM81*$A$83 -> 0 | AN83: =AN81*$A$83 -> 0 | AO83: =SUM(AB83:AN83) -> 0 | AP83: =AP81*$A$83 -> 0 | AQ83: =AQ81*$A$83 -> 0 | AR83: =AR81*$A$83 -> 0 | AS83: =AS81*$A$83 -> 0 | AT83: =AT81*$A$83 -> 0 | AU83: =AU81*$A$83 -> 0 | AV83: =AV81*$A$83 -> 0 | AW83: =AW81*$A$83 -> 0 | ... BA83: =BA81*$A$83 -> 0 | BB83: =SUM(AP83:BA83) -> 0
A84: 0 | B84: Cartão de Débito | C84: =C81*$A$84 -> 0 | AA84: =AA81*$A$84 -> 0 | AB84: =AB81*$A$84 -> 0 | AC84: =AC81*$A$84 -> 0 | AD84: =AD81*$A$84 -> 0 | AE84: =AE81*$A$84 -> 0 | AF84: =AF81*$A$84 -> 0 | AG84: =AG81*$A$84 -> 0 | AH84: =AH81*$A$84 -> 0 | AJ84: =AJ81*$A$84 -> 0 | AK84: =AK81*$A$84 -> 0 | AL84: =AL81*$A$84 -> 0 | AM84: =AM81*$A$84 -> 0 | AN84: =AN81*$A$84 -> 0 | AO84: =SUM(AB84:AN84) -> 0 | AP84: =AP81*$A$84 -> 0 | AQ84: =AQ81*$A$84 -> 0 | AR84: =AR81*$A$84 -> 0 | AS84: =AS81*$A$84 -> 0 | AT84: =AT81*$A$84 -> 0 | AU84: =AU81*$A$84 -> 0 | AV84: =AV81*$A$84 -> 0 | AW84: =AW81*$A$84 -> 0 | ... BA84: =BA81*$A$84 -> 0 | BB84: =SUM(AP84:BA84) -> 0
A85: =71.058%+0.015% -> 0.71073 | B85: Pix | C85: =C81*$A$85 -> 0 | D85: 795431.78 | AA85: =AA81*$A$85 -> 0 | AB85: =AB81*$A$85 -> 0 | AC85: =AC81*$A$85 -> 0 | AD85: =AD81*$A$85 -> 0 | AE85: =AE81*$A$85 -> 0 | AF85: =AF81*$A$85 -> 0 | AG85: =AG81*$A$85 -> 0 | AH85: =AH81*$A$85 -> 0 | AJ85: =AJ81*$A$85 -> 0 | AK85: =AK81*$A$85 -> 0 | AL85: =AL81*$A$85 -> 0 | AM85: =AM81*$A$85 -> 0 | AN85: =AN81*$A$85 -> 0 | AO85: =SUM(AB85:AN85) -> 0 | AP85: =AP81*$A$85 -> 0 | AQ85: =AQ81*$A$85 -> 0 | AR85: =AR81*$A$85 -> 0 | AS85: =AS81*$A$85 -> 0 | AT85: =AT81*$A$85 -> 0 | AU85: =AU81*$A$85 -> 0 | AV85: =AV81*$A$85 -> 0 | AW85: =AW81*$A$85 -> 0 | ... BA85: =BA81*$A$85 -> 0 | BB85: =SUM(AP85:BA85) -> 0
A86: 0 | B86: Carteira Digital KIM+ | C86: =C81*$A$86 -> 0 | AA86: =AA81*$A$86 -> 0 | AB86: =AB81*$A$86 -> 0 | AC86: =AC81*$A$86 -> 0 | AD86: =AD81*$A$86 -> 0 | AE86: =AE81*$A$86 -> 0 | AF86: =AF81*$A$86 -> 0 | AG86: =AG81*$A$86 -> 0 | AH86: =AH81*$A$86 -> 0 | AJ86: =AJ81*$A$86 -> 0 | AK86: =AK81*$A$86 -> 0 | AL86: =AL81*$A$86 -> 0 | AM86: =AM81*$A$86 -> 0 | AN86: =AN81*$A$86 -> 0 | AO86: =SUM(AB86:AN86) -> 0 | AP86: =AP81*$A$86 -> 0 | AQ86: =AQ81*$A$86 -> 0 | AR86: =AR81*$A$86 -> 0 | AS86: =AS81*$A$86 -> 0 | AT86: =AT81*$A$86 -> 0 | AU86: =AU81*$A$86 -> 0 | AV86: =AV81*$A$86 -> 0 | AW86: =AW81*$A$86 -> 0 | ... BA86: =BA81*$A$86 -> 0 | BB86: =SUM(AP86:BA86) -> 0
A87: 0.01438 | B87: Transferência | C87: =C81*$A$87 -> 0 | AA87: =AA81*$A$87 -> 0 | AB87: =AB81*$A$87 -> 0 | AC87: =AC81*$A$87 -> 0 | AD87: =AD81*$A$87 -> 0 | AE87: =AE81*$A$87 -> 0 | AF87: =AF81*$A$87 -> 0 | AG87: =AG81*$A$87 -> 0 | AH87: =AH81*$A$87 -> 0 | AJ87: =AJ81*$A$87 -> 0 | AK87: =AK81*$A$87 -> 0 | AL87: =AL81*$A$87 -> 0 | AM87: =AM81*$A$87 -> 0 | AN87: =AN81*$A$87 -> 0 | AO87: =SUM(AB87:AN87) -> 0 | AP87: =AP81*$A$87 -> 0 | AQ87: =AQ81*$A$87 -> 0 | AR87: =AR81*$A$87 -> 0 | AS87: =AS81*$A$87 -> 0 | AT87: =AT81*$A$87 -> 0 | AU87: =AU81*$A$87 -> 0 | AV87: =AV81*$A$87 -> 0 | AW87: =AW81*$A$87 -> 0 | ... BA87: =BA81*$A$87 -> 0 | BB87: =SUM(AP87:BA87) -> 0
A88: 0.00063 | B88: Depósito | C88: =C81*$A$88 -> 0 | AA88: =AA81*$A$88 -> 0 | AB88: =AB81*$A$88 -> 0 | AC88: =AC81*$A$88 -> 0 | AD88: =AD81*$A$88 -> 0 | AE88: =AE81*$A$88 -> 0 | AF88: =AF81*$A$88 -> 0 | AG88: =AG81*$A$88 -> 0 | AH88: =AH81*$A$88 -> 0 | AJ88: =AJ81*$A$88 -> 0 | AK88: =AK81*$A$88 -> 0 | AL88: =AL81*$A$88 -> 0 | AM88: =AM81*$A$88 -> 0 | AN88: =AN81*$A$88 -> 0 | AO88: =SUM(AB88:AN88) -> 0 | AP88: =AP81*$A$88 -> 0 | AQ88: =AQ81*$A$88 -> 0 | AR88: =AR81*$A$88 -> 0 | AS88: =AS81*$A$88 -> 0 | AT88: =AT81*$A$88 -> 0 | AU88: =AU81*$A$88 -> 0 | AV88: =AV81*$A$88 -> 0 | AW88: =AW81*$A$88 -> 0 | ... BA88: =BA81*$A$88 -> 0 | BB88: =SUM(AP88:BA88) -> 0
A89: 0.02081 | B89: Boleto Bancário | C89: =C81*$A$89 -> 0 | AA89: =AA81*$A$89 -> 0 | AB89: =AB81*$A$89 -> 0 | AC89: =AC81*$A$89 -> 0 | AD89: =AD81*$A$89 -> 0 | AE89: =AE81*$A$89 -> 0 | AF89: =AF81*$A$89 -> 0 | AG89: =AG81*$A$89 -> 0 | AH89: =AH81*$A$89 -> 0 | AJ89: =AJ81*$A$89 -> 0 | AK89: =AK81*$A$89 -> 0 | AL89: =AL81*$A$89 -> 0 | AM89: =AM81*$A$89 -> 0 | AN89: =AN81*$A$89 -> 0 | AO89: =SUM(AB89:AN89) -> 0 | AP89: =AP81*$A$89 -> 0 | AQ89: =AQ81*$A$89 -> 0 | AR89: =AR81*$A$89 -> 0 | AS89: =AS81*$A$89 -> 0 | AT89: =AT81*$A$89 -> 0 | AU89: =AU81*$A$89 -> 0 | AV89: =AV81*$A$89 -> 0 | AW89: =AW81*$A$89 -> 0 | ... BA89: =BA81*$A$89 -> 0 | BB89: =SUM(AP89:BA89) -> 0
B90: Receitas
A91: 0 | B91: Receita de Usuários | C91: =C81*$A$91 -> 0 | E91: =E81*$A$91 -> 0 | G91: =G81*$A$91 -> 0 | I91: =I81*$A$91 -> 0 | K91: =K81*$A$91 -> 0 | M91: =M81*$A$91 -> 0 | O91: =O81*$A$91 -> 0 | Q91: =Q81*$A$91 -> 0 | S91: =S81*$A$91 -> 0 | U91: =U81*$A$91 -> 0 | W91: =W81*$A$91 -> 0 | Y91: =Y81*$A$91 -> 0 | AA91: =AA81*$A$91 -> 0 | AB91: =AB81*$A$91 -> 0 | AC91: =AC81*$A$91 -> 0 | AD91: =AD81*$A$91 -> 0 | AE91: =AE81*$A$91 -> 0 | AF91: =AF81*$A$91 -> 0 | AG91: =AG81*$A$91 -> 0 | AH91: =AH81*$A$91 -> 0 | AJ91: =AJ81*$A$91 -> 0 | AK91: =AK81*$A$91 -> 0 | AL91: =AL81*$A$91 -> 0 | AM91: =AM81*$A$91 -> 0 | AN91: =AN81*$A$91 -> 0 | AO91: =SUM(AB91:AN91) -> 0 | AP91: =AP81*$A$91 -> 0 | AQ91: =AQ81*$A$91 -> 0 | AR91: =AR81*$A$91 -> 0 | AS91: =AS81*$A$91 -> 0 | AT91: =AT81*$A$91 -> 0 | AU91: =AU81*$A$91 -> 0 | AV91: =AV81*$A$91 -> 0 | AW91: =AW81*$A$91 -> 0 | ... BA91: =BA81*$A$91 -> 0 | BB91: =SUM(AP91:BA91) -> 0
A92: 0.03 | B92: Receita de Operadora | C92: =((C83+C84+C89)*3%)+(C85*1.75%)+((C87+C88+C86)*2%) -> 0 | D92: =((D83+D84+D89)*3%)+(D85*1.75%)+((D87+D88+D86)*2%) -> 17825.414 | E92: =((E83+E84+E89)*3%)+(E85*1.75%)+((E87+E88+E86)*2%) -> 0 | F92: =((F83+F84+F89)*3%)+(F85*1.75%)+((F87+F88+F86)*2%) -> 0 | G92: =((G83+G84+G89)*3%)+(G85*1.75%)+((G87+G88+G86)*2%) -> 0 | H92: =((H83+H84+H89)*3%)+(H85*1.75%)+((H87+H88+H86)*2%) -> 0 | I92: =((I83+I84+I89)*3%)+(I85*1.75%)+((I87+I88+I86)*2%) -> 0 | J92: =((J83+J84+J89)*3%)+(J85*1.75%)+((J87+J88+J86)*2%) -> 0 | ... Z92: =((Z83+Z84+Z89)*3%)+(Z85*1.75%)+((Z87+Z88+Z86)*2%) -> 0 | AA92: =AA81*$A$92 -> 0 | AB92: =AB81*$A$92 -> 0 | AC92: =AC81*$A$92 -> 0 | AD92: =AD81*$A$92 -> 0 | AE92: =AE81*$A$92 -> 0 | AF92: =AF81*$A$92 -> 0 | AG92: =AG81*$A$92 -> 0 | AH92: =AH81*$A$92 -> 0 | AJ92: =AJ81*$A$92 -> 0 | AK92: =AK81*$A$92 -> 0 | AL92: =AL81*$A$92 -> 0 | AM92: =AM81*$A$92 -> 0 | AN92: =AN81*$A$92 -> 0 | AO92: =SUM(AB92:AN92) -> 0 | AP92: =AP81*$A$92 -> 0 | AQ92: =AQ81*$A$92 -> 0 | AR92: =AR81*$A$92 -> 0 | AS92: =AS81*$A$92 -> 0 | AT92: =AT81*$A$92 -> 0 | AU92: =AU81*$A$92 -> 0 | AV92: =AV81*$A$92 -> 0 | AW92: =AW81*$A$92 -> 0 | ... BA92: =BA81*$A$92 -> 0 | BB92: =SUM(AP92:BA92) -> 0
B93: Receitas Totais | C93: =SUM(C91:C92) -> 0 | D93: =SUM(D91:D92) -> 17825.414 | E93: =SUM(E91:E92) -> 0 | F93: =SUM(F91:F92) -> 0 | G93: =SUM(G91:G92) -> 0 | H93: =SUM(H91:H92) -> 0 | I93: =SUM(I91:I92) -> 0 | J93: =SUM(J91:J92) -> 0 | ... AH93: =SUM(AH91:AH92) -> 0 | AJ93: =SUM(AJ91:AJ92) -> 0 | AK93: =SUM(AK91:AK92) -> 0 | AL93: =SUM(AL91:AL92) -> 0 | AM93: =SUM(AM91:AM92) -> 0 | AN93: =SUM(AN91:AN92) -> 0 | AO93: =SUM(AB93:AN93) -> 0 | AP93: =SUM(AP91:AP92) -> 0 | AQ93: =SUM(AQ91:AQ92) -> 0 | AR93: =SUM(AR91:AR92) -> 0 | AS93: =SUM(AS91:AS92) -> 0 | AT93: =SUM(AT91:AT92) -> 0 | AU93: =SUM(AU91:AU92) -> 0 | AV93: =SUM(AV91:AV92) -> 0 | AW93: =SUM(AW91:AW92) -> 0 | ... BA93: =SUM(BA91:BA92) -> 0 | BB93: =SUM(AP93:BA93) -> 0
B94: Via Ouro/Nova Lima
B95: Vendas Totais | D95: =SUM(D96:D103) -> 50281.58 | F95: =SUM(F96:F103) -> 0 | H95: =SUM(H96:H103) -> 0 | J95: =SUM(J96:J103) -> 0 | L95: =SUM(L96:L103) -> 0 | N95: =SUM(N96:N103) -> 0 | P95: =SUM(P96:P103) -> 0 | R95: =SUM(R96:R103) -> 0 | T95: =SUM(T96:T103) -> 0 | V95: =SUM(V96:V103) -> 0 | X95: =SUM(X96:X103) -> 0 | Z95: =SUM(Z96:Z103) -> 0 | AA95: 0 | AB95: 0 | AC95: 0 | AD95: 0 | AE95: 0 | AF95: 0 | AG95: 0 | AH95: 0
B96: Vendas por meio de Pgto
A97: 0.25345 | B97: Cartão de Crédito | C97: =C95*$A$97 -> 0 | D97: 6311.48 | AE97: =AE95*$A$83 -> 0 | AF97: =AF95*$A$83 -> 0 | AG97: =AG95*$A$83 -> 0 | AH97: =AH95*$A$83 -> 0
A98: 0 | B98: Cartão de Débito | C98: =C95*$A$98 -> 0 | AE98: =AE95*$A$84 -> 0 | AF98: =AF95*$A$84 -> 0 | AG98: =AG95*$A$84 -> 0 | AH98: =AH95*$A$84 -> 0
A99: =71.058%+0.015% -> 0.71073 | B99: Pix | C99: =C95*$A$99 -> 0 | D99: 43970.1 | AE99: =AE95*$A$85 -> 0 | AF99: =AF95*$A$85 -> 0 | AG99: =AG95*$A$85 -> 0 | AH99: =AH95*$A$85 -> 0
A100: 0 | B100: Carteira Digital KIM+ | C100: =C95*$A$100 -> 0 | AE100: =AE95*$A$86 -> 0 | AF100: =AF95*$A$86 -> 0 | AG100: =AG95*$A$86 -> 0 | AH100: =AH95*$A$86 -> 0
A101: 0.01438 | B101: Transferência | C101: =C95*$A$101 -> 0 | AE101: =AE95*$A$87 -> 0 | AF101: =AF95*$A$87 -> 0 | AG101: =AG95*$A$87 -> 0 | AH101: =AH95*$A$87 -> 0
A102: 0.00063 | B102: Depósito | C102: =C95*$A$102 -> 0 | AE102: =AE95*$A$88 -> 0 | AF102: =AF95*$A$88 -> 0 | AG102: =AG95*$A$88 -> 0 | AH102: =AH95*$A$88 -> 0
A103: 0.02081 | B103: Boleto Bancário | C103: =C95*$A$103 -> 0 | AE103: =AE95*$A$89 -> 0 | AF103: =AF95*$A$89 -> 0 | AG103: =AG95*$A$89 -> 0 | AH103: =AH95*$A$89 -> 0
B104: Receitas
A105: 0 | B105: Receita de Usuários | C105: =C95*$A$105 -> 0 | E105: =E95*$A$105 -> 0 | G105: =G95*$A$105 -> 0 | I105: =I95*$A$105 -> 0 | K105: =K95*$A$105 -> 0 | M105: =M95*$A$105 -> 0 | O105: =O95*$A$105 -> 0 | Q105: =Q95*$A$105 -> 0 | S105: =S95*$A$105 -> 0 | U105: =U95*$A$105 -> 0 | W105: =W95*$A$105 -> 0 | Y105: =Y95*$A$105 -> 0 | AA105: =AA95*$A$91 -> 0 | AB105: =AB95*$A$91 -> 0 | AC105: =AC95*$A$91 -> 0 | AD105: =AD95*$A$91 -> 0 | AE105: =AE95*$A$91 -> 0 | AF105: =AF95*$A$91 -> 0 | AG105: =AG95*$A$91 -> 0 | AH105: =AH95*$A$91 -> 0
...
